.bytecode 52.0
.source "Token.kt"
.class public com/anatawa12/jasm/tree/CharPosition
.super java/lang/Object

.annotation visible kotlin/Metadata
    mv [ = .annotation array
        I = 1
        I = 1
        I = 16
    .end annotation
    bv [ = .annotation array
        I = 1
        I = 0
        I = 3
    .end annotation
    k I = 1
    d1 [ = .annotation array
        s = "\u0000 \n\u0002\u0018\u0002\n\u0002\u0010\u0000\n\u0000\n\u0002\u0010\b\n\u0002\b\u000c\n\u0002\u0010\u000b\n\u0002\b\u0003\n\u0002\u0010\u000e\n\u0000\b\u0086\b\u0018\u00002\u00020\u0001B\u001d\u0012\u0006\u0010\u0002\u001a\u00020\u0003\u0012\u0006\u0010\u0004\u001a\u00020\u0003\u0012\u0006\u0010\u0005\u001a\u00020\u0003¢\u0006\u0002\u0010\u0006J\t\u0010\u000b\u001a\u00020\u0003HÆ\u0003J\t\u0010\u000c\u001a\u00020\u0003HÆ\u0003J\t\u0010\r\u001a\u00020\u0003HÆ\u0003J\'\u0010\u000e\u001a\u00020\u00002\b\b\u0002\u0010\u0002\u001a\u00020\u00032\b\b\u0002\u0010\u0004\u001a\u00020\u00032\b\b\u0002\u0010\u0005\u001a\u00020\u0003HÆ\u0001J\u0013\u0010\u000f\u001a\u00020\u00102\b\u0010\u0011\u001a\u0004\u0018\u00010\u0001HÖ\u0003J\t\u0010\u0012\u001a\u00020\u0003HÖ\u0001J\t\u0010\u0013\u001a\u00020\u0014HÖ\u0001R\u0011\u0010\u0005\u001a\u00020\u0003¢\u0006\b\n\u0000\u001a\u0004\b\u0007\u0010\bR\u0011\u0010\u0002\u001a\u00020\u0003¢\u0006\b\n\u0000\u001a\u0004\b\t\u0010\bR\u0011\u0010\u0004\u001a\u00020\u0003¢\u0006\b\n\u0000\u001a\u0004\b\n\u0010\b¨\u0006\u0015"
    .end annotation
    d2 [ = .annotation array
        s = "Lcom/anatawa12/jasm/tree/CharPosition;"
        s = ""
        s = "index"
        s = ""
        s = "line"
        s = "column"
        s = "(III)V"
        s = "getColumn"
        s = "()I"
        s = "getIndex"
        s = "getLine"
        s = "component1"
        s = "component2"
        s = "component3"
        s = "copy"
        s = "equals"
        s = ""
        s = "other"
        s = "hashCode"
        s = "toString"
        s = ""
        s = "jasm"
    .end annotation
.end annotation

.method public getIndex ()I
    .limit stack 1
    .limit local 1
L_0000:
    .line 11
    .var 0 is this Lcom/anatawa12/jasm/tree/CharPosition; from L_0000 to L_0005
    aload 0
    getfield com/anatawa12/jasm/tree/CharPosition/index I
    ireturn
L_0005:
.end method

.method public getLine ()I
    .limit stack 1
    .limit local 1
L_0000:
    .line 11
    .var 0 is this Lcom/anatawa12/jasm/tree/CharPosition; from L_0000 to L_0005
    aload 0
    getfield com/anatawa12/jasm/tree/CharPosition/line I
    ireturn
L_0005:
.end method

.method public getColumn ()I
    .limit stack 1
    .limit local 1
L_0000:
    .line 11
    .var 0 is this Lcom/anatawa12/jasm/tree/CharPosition; from L_0000 to L_0005
    aload 0
    getfield com/anatawa12/jasm/tree/CharPosition/column I
    ireturn
L_0005:
.end method

.method public <init> (III)V
    .limit stack 2
    .limit local 4
L_0000:
    .line 11
    .var 0 is this Lcom/anatawa12/jasm/tree/CharPosition; from L_0000 to L_000e
    .var 1 is index I from L_0000 to L_000e
    .var 2 is line I from L_0000 to L_000e
    .var 3 is column I from L_0000 to L_000e
    aload 0
    invokespecial java/lang/Object/<init> ()V
    aload 0
    iload 1
    putfield com/anatawa12/jasm/tree/CharPosition/index I
    aload 0
    iload 2
    putfield com/anatawa12/jasm/tree/CharPosition/line I
    aload 0
    iload 3
    putfield com/anatawa12/jasm/tree/CharPosition/column I
    return
L_000e:
.end method

.method public component1 ()I
    .limit stack 1
    .limit local 1
L_0000:
    .var 0 is this Lcom/anatawa12/jasm/tree/CharPosition; from L_0000 to L_0004
    aload 0
    getfield com/anatawa12/jasm/tree/CharPosition/index I
    ireturn
L_0004:
.end method

.method public component2 ()I
    .limit stack 1
    .limit local 1
L_0000:
    .var 0 is this Lcom/anatawa12/jasm/tree/CharPosition; from L_0000 to L_0004
    aload 0
    getfield com/anatawa12/jasm/tree/CharPosition/line I
    ireturn
L_0004:
.end method

.method public component3 ()I
    .limit stack 1
    .limit local 1
L_0000:
    .var 0 is this Lcom/anatawa12/jasm/tree/CharPosition; from L_0000 to L_0004
    aload 0
    getfield com/anatawa12/jasm/tree/CharPosition/column I
    ireturn
L_0004:
.end method

.method public copy (III)Lcom/anatawa12/jasm/tree/CharPosition;
    .annotation invisible org/jetbrains/annotations/NotNull
    .end annotation
    .limit stack 5
    .limit local 4
L_0000:
    .var 0 is this Lcom/anatawa12/jasm/tree/CharPosition; from L_0000 to L_0008
    .var 1 is index I from L_0000 to L_0008
    .var 2 is line I from L_0000 to L_0008
    .var 3 is column I from L_0000 to L_0008
    new com/anatawa12/jasm/tree/CharPosition
    dup
    iload 1
    iload 2
    iload 3
    invokespecial com/anatawa12/jasm/tree/CharPosition/<init> (III)V
    areturn
L_0008:
.end method

.method public copy$default (Lcom/anatawa12/jasm/tree/CharPosition;IIIILjava/lang/Object;)Lcom/anatawa12/jasm/tree/CharPosition;
    .limit stack 4
    .limit local 6
    iload 4
    iconst_1
    iand
    ifeq L_0007
    aload 0
    getfield com/anatawa12/jasm/tree/CharPosition/index I
    istore 1
L_0007:
    .stack
        locals Object com/anatawa12/jasm/tree/CharPosition
        locals Integer
        locals Integer
        locals Integer
        locals Integer
        locals Object java/lang/Object
    .end stack
    iload 4
    iconst_2
    iand
    ifeq L_0010
    aload 0
    getfield com/anatawa12/jasm/tree/CharPosition/line I
    istore 2
L_0010:
    .stack use locals
    .end stack
    iload 4
    iconst_4
    iand
    ifeq L_0019
    aload 0
    getfield com/anatawa12/jasm/tree/CharPosition/column I
    istore 3
L_0019:
    .stack use locals
    .end stack
    aload 0
    iload 1
    iload 2
    iload 3
    invokevirtual com/anatawa12/jasm/tree/CharPosition/copy (III)Lcom/anatawa12/jasm/tree/CharPosition;
    areturn
.end method

.method public toString ()Ljava/lang/String;
    .annotation invisible org/jetbrains/annotations/NotNull
    .end annotation
    .limit stack 2
    .limit local 1
    new java/lang/StringBuilder
    dup
    invokespecial java/lang/StringBuilder/<init> ()V
    ldc "CharPosition(index="
    invokevirtual java/lang/StringBuilder/append (Ljava/lang/String;)Ljava/lang/StringBuilder;
    aload 0
    getfield com/anatawa12/jasm/tree/CharPosition/index I
    invokevirtual java/lang/StringBuilder/append (I)Ljava/lang/StringBuilder;
    ldc ", line="
    invokevirtual java/lang/StringBuilder/append (Ljava/lang/String;)Ljava/lang/StringBuilder;
    aload 0
    getfield com/anatawa12/jasm/tree/CharPosition/line I
    invokevirtual java/lang/StringBuilder/append (I)Ljava/lang/StringBuilder;
    ldc ", column="
    invokevirtual java/lang/StringBuilder/append (Ljava/lang/String;)Ljava/lang/StringBuilder;
    aload 0
    getfield com/anatawa12/jasm/tree/CharPosition/column I
    invokevirtual java/lang/StringBuilder/append (I)Ljava/lang/StringBuilder;
    ldc ")"
    invokevirtual java/lang/StringBuilder/append (Ljava/lang/String;)Ljava/lang/StringBuilder;
    invokevirtual java/lang/StringBuilder/toString ()Ljava/lang/String;
    areturn
.end method

.method public hashCode ()I
    .limit stack 2
    .limit local 1
    aload 0
    getfield com/anatawa12/jasm/tree/CharPosition/index I
    invokestatic java/lang/Integer/hashCode (I)I
    bipush 31
    imul
    aload 0
    getfield com/anatawa12/jasm/tree/CharPosition/line I
    invokestatic java/lang/Integer/hashCode (I)I
    iadd
    bipush 31
    imul
    aload 0
    getfield com/anatawa12/jasm/tree/CharPosition/column I
    invokestatic java/lang/Integer/hashCode (I)I
    iadd
    ireturn
.end method

.method public equals (Ljava/lang/Object;)Z
    .annotation invisiblepararm 0 org/jetbrains/annotations/Nullable
    .end annotation
    .limit stack 2
    .limit local 3
    aload 0
    aload 1
    if_acmpeq L_0018
    aload 1
    instanceof com/anatawa12/jasm/tree/CharPosition
    ifeq L_001c
    aload 1
    checkcast com/anatawa12/jasm/tree/CharPosition
    astore 2
    aload 0
    getfield com/anatawa12/jasm/tree/CharPosition/index I
    aload 2
    getfield com/anatawa12/jasm/tree/CharPosition/index I
    if_icmpne L_001c
    aload 0
    getfield com/anatawa12/jasm/tree/CharPosition/line I
    aload 2
    getfield com/anatawa12/jasm/tree/CharPosition/line I
    if_icmpne L_001c
    aload 0
    getfield com/anatawa12/jasm/tree/CharPosition/column I
    aload 2
    getfield com/anatawa12/jasm/tree/CharPosition/column I
    if_icmpne L_001c
L_0018:
    .stack
        locals Object com/anatawa12/jasm/tree/CharPosition
        locals Object java/lang/Object
    .end stack
    iconst_1
    ireturn
L_001c:
    .stack use locals
    .end stack
    iconst_0
    ireturn
.end method

.field private index I
.end field

.field private line I
.end field

.field private column I
.end field

