.bytecode 52.0
.source "ClassHeader.kt"
.class public com/anatawa12/jasm/tree/EnclosingMethodDirective
.super com/anatawa12/jasm/tree/EnclosingDirective

.annotation visible kotlin/Metadata
   mv [ = .annotation array
      I = 1
      I = 1
      I = 16
   .end annotation
   bv [ = .annotation array
      I = 1
      I = 0
      I = 3
   .end annotation
   k I = 1
   d1 [ = .annotation array
      s = "\u0000&\n\u0002\u0018\u0002\n\u0002\u0018\u0002\n\u0000\n\u0002\u0010\u000e\n\u0002\b\u000c\n\u0002\u0010\u000b\n\u0000\n\u0002\u0010\u0000\n\u0000\n\u0002\u0010\b\n\u0002\b\u0002\b\u0086\b\u0018\u00002\u00020\u0001B\u001d\u0012\u0006\u0010\u0002\u001a\u00020\u0003\u0012\u0006\u0010\u0004\u001a\u00020\u0003\u0012\u0006\u0010\u0005\u001a\u00020\u0003¢\u0006\u0002\u0010\u0006J\t\u0010\u000b\u001a\u00020\u0003HÆ\u0003J\t\u0010\u000c\u001a\u00020\u0003HÆ\u0003J\t\u0010\r\u001a\u00020\u0003HÆ\u0003J\'\u0010\u000e\u001a\u00020\u00002\b\b\u0002\u0010\u0002\u001a\u00020\u00032\b\b\u0002\u0010\u0004\u001a\u00020\u00032\b\b\u0002\u0010\u0005\u001a\u00020\u0003HÆ\u0001J\u0013\u0010\u000f\u001a\u00020\u00102\b\u0010\u0011\u001a\u0004\u0018\u00010\u0012HÖ\u0003J\t\u0010\u0013\u001a\u00020\u0014HÖ\u0001J\t\u0010\u0015\u001a\u00020\u0003HÖ\u0001R\u0011\u0010\u0005\u001a\u00020\u0003¢\u0006\b\n\u0000\u001a\u0004\b\u0007\u0010\bR\u0011\u0010\u0004\u001a\u00020\u0003¢\u0006\b\n\u0000\u001a\u0004\b\t\u0010\bR\u0014\u0010\u0002\u001a\u00020\u0003X\u0096\u0004¢\u0006\b\n\u0000\u001a\u0004\b\n\u0010\b¨\u0006\u0016"
   .end annotation
   d2 [ = .annotation array
      s = "Lcom/anatawa12/jasm/tree/EnclosingMethodDirective;"
      s = "Lcom/anatawa12/jasm/tree/EnclosingDirective;"
      s = "owner"
      s = ""
      s = "name"
      s = "descriptor"
      s = "(Ljava/lang/String;Ljava/lang/String;Ljava/lang/String;)V"
      s = "getDescriptor"
      s = "()Ljava/lang/String;"
      s = "getName"
      s = "getOwner"
      s = "component1"
      s = "component2"
      s = "component3"
      s = "copy"
      s = "equals"
      s = ""
      s = "other"
      s = ""
      s = "hashCode"
      s = ""
      s = "toString"
      s = "jasm"
   .end annotation
.end annotation

.method public getOwner ()Ljava/lang/String;
   .annotation invisible org/jetbrains/annotations/NotNull
   .end annotation
   .limit stack 1
   .limit local 1
L_0000:
   .line 25
   .var 0 is this Lcom/anatawa12/jasm/tree/EnclosingMethodDirective; from L_0000 to L_0005
   aload 0
   getfield com/anatawa12/jasm/tree/EnclosingMethodDirective/owner Ljava/lang/String;
   areturn
L_0005:
.end method

.method public getName ()Ljava/lang/String;
   .annotation invisible org/jetbrains/annotations/NotNull
   .end annotation
   .limit stack 1
   .limit local 1
L_0000:
   .line 25
   .var 0 is this Lcom/anatawa12/jasm/tree/EnclosingMethodDirective; from L_0000 to L_0005
   aload 0
   getfield com/anatawa12/jasm/tree/EnclosingMethodDirective/name Ljava/lang/String;
   areturn
L_0005:
.end method

.method public getDescriptor ()Ljava/lang/String;
   .annotation invisible org/jetbrains/annotations/NotNull
   .end annotation
   .limit stack 1
   .limit local 1
L_0000:
   .line 25
   .var 0 is this Lcom/anatawa12/jasm/tree/EnclosingMethodDirective; from L_0000 to L_0005
   aload 0
   getfield com/anatawa12/jasm/tree/EnclosingMethodDirective/descriptor Ljava/lang/String;
   areturn
L_0005:
.end method

.method public <init> (Ljava/lang/String;Ljava/lang/String;Ljava/lang/String;)V
   .annotation invisiblepararm 0 org/jetbrains/annotations/NotNull
   .end annotation
   .annotation invisiblepararm 1 org/jetbrains/annotations/NotNull
   .end annotation
   .annotation invisiblepararm 2 org/jetbrains/annotations/NotNull
   .end annotation
   .limit stack 2
   .limit local 4
L_0000:
   .var 0 is this Lcom/anatawa12/jasm/tree/EnclosingMethodDirective; from L_0000 to L_0019
   .var 1 is owner Ljava/lang/String; from L_0000 to L_0019
   .var 2 is name Ljava/lang/String; from L_0000 to L_0019
   .var 3 is descriptor Ljava/lang/String; from L_0000 to L_0019
   aload 1
   ldc "owner"
   invokestatic kotlin/jvm/internal/Intrinsics/checkParameterIsNotNull (Ljava/lang/Object;Ljava/lang/String;)V
   aload 2
   ldc "name"
   invokestatic kotlin/jvm/internal/Intrinsics/checkParameterIsNotNull (Ljava/lang/Object;Ljava/lang/String;)V
   aload 3
   ldc "descriptor"
   invokestatic kotlin/jvm/internal/Intrinsics/checkParameterIsNotNull (Ljava/lang/Object;Ljava/lang/String;)V
L_000a:
   .line 25
   aload 0
   aconst_null
   invokespecial com/anatawa12/jasm/tree/EnclosingDirective/<init> (Lkotlin/jvm/internal/DefaultConstructorMarker;)V
   aload 0
   aload 1
   putfield com/anatawa12/jasm/tree/EnclosingMethodDirective/owner Ljava/lang/String;
   aload 0
   aload 2
   putfield com/anatawa12/jasm/tree/EnclosingMethodDirective/name Ljava/lang/String;
   aload 0
   aload 3
   putfield com/anatawa12/jasm/tree/EnclosingMethodDirective/descriptor Ljava/lang/String;
   return
L_0019:
.end method

.method public component1 ()Ljava/lang/String;
   .annotation invisible org/jetbrains/annotations/NotNull
   .end annotation
   .limit stack 1
   .limit local 1
L_0000:
   .var 0 is this Lcom/anatawa12/jasm/tree/EnclosingMethodDirective; from L_0000 to L_0004
   aload 0
   invokevirtual com/anatawa12/jasm/tree/EnclosingMethodDirective/getOwner ()Ljava/lang/String;
   areturn
L_0004:
.end method

.method public component2 ()Ljava/lang/String;
   .annotation invisible org/jetbrains/annotations/NotNull
   .end annotation
   .limit stack 1
   .limit local 1
L_0000:
   .var 0 is this Lcom/anatawa12/jasm/tree/EnclosingMethodDirective; from L_0000 to L_0004
   aload 0
   getfield com/anatawa12/jasm/tree/EnclosingMethodDirective/name Ljava/lang/String;
   areturn
L_0004:
.end method

.method public component3 ()Ljava/lang/String;
   .annotation invisible org/jetbrains/annotations/NotNull
   .end annotation
   .limit stack 1
   .limit local 1
L_0000:
   .var 0 is this Lcom/anatawa12/jasm/tree/EnclosingMethodDirective; from L_0000 to L_0004
   aload 0
   getfield com/anatawa12/jasm/tree/EnclosingMethodDirective/descriptor Ljava/lang/String;
   areturn
L_0004:
.end method

.method public copy (Ljava/lang/String;Ljava/lang/String;Ljava/lang/String;)Lcom/anatawa12/jasm/tree/EnclosingMethodDirective;
   .annotation invisible org/jetbrains/annotations/NotNull
   .end annotation
   .annotation invisiblepararm 0 org/jetbrains/annotations/NotNull
   .end annotation
   .annotation invisiblepararm 1 org/jetbrains/annotations/NotNull
   .end annotation
   .annotation invisiblepararm 2 org/jetbrains/annotations/NotNull
   .end annotation
   .limit stack 5
   .limit local 4
L_0000:
   .var 0 is this Lcom/anatawa12/jasm/tree/EnclosingMethodDirective; from L_0000 to L_0011
   .var 1 is owner Ljava/lang/String; from L_0000 to L_0011
   .var 2 is name Ljava/lang/String; from L_0000 to L_0011
   .var 3 is descriptor Ljava/lang/String; from L_0000 to L_0011
   aload 1
   ldc "owner"
   invokestatic kotlin/jvm/internal/Intrinsics/checkParameterIsNotNull (Ljava/lang/Object;Ljava/lang/String;)V
   aload 2
   ldc "name"
   invokestatic kotlin/jvm/internal/Intrinsics/checkParameterIsNotNull (Ljava/lang/Object;Ljava/lang/String;)V
   aload 3
   ldc "descriptor"
   invokestatic kotlin/jvm/internal/Intrinsics/checkParameterIsNotNull (Ljava/lang/Object;Ljava/lang/String;)V
   new com/anatawa12/jasm/tree/EnclosingMethodDirective
   dup
   aload 1
   aload 2
   aload 3
   invokespecial com/anatawa12/jasm/tree/EnclosingMethodDirective/<init> (Ljava/lang/String;Ljava/lang/String;Ljava/lang/String;)V
   areturn
L_0011:
.end method

.method public copy$default (Lcom/anatawa12/jasm/tree/EnclosingMethodDirective;Ljava/lang/String;Ljava/lang/String;Ljava/lang/String;ILjava/lang/Object;)Lcom/anatawa12/jasm/tree/EnclosingMethodDirective;
   .limit stack 4
   .limit local 6
   iload 4
   iconst_1
   iand
   ifeq L_0007
   aload 0
   invokevirtual com/anatawa12/jasm/tree/EnclosingMethodDirective/getOwner ()Ljava/lang/String;
   astore 1
L_0007:
   .stack
      locals Object com/anatawa12/jasm/tree/EnclosingMethodDirective
      locals Object java/lang/String
      locals Object java/lang/String
      locals Object java/lang/String
      locals Integer
      locals Object java/lang/Object
   .end stack
   iload 4
   iconst_2
   iand
   ifeq L_0010
   aload 0
   getfield com/anatawa12/jasm/tree/EnclosingMethodDirective/name Ljava/lang/String;
   astore 2
L_0010:
   .stack use locals
   .end stack
   iload 4
   iconst_4
   iand
   ifeq L_0019
   aload 0
   getfield com/anatawa12/jasm/tree/EnclosingMethodDirective/descriptor Ljava/lang/String;
   astore 3
L_0019:
   .stack use locals
   .end stack
   aload 0
   aload 1
   aload 2
   aload 3
   invokevirtual com/anatawa12/jasm/tree/EnclosingMethodDirective/copy (Ljava/lang/String;Ljava/lang/String;Ljava/lang/String;)Lcom/anatawa12/jasm/tree/EnclosingMethodDirective;
   areturn
.end method

.method public toString ()Ljava/lang/String;
   .annotation invisible org/jetbrains/annotations/NotNull
   .end annotation
   .limit stack 2
   .limit local 1
   new java/lang/StringBuilder
   dup
   invokespecial java/lang/StringBuilder/<init> ()V
   ldc "EnclosingMethodDirective(owner="
   invokevirtual java/lang/StringBuilder/append (Ljava/lang/String;)Ljava/lang/StringBuilder;
   aload 0
   invokevirtual com/anatawa12/jasm/tree/EnclosingMethodDirective/getOwner ()Ljava/lang/String;
   invokevirtual java/lang/StringBuilder/append (Ljava/lang/String;)Ljava/lang/StringBuilder;
   ldc ", name="
   invokevirtual java/lang/StringBuilder/append (Ljava/lang/String;)Ljava/lang/StringBuilder;
   aload 0
   getfield com/anatawa12/jasm/tree/EnclosingMethodDirective/name Ljava/lang/String;
   invokevirtual java/lang/StringBuilder/append (Ljava/lang/String;)Ljava/lang/StringBuilder;
   ldc ", descriptor="
   invokevirtual java/lang/StringBuilder/append (Ljava/lang/String;)Ljava/lang/StringBuilder;
   aload 0
   getfield com/anatawa12/jasm/tree/EnclosingMethodDirective/descriptor Ljava/lang/String;
   invokevirtual java/lang/StringBuilder/append (Ljava/lang/String;)Ljava/lang/StringBuilder;
   ldc ")"
   invokevirtual java/lang/StringBuilder/append (Ljava/lang/String;)Ljava/lang/StringBuilder;
   invokevirtual java/lang/StringBuilder/toString ()Ljava/lang/String;
   areturn
.end method

.method public hashCode ()I
   .limit stack 3
   .limit local 1
   aload 0
   invokevirtual com/anatawa12/jasm/tree/EnclosingMethodDirective/getOwner ()Ljava/lang/String;
   dup
   ifnull L_0006
   invokevirtual java/lang/Object/hashCode ()I
   goto L_000a
L_0006:
   .stack
      locals Object com/anatawa12/jasm/tree/EnclosingMethodDirective
      stacks Object java/lang/String
   .end stack
   pop
   iconst_0
L_000a:
   .stack use locals
      stacks Integer
   .end stack
   bipush 31
   imul
   aload 0
   getfield com/anatawa12/jasm/tree/EnclosingMethodDirective/name Ljava/lang/String;
   dup
   ifnull L_0014
   invokevirtual java/lang/Object/hashCode ()I
   goto L_0018
L_0014:
   .stack use locals
      stacks Integer
      stacks Object java/lang/String
   .end stack
   pop
   iconst_0
L_0018:
   .stack use locals
      stacks Integer
      stacks Integer
   .end stack
   iadd
   bipush 31
   imul
   aload 0
   getfield com/anatawa12/jasm/tree/EnclosingMethodDirective/descriptor Ljava/lang/String;
   dup
   ifnull L_0023
   invokevirtual java/lang/Object/hashCode ()I
   goto L_0027
L_0023:
   .stack use locals
      stacks Integer
      stacks Object java/lang/String
   .end stack
   pop
   iconst_0
L_0027:
   .stack use locals
      stacks Integer
      stacks Integer
   .end stack
   iadd
   ireturn
.end method

.method public equals (Ljava/lang/Object;)Z
   .annotation invisiblepararm 0 org/jetbrains/annotations/Nullable
   .end annotation
   .limit stack 2
   .limit local 3
   aload 0
   aload 1
   if_acmpeq L_001b
   aload 1
   instanceof com/anatawa12/jasm/tree/EnclosingMethodDirective
   ifeq L_001f
   aload 1
   checkcast com/anatawa12/jasm/tree/EnclosingMethodDirective
   astore 2
   aload 0
   invokevirtual com/anatawa12/jasm/tree/EnclosingMethodDirective/getOwner ()Ljava/lang/String;
   aload 2
   invokevirtual com/anatawa12/jasm/tree/EnclosingMethodDirective/getOwner ()Ljava/lang/String;
   invokestatic kotlin/jvm/internal/Intrinsics/areEqual (Ljava/lang/Object;Ljava/lang/Object;)Z
   ifeq L_001f
   aload 0
   getfield com/anatawa12/jasm/tree/EnclosingMethodDirective/name Ljava/lang/String;
   aload 2
   getfield com/anatawa12/jasm/tree/EnclosingMethodDirective/name Ljava/lang/String;
   invokestatic kotlin/jvm/internal/Intrinsics/areEqual (Ljava/lang/Object;Ljava/lang/Object;)Z
   ifeq L_001f
   aload 0
   getfield com/anatawa12/jasm/tree/EnclosingMethodDirective/descriptor Ljava/lang/String;
   aload 2
   getfield com/anatawa12/jasm/tree/EnclosingMethodDirective/descriptor Ljava/lang/String;
   invokestatic kotlin/jvm/internal/Intrinsics/areEqual (Ljava/lang/Object;Ljava/lang/Object;)Z
   ifeq L_001f
L_001b:
   .stack
      locals Object com/anatawa12/jasm/tree/EnclosingMethodDirective
      locals Object java/lang/Object
   .end stack
   iconst_1
   ireturn
L_001f:
   .stack use locals
   .end stack
   iconst_0
   ireturn
.end method

.field private owner Ljava/lang/String;
   .annotation invisible org/jetbrains/annotations/NotNull
   .end annotation
.end field

.field private name Ljava/lang/String;
   .annotation invisible org/jetbrains/annotations/NotNull
   .end annotation
.end field

.field private descriptor Ljava/lang/String;
   .annotation invisible org/jetbrains/annotations/NotNull
   .end annotation
.end field

