.bytecode 52.0
.source "ClassHeader.kt"
.class public com/anatawa12/jasm/tree/InnerClassDirective
.super com/anatawa12/jasm/tree/BranchNode

.annotation visible kotlin/Metadata
   mv [ = .annotation array
      I = 1
      I = 1
      I = 16
   .end annotation
   bv [ = .annotation array
      I = 1
      I = 0
      I = 3
   .end annotation
   k I = 1
   d1 [ = .annotation array
      s = "\u0000,\n\u0002\u0018\u0002\n\u0002\u0018\u0002\n\u0000\n\u0002\u0018\u0002\n\u0000\n\u0002\u0010\u000e\n\u0002\b\u000f\n\u0002\u0010\u000b\n\u0000\n\u0002\u0010\u0000\n\u0000\n\u0002\u0010\b\n\u0002\b\u0002\b\u0086\b\u0018\u00002\u00020\u0001B)\u0012\u0006\u0010\u0002\u001a\u00020\u0003\u0012\u0006\u0010\u0004\u001a\u00020\u0005\u0012\b\u0010\u0006\u001a\u0004\u0018\u00010\u0005\u0012\b\u0010\u0007\u001a\u0004\u0018\u00010\u0005¢\u0006\u0002\u0010\bJ\t\u0010\u000f\u001a\u00020\u0003HÆ\u0003J\t\u0010\u0010\u001a\u00020\u0005HÆ\u0003J\u000b\u0010\u0011\u001a\u0004\u0018\u00010\u0005HÆ\u0003J\u000b\u0010\u0012\u001a\u0004\u0018\u00010\u0005HÆ\u0003J5\u0010\u0013\u001a\u00020\u00002\b\b\u0002\u0010\u0002\u001a\u00020\u00032\b\b\u0002\u0010\u0004\u001a\u00020\u00052\n\b\u0002\u0010\u0006\u001a\u0004\u0018\u00010\u00052\n\b\u0002\u0010\u0007\u001a\u0004\u0018\u00010\u0005HÆ\u0001J\u0013\u0010\u0014\u001a\u00020\u00152\b\u0010\u0016\u001a\u0004\u0018\u00010\u0017HÖ\u0003J\t\u0010\u0018\u001a\u00020\u0019HÖ\u0001J\t\u0010\u001a\u001a\u00020\u0005HÖ\u0001R\u0011\u0010\u0002\u001a\u00020\u0003¢\u0006\b\n\u0000\u001a\u0004\b\t\u0010\nR\u0013\u0010\u0007\u001a\u0004\u0018\u00010\u0005¢\u0006\b\n\u0000\u001a\u0004\b\u000b\u0010\u000cR\u0011\u0010\u0004\u001a\u00020\u0005¢\u0006\b\n\u0000\u001a\u0004\b\r\u0010\u000cR\u0013\u0010\u0006\u001a\u0004\u0018\u00010\u0005¢\u0006\b\n\u0000\u001a\u0004\b\u000e\u0010\u000c¨\u0006\u001b"
   .end annotation
   d2 [ = .annotation array
      s = "Lcom/anatawa12/jasm/tree/InnerClassDirective;"
      s = "Lcom/anatawa12/jasm/tree/BranchNode;"
      s = "accessFlags"
      s = "Lcom/anatawa12/jasm/tree/AccessFlags;"
      s = "name"
      s = ""
      s = "outerName"
      s = "innerName"
      s = "(Lcom/anatawa12/jasm/tree/AccessFlags;Ljava/lang/String;Ljava/lang/String;Ljava/lang/String;)V"
      s = "getAccessFlags"
      s = "()Lcom/anatawa12/jasm/tree/AccessFlags;"
      s = "getInnerName"
      s = "()Ljava/lang/String;"
      s = "getName"
      s = "getOuterName"
      s = "component1"
      s = "component2"
      s = "component3"
      s = "component4"
      s = "copy"
      s = "equals"
      s = ""
      s = "other"
      s = ""
      s = "hashCode"
      s = ""
      s = "toString"
      s = "jasm"
   .end annotation
.end annotation

.method public getAccessFlags ()Lcom/anatawa12/jasm/tree/AccessFlags;
   .annotation invisible org/jetbrains/annotations/NotNull
   .end annotation
   .limit stack 1
   .limit local 1
L_0000:
   .line 27
   .var 0 is this Lcom/anatawa12/jasm/tree/InnerClassDirective; from L_0000 to L_0005
   aload 0
   getfield com/anatawa12/jasm/tree/InnerClassDirective/accessFlags Lcom/anatawa12/jasm/tree/AccessFlags;
   areturn
L_0005:
.end method

.method public getName ()Ljava/lang/String;
   .annotation invisible org/jetbrains/annotations/NotNull
   .end annotation
   .limit stack 1
   .limit local 1
L_0000:
   .line 27
   .var 0 is this Lcom/anatawa12/jasm/tree/InnerClassDirective; from L_0000 to L_0005
   aload 0
   getfield com/anatawa12/jasm/tree/InnerClassDirective/name Ljava/lang/String;
   areturn
L_0005:
.end method

.method public getOuterName ()Ljava/lang/String;
   .annotation invisible org/jetbrains/annotations/Nullable
   .end annotation
   .limit stack 1
   .limit local 1
L_0000:
   .line 27
   .var 0 is this Lcom/anatawa12/jasm/tree/InnerClassDirective; from L_0000 to L_0005
   aload 0
   getfield com/anatawa12/jasm/tree/InnerClassDirective/outerName Ljava/lang/String;
   areturn
L_0005:
.end method

.method public getInnerName ()Ljava/lang/String;
   .annotation invisible org/jetbrains/annotations/Nullable
   .end annotation
   .limit stack 1
   .limit local 1
L_0000:
   .line 27
   .var 0 is this Lcom/anatawa12/jasm/tree/InnerClassDirective; from L_0000 to L_0005
   aload 0
   getfield com/anatawa12/jasm/tree/InnerClassDirective/innerName Ljava/lang/String;
   areturn
L_0005:
.end method

.method public <init> (Lcom/anatawa12/jasm/tree/AccessFlags;Ljava/lang/String;Ljava/lang/String;Ljava/lang/String;)V
   .annotation invisiblepararm 0 org/jetbrains/annotations/NotNull
   .end annotation
   .annotation invisiblepararm 1 org/jetbrains/annotations/NotNull
   .end annotation
   .annotation invisiblepararm 2 org/jetbrains/annotations/Nullable
   .end annotation
   .annotation invisiblepararm 3 org/jetbrains/annotations/Nullable
   .end annotation
   .limit stack 2
   .limit local 5
L_0000:
   .var 0 is this Lcom/anatawa12/jasm/tree/InnerClassDirective; from L_0000 to L_0018
   .var 1 is accessFlags Lcom/anatawa12/jasm/tree/AccessFlags; from L_0000 to L_0018
   .var 2 is name Ljava/lang/String; from L_0000 to L_0018
   .var 3 is outerName Ljava/lang/String; from L_0000 to L_0018
   .var 4 is innerName Ljava/lang/String; from L_0000 to L_0018
   aload 1
   ldc "accessFlags"
   invokestatic kotlin/jvm/internal/Intrinsics/checkParameterIsNotNull (Ljava/lang/Object;Ljava/lang/String;)V
   aload 2
   ldc "name"
   invokestatic kotlin/jvm/internal/Intrinsics/checkParameterIsNotNull (Ljava/lang/Object;Ljava/lang/String;)V
L_0007:
   .line 27
   aload 0
   invokespecial com/anatawa12/jasm/tree/BranchNode/<init> ()V
   aload 0
   aload 1
   putfield com/anatawa12/jasm/tree/InnerClassDirective/accessFlags Lcom/anatawa12/jasm/tree/AccessFlags;
   aload 0
   aload 2
   putfield com/anatawa12/jasm/tree/InnerClassDirective/name Ljava/lang/String;
   aload 0
   aload 3
   putfield com/anatawa12/jasm/tree/InnerClassDirective/outerName Ljava/lang/String;
   aload 0
   aload 4
   putfield com/anatawa12/jasm/tree/InnerClassDirective/innerName Ljava/lang/String;
   return
L_0018:
.end method

.method public component1 ()Lcom/anatawa12/jasm/tree/AccessFlags;
   .annotation invisible org/jetbrains/annotations/NotNull
   .end annotation
   .limit stack 1
   .limit local 1
L_0000:
   .var 0 is this Lcom/anatawa12/jasm/tree/InnerClassDirective; from L_0000 to L_0004
   aload 0
   getfield com/anatawa12/jasm/tree/InnerClassDirective/accessFlags Lcom/anatawa12/jasm/tree/AccessFlags;
   areturn
L_0004:
.end method

.method public component2 ()Ljava/lang/String;
   .annotation invisible org/jetbrains/annotations/NotNull
   .end annotation
   .limit stack 1
   .limit local 1
L_0000:
   .var 0 is this Lcom/anatawa12/jasm/tree/InnerClassDirective; from L_0000 to L_0004
   aload 0
   getfield com/anatawa12/jasm/tree/InnerClassDirective/name Ljava/lang/String;
   areturn
L_0004:
.end method

.method public component3 ()Ljava/lang/String;
   .annotation invisible org/jetbrains/annotations/Nullable
   .end annotation
   .limit stack 1
   .limit local 1
L_0000:
   .var 0 is this Lcom/anatawa12/jasm/tree/InnerClassDirective; from L_0000 to L_0004
   aload 0
   getfield com/anatawa12/jasm/tree/InnerClassDirective/outerName Ljava/lang/String;
   areturn
L_0004:
.end method

.method public component4 ()Ljava/lang/String;
   .annotation invisible org/jetbrains/annotations/Nullable
   .end annotation
   .limit stack 1
   .limit local 1
L_0000:
   .var 0 is this Lcom/anatawa12/jasm/tree/InnerClassDirective; from L_0000 to L_0004
   aload 0
   getfield com/anatawa12/jasm/tree/InnerClassDirective/innerName Ljava/lang/String;
   areturn
L_0004:
.end method

.method public copy (Lcom/anatawa12/jasm/tree/AccessFlags;Ljava/lang/String;Ljava/lang/String;Ljava/lang/String;)Lcom/anatawa12/jasm/tree/InnerClassDirective;
   .annotation invisible org/jetbrains/annotations/NotNull
   .end annotation
   .annotation invisiblepararm 0 org/jetbrains/annotations/NotNull
   .end annotation
   .annotation invisiblepararm 1 org/jetbrains/annotations/NotNull
   .end annotation
   .annotation invisiblepararm 2 org/jetbrains/annotations/Nullable
   .end annotation
   .annotation invisiblepararm 3 org/jetbrains/annotations/Nullable
   .end annotation
   .limit stack 6
   .limit local 5
L_0000:
   .var 0 is this Lcom/anatawa12/jasm/tree/InnerClassDirective; from L_0000 to L_000f
   .var 1 is accessFlags Lcom/anatawa12/jasm/tree/AccessFlags; from L_0000 to L_000f
   .var 2 is name Ljava/lang/String; from L_0000 to L_000f
   .var 3 is outerName Ljava/lang/String; from L_0000 to L_000f
   .var 4 is innerName Ljava/lang/String; from L_0000 to L_000f
   aload 1
   ldc "accessFlags"
   invokestatic kotlin/jvm/internal/Intrinsics/checkParameterIsNotNull (Ljava/lang/Object;Ljava/lang/String;)V
   aload 2
   ldc "name"
   invokestatic kotlin/jvm/internal/Intrinsics/checkParameterIsNotNull (Ljava/lang/Object;Ljava/lang/String;)V
   new com/anatawa12/jasm/tree/InnerClassDirective
   dup
   aload 1
   aload 2
   aload 3
   aload 4
   invokespecial com/anatawa12/jasm/tree/InnerClassDirective/<init> (Lcom/anatawa12/jasm/tree/AccessFlags;Ljava/lang/String;Ljava/lang/String;Ljava/lang/String;)V
   areturn
L_000f:
.end method

.method public copy$default (Lcom/anatawa12/jasm/tree/InnerClassDirective;Lcom/anatawa12/jasm/tree/AccessFlags;Ljava/lang/String;Ljava/lang/String;Ljava/lang/String;ILjava/lang/Object;)Lcom/anatawa12/jasm/tree/InnerClassDirective;
   .limit stack 5
   .limit local 7
   iload 5
   iconst_1
   iand
   ifeq L_0007
   aload 0
   getfield com/anatawa12/jasm/tree/InnerClassDirective/accessFlags Lcom/anatawa12/jasm/tree/AccessFlags;
   astore 1
L_0007:
   .stack
      locals Object com/anatawa12/jasm/tree/InnerClassDirective
      locals Object com/anatawa12/jasm/tree/AccessFlags
      locals Object java/lang/String
      locals Object java/lang/String
      locals Object java/lang/String
      locals Integer
      locals Object java/lang/Object
   .end stack
   iload 5
   iconst_2
   iand
   ifeq L_0010
   aload 0
   getfield com/anatawa12/jasm/tree/InnerClassDirective/name Ljava/lang/String;
   astore 2
L_0010:
   .stack use locals
   .end stack
   iload 5
   iconst_4
   iand
   ifeq L_0019
   aload 0
   getfield com/anatawa12/jasm/tree/InnerClassDirective/outerName Ljava/lang/String;
   astore 3
L_0019:
   .stack use locals
   .end stack
   iload 5
   bipush 8
   iand
   ifeq L_0022
   aload 0
   getfield com/anatawa12/jasm/tree/InnerClassDirective/innerName Ljava/lang/String;
   astore 4
L_0022:
   .stack use locals
   .end stack
   aload 0
   aload 1
   aload 2
   aload 3
   aload 4
   invokevirtual com/anatawa12/jasm/tree/InnerClassDirective/copy (Lcom/anatawa12/jasm/tree/AccessFlags;Ljava/lang/String;Ljava/lang/String;Ljava/lang/String;)Lcom/anatawa12/jasm/tree/InnerClassDirective;
   areturn
.end method

.method public toString ()Ljava/lang/String;
   .annotation invisible org/jetbrains/annotations/NotNull
   .end annotation
   .limit stack 2
   .limit local 1
   new java/lang/StringBuilder
   dup
   invokespecial java/lang/StringBuilder/<init> ()V
   ldc "InnerClassDirective(accessFlags="
   invokevirtual java/lang/StringBuilder/append (Ljava/lang/String;)Ljava/lang/StringBuilder;
   aload 0
   getfield com/anatawa12/jasm/tree/InnerClassDirective/accessFlags Lcom/anatawa12/jasm/tree/AccessFlags;
   invokevirtual java/lang/StringBuilder/append (Ljava/lang/Object;)Ljava/lang/StringBuilder;
   ldc ", name="
   invokevirtual java/lang/StringBuilder/append (Ljava/lang/String;)Ljava/lang/StringBuilder;
   aload 0
   getfield com/anatawa12/jasm/tree/InnerClassDirective/name Ljava/lang/String;
   invokevirtual java/lang/StringBuilder/append (Ljava/lang/String;)Ljava/lang/StringBuilder;
   ldc ", outerName="
   invokevirtual java/lang/StringBuilder/append (Ljava/lang/String;)Ljava/lang/StringBuilder;
   aload 0
   getfield com/anatawa12/jasm/tree/InnerClassDirective/outerName Ljava/lang/String;
   invokevirtual java/lang/StringBuilder/append (Ljava/lang/String;)Ljava/lang/StringBuilder;
   ldc ", innerName="
   invokevirtual java/lang/StringBuilder/append (Ljava/lang/String;)Ljava/lang/StringBuilder;
   aload 0
   getfield com/anatawa12/jasm/tree/InnerClassDirective/innerName Ljava/lang/String;
   invokevirtual java/lang/StringBuilder/append (Ljava/lang/String;)Ljava/lang/StringBuilder;
   ldc ")"
   invokevirtual java/lang/StringBuilder/append (Ljava/lang/String;)Ljava/lang/StringBuilder;
   invokevirtual java/lang/StringBuilder/toString ()Ljava/lang/String;
   areturn
.end method

.method public hashCode ()I
   .limit stack 3
   .limit local 1
   aload 0
   getfield com/anatawa12/jasm/tree/InnerClassDirective/accessFlags Lcom/anatawa12/jasm/tree/AccessFlags;
   dup
   ifnull L_0006
   invokevirtual java/lang/Object/hashCode ()I
   goto L_000a
L_0006:
   .stack
      locals Object com/anatawa12/jasm/tree/InnerClassDirective
      stacks Object com/anatawa12/jasm/tree/AccessFlags
   .end stack
   pop
   iconst_0
L_000a:
   .stack use locals
      stacks Integer
   .end stack
   bipush 31
   imul
   aload 0
   getfield com/anatawa12/jasm/tree/InnerClassDirective/name Ljava/lang/String;
   dup
   ifnull L_0014
   invokevirtual java/lang/Object/hashCode ()I
   goto L_0018
L_0014:
   .stack use locals
      stacks Integer
      stacks Object java/lang/String
   .end stack
   pop
   iconst_0
L_0018:
   .stack use locals
      stacks Integer
      stacks Integer
   .end stack
   iadd
   bipush 31
   imul
   aload 0
   getfield com/anatawa12/jasm/tree/InnerClassDirective/outerName Ljava/lang/String;
   dup
   ifnull L_0023
   invokevirtual java/lang/Object/hashCode ()I
   goto L_0027
L_0023:
   .stack use locals
      stacks Integer
      stacks Object java/lang/String
   .end stack
   pop
   iconst_0
L_0027:
   .stack use locals
      stacks Integer
      stacks Integer
   .end stack
   iadd
   bipush 31
   imul
   aload 0
   getfield com/anatawa12/jasm/tree/InnerClassDirective/innerName Ljava/lang/String;
   dup
   ifnull L_0032
   invokevirtual java/lang/Object/hashCode ()I
   goto L_0036
L_0032:
   .stack use locals
      stacks Integer
      stacks Object java/lang/String
   .end stack
   pop
   iconst_0
L_0036:
   .stack use locals
      stacks Integer
      stacks Integer
   .end stack
   iadd
   ireturn
.end method

.method public equals (Ljava/lang/Object;)Z
   .annotation invisiblepararm 0 org/jetbrains/annotations/Nullable
   .end annotation
   .limit stack 2
   .limit local 3
   aload 0
   aload 1
   if_acmpeq L_0021
   aload 1
   instanceof com/anatawa12/jasm/tree/InnerClassDirective
   ifeq L_0025
   aload 1
   checkcast com/anatawa12/jasm/tree/InnerClassDirective
   astore 2
   aload 0
   getfield com/anatawa12/jasm/tree/InnerClassDirective/accessFlags Lcom/anatawa12/jasm/tree/AccessFlags;
   aload 2
   getfield com/anatawa12/jasm/tree/InnerClassDirective/accessFlags Lcom/anatawa12/jasm/tree/AccessFlags;
   invokestatic kotlin/jvm/internal/Intrinsics/areEqual (Ljava/lang/Object;Ljava/lang/Object;)Z
   ifeq L_0025
   aload 0
   getfield com/anatawa12/jasm/tree/InnerClassDirective/name Ljava/lang/String;
   aload 2
   getfield com/anatawa12/jasm/tree/InnerClassDirective/name Ljava/lang/String;
   invokestatic kotlin/jvm/internal/Intrinsics/areEqual (Ljava/lang/Object;Ljava/lang/Object;)Z
   ifeq L_0025
   aload 0
   getfield com/anatawa12/jasm/tree/InnerClassDirective/outerName Ljava/lang/String;
   aload 2
   getfield com/anatawa12/jasm/tree/InnerClassDirective/outerName Ljava/lang/String;
   invokestatic kotlin/jvm/internal/Intrinsics/areEqual (Ljava/lang/Object;Ljava/lang/Object;)Z
   ifeq L_0025
   aload 0
   getfield com/anatawa12/jasm/tree/InnerClassDirective/innerName Ljava/lang/String;
   aload 2
   getfield com/anatawa12/jasm/tree/InnerClassDirective/innerName Ljava/lang/String;
   invokestatic kotlin/jvm/internal/Intrinsics/areEqual (Ljava/lang/Object;Ljava/lang/Object;)Z
   ifeq L_0025
L_0021:
   .stack
      locals Object com/anatawa12/jasm/tree/InnerClassDirective
      locals Object java/lang/Object
   .end stack
   iconst_1
   ireturn
L_0025:
   .stack use locals
   .end stack
   iconst_0
   ireturn
.end method

.field private accessFlags Lcom/anatawa12/jasm/tree/AccessFlags;
   .annotation invisible org/jetbrains/annotations/NotNull
   .end annotation
.end field

.field private name Ljava/lang/String;
   .annotation invisible org/jetbrains/annotations/NotNull
   .end annotation
.end field

.field private outerName Ljava/lang/String;
   .annotation invisible org/jetbrains/annotations/Nullable
   .end annotation
.end field

.field private innerName Ljava/lang/String;
   .annotation invisible org/jetbrains/annotations/Nullable
   .end annotation
.end field

