.bytecode 52.0
.source "JasmHeader.kt"
.class public com/anatawa12/jasm/tree/JasmHeader
.super com/anatawa12/jasm/tree/BranchNode

.annotation visible kotlin/Metadata
    mv [ = .annotation array
        I = 1
        I = 1
        I = 16
    .end annotation
    bv [ = .annotation array
        I = 1
        I = 0
        I = 3
    .end annotation
    k I = 1
    d1 [ = .annotation array
        s = "\u0000.\n\u0002\u0018\u0002\n\u0002\u0018\u0002\n\u0000\n\u0002\u0010 \n\u0002\u0018\u0002\n\u0002\b\u0006\n\u0002\u0010\u000b\n\u0000\n\u0002\u0010\u0000\n\u0000\n\u0002\u0010\b\n\u0000\n\u0002\u0010\u000e\n\u0000\b\u0086\b\u0018\u00002\u00020\u0001B\u0013\u0012\u000c\u0010\u0002\u001a\b\u0012\u0004\u0012\u00020\u00040\u0003¢\u0006\u0002\u0010\u0005J\u000f\u0010\b\u001a\b\u0012\u0004\u0012\u00020\u00040\u0003HÆ\u0003J\u0019\u0010\t\u001a\u00020\u00002\u000e\b\u0002\u0010\u0002\u001a\b\u0012\u0004\u0012\u00020\u00040\u0003HÆ\u0001J\u0013\u0010\n\u001a\u00020\u000b2\b\u0010\u000c\u001a\u0004\u0018\u00010\rHÖ\u0003J\t\u0010\u000e\u001a\u00020\u000fHÖ\u0001J\t\u0010\u0010\u001a\u00020\u0011HÖ\u0001R\u0017\u0010\u0002\u001a\b\u0012\u0004\u0012\u00020\u00040\u0003¢\u0006\b\n\u0000\u001a\u0004\b\u0006\u0010\u0007¨\u0006\u0012"
    .end annotation
    d2 [ = .annotation array
        s = "Lcom/anatawa12/jasm/tree/JasmHeader;"
        s = "Lcom/anatawa12/jasm/tree/BranchNode;"
        s = "elements"
        s = ""
        s = "Lcom/anatawa12/jasm/tree/JasmHeaderElement;"
        s = "(Ljava/util/List;)V"
        s = "getElements"
        s = "()Ljava/util/List;"
        s = "component1"
        s = "copy"
        s = "equals"
        s = ""
        s = "other"
        s = ""
        s = "hashCode"
        s = ""
        s = "toString"
        s = ""
        s = "jasm"
    .end annotation
.end annotation

.method public getElements ()Ljava/util/List;
    .signature "()Ljava/util/List<Lcom/anatawa12/jasm/tree/JasmHeaderElement;>;"
    .annotation invisible org/jetbrains/annotations/NotNull
    .end annotation
    .limit stack 1
    .limit local 1
L_0000:
    .line 3
    .var 0 is this Lcom/anatawa12/jasm/tree/JasmHeader; from L_0000 to L_0005
    aload 0
    getfield com/anatawa12/jasm/tree/JasmHeader/elements Ljava/util/List;
    areturn
L_0005:
.end method

.method public <init> (Ljava/util/List;)V
    .signature "(Ljava/util/List<+Lcom/anatawa12/jasm/tree/JasmHeaderElement;>;)V"
    .annotation invisiblepararm 0 org/jetbrains/annotations/NotNull
    .end annotation
    .limit stack 2
    .limit local 2
L_0000:
    .var 0 is this Lcom/anatawa12/jasm/tree/JasmHeader; from L_0000 to L_000c
    .var 1 is elements Ljava/util/List; from L_0000 to L_000c
    aload 1
    ldc "elements"
    invokestatic kotlin/jvm/internal/Intrinsics/checkParameterIsNotNull (Ljava/lang/Object;Ljava/lang/String;)V
L_0004:
    .line 3
    aload 0
    invokespecial com/anatawa12/jasm/tree/BranchNode/<init> ()V
    aload 0
    aload 1
    putfield com/anatawa12/jasm/tree/JasmHeader/elements Ljava/util/List;
    return
L_000c:
.end method

.method public component1 ()Ljava/util/List;
    .signature "()Ljava/util/List<Lcom/anatawa12/jasm/tree/JasmHeaderElement;>;"
    .annotation invisible org/jetbrains/annotations/NotNull
    .end annotation
    .limit stack 1
    .limit local 1
L_0000:
    .var 0 is this Lcom/anatawa12/jasm/tree/JasmHeader; from L_0000 to L_0004
    aload 0
    getfield com/anatawa12/jasm/tree/JasmHeader/elements Ljava/util/List;
    areturn
L_0004:
.end method

.method public copy (Ljava/util/List;)Lcom/anatawa12/jasm/tree/JasmHeader;
    .signature "(Ljava/util/List<+Lcom/anatawa12/jasm/tree/JasmHeaderElement;>;)Lcom/anatawa12/jasm/tree/JasmHeader;"
    .annotation invisible org/jetbrains/annotations/NotNull
    .end annotation
    .annotation invisiblepararm 0 org/jetbrains/annotations/NotNull
    .end annotation
    .limit stack 3
    .limit local 2
L_0000:
    .var 0 is this Lcom/anatawa12/jasm/tree/JasmHeader; from L_0000 to L_0009
    .var 1 is elements Ljava/util/List; from L_0000 to L_0009
    aload 1
    ldc "elements"
    invokestatic kotlin/jvm/internal/Intrinsics/checkParameterIsNotNull (Ljava/lang/Object;Ljava/lang/String;)V
    new com/anatawa12/jasm/tree/JasmHeader
    dup
    aload 1
    invokespecial com/anatawa12/jasm/tree/JasmHeader/<init> (Ljava/util/List;)V
    areturn
L_0009:
.end method

.method public copy$default (Lcom/anatawa12/jasm/tree/JasmHeader;Ljava/util/List;ILjava/lang/Object;)Lcom/anatawa12/jasm/tree/JasmHeader;
    .limit stack 2
    .limit local 4
    iload 2
    iconst_1
    iand
    ifeq L_0007
    aload 0
    getfield com/anatawa12/jasm/tree/JasmHeader/elements Ljava/util/List;
    astore 1
L_0007:
    .stack
        locals Object com/anatawa12/jasm/tree/JasmHeader
        locals Object java/util/List
        locals Integer
        locals Object java/lang/Object
    .end stack
    aload 0
    aload 1
    invokevirtual com/anatawa12/jasm/tree/JasmHeader/copy (Ljava/util/List;)Lcom/anatawa12/jasm/tree/JasmHeader;
    areturn
.end method

.method public toString ()Ljava/lang/String;
    .annotation invisible org/jetbrains/annotations/NotNull
    .end annotation
    .limit stack 2
    .limit local 1
    new java/lang/StringBuilder
    dup
    invokespecial java/lang/StringBuilder/<init> ()V
    ldc "JasmHeader(elements="
    invokevirtual java/lang/StringBuilder/append (Ljava/lang/String;)Ljava/lang/StringBuilder;
    aload 0
    getfield com/anatawa12/jasm/tree/JasmHeader/elements Ljava/util/List;
    invokevirtual java/lang/StringBuilder/append (Ljava/lang/Object;)Ljava/lang/StringBuilder;
    ldc ")"
    invokevirtual java/lang/StringBuilder/append (Ljava/lang/String;)Ljava/lang/StringBuilder;
    invokevirtual java/lang/StringBuilder/toString ()Ljava/lang/String;
    areturn
.end method

.method public hashCode ()I
    .limit stack 2
    .limit local 1
    aload 0
    getfield com/anatawa12/jasm/tree/JasmHeader/elements Ljava/util/List;
    dup
    ifnull L_0006
    invokevirtual java/lang/Object/hashCode ()I
    goto L_000a
L_0006:
    .stack
        locals Object com/anatawa12/jasm/tree/JasmHeader
        stacks Object java/util/List
    .end stack
    pop
    iconst_0
L_000a:
    .stack use locals
        stacks Integer
    .end stack
    ireturn
.end method

.method public equals (Ljava/lang/Object;)Z
    .annotation invisiblepararm 0 org/jetbrains/annotations/Nullable
    .end annotation
    .limit stack 2
    .limit local 3
    aload 0
    aload 1
    if_acmpeq L_000f
    aload 1
    instanceof com/anatawa12/jasm/tree/JasmHeader
    ifeq L_0013
    aload 1
    checkcast com/anatawa12/jasm/tree/JasmHeader
    astore 2
    aload 0
    getfield com/anatawa12/jasm/tree/JasmHeader/elements Ljava/util/List;
    aload 2
    getfield com/anatawa12/jasm/tree/JasmHeader/elements Ljava/util/List;
    invokestatic kotlin/jvm/internal/Intrinsics/areEqual (Ljava/lang/Object;Ljava/lang/Object;)Z
    ifeq L_0013
L_000f:
    .stack
        locals Object com/anatawa12/jasm/tree/JasmHeader
        locals Object java/lang/Object
    .end stack
    iconst_1
    ireturn
L_0013:
    .stack use locals
    .end stack
    iconst_0
    ireturn
.end method

.field private elements Ljava/util/List;
    .signature "Ljava/util/List<Lcom/anatawa12/jasm/tree/JasmHeaderElement;>;"
    .annotation invisible org/jetbrains/annotations/NotNull
    .end annotation
.end field

