.bytecode 52.0
.source "MethodStatement.kt"
.class public com/anatawa12/jasm/tree/LocalVar
.super com/anatawa12/jasm/tree/MethodStatement

.annotation visible kotlin/Metadata
   mv [ = .annotation array
      I = 1
      I = 1
      I = 16
   .end annotation
   bv [ = .annotation array
      I = 1
      I = 0
      I = 3
   .end annotation
   k I = 1
   d1 [ = .annotation array
      s = "\u0000.\n\u0002\u0018\u0002\n\u0002\u0018\u0002\n\u0000\n\u0002\u0010\b\n\u0000\n\u0002\u0010\u000e\n\u0002\b\u0003\n\u0002\u0018\u0002\n\u0002\b\u0013\n\u0002\u0010\u000b\n\u0000\n\u0002\u0010\u0000\n\u0002\b\u0003\b\u0086\b\u0018\u00002\u00020\u0001B7\u0012\u0006\u0010\u0002\u001a\u00020\u0003\u0012\u0006\u0010\u0004\u001a\u00020\u0005\u0012\u0006\u0010\u0006\u001a\u00020\u0005\u0012\b\u0010\u0007\u001a\u0004\u0018\u00010\u0005\u0012\u0006\u0010\b\u001a\u00020\t\u0012\u0006\u0010\n\u001a\u00020\t¢\u0006\u0002\u0010\u000bJ\t\u0010\u0015\u001a\u00020\u0003HÆ\u0003J\t\u0010\u0016\u001a\u00020\u0005HÆ\u0003J\t\u0010\u0017\u001a\u00020\u0005HÆ\u0003J\u000b\u0010\u0018\u001a\u0004\u0018\u00010\u0005HÆ\u0003J\t\u0010\u0019\u001a\u00020\tHÆ\u0003J\t\u0010\u001a\u001a\u00020\tHÆ\u0003JG\u0010\u001b\u001a\u00020\u00002\b\b\u0002\u0010\u0002\u001a\u00020\u00032\b\b\u0002\u0010\u0004\u001a\u00020\u00052\b\b\u0002\u0010\u0006\u001a\u00020\u00052\n\b\u0002\u0010\u0007\u001a\u0004\u0018\u00010\u00052\b\b\u0002\u0010\b\u001a\u00020\t2\b\b\u0002\u0010\n\u001a\u00020\tHÆ\u0001J\u0013\u0010\u001c\u001a\u00020\u001d2\b\u0010\u001e\u001a\u0004\u0018\u00010\u001fHÖ\u0003J\t\u0010 \u001a\u00020\u0003HÖ\u0001J\t\u0010!\u001a\u00020\u0005HÖ\u0001R\u0011\u0010\u0006\u001a\u00020\u0005¢\u0006\b\n\u0000\u001a\u0004\b\u000c\u0010\rR\u0011\u0010\b\u001a\u00020\t¢\u0006\b\n\u0000\u001a\u0004\b\u000e\u0010\u000fR\u0011\u0010\u0004\u001a\u00020\u0005¢\u0006\b\n\u0000\u001a\u0004\b\u0010\u0010\rR\u0013\u0010\u0007\u001a\u0004\u0018\u00010\u0005¢\u0006\b\n\u0000\u001a\u0004\b\u0011\u0010\rR\u0011\u0010\n\u001a\u00020\t¢\u0006\b\n\u0000\u001a\u0004\b\u0012\u0010\u000fR\u0011\u0010\u0002\u001a\u00020\u0003¢\u0006\b\n\u0000\u001a\u0004\b\u0013\u0010\u0014¨\u0006\""
   .end annotation
   d2 [ = .annotation array
      s = "Lcom/anatawa12/jasm/tree/LocalVar;"
      s = "Lcom/anatawa12/jasm/tree/MethodStatement;"
      s = "variable"
      s = ""
      s = "name"
      s = ""
      s = "descriptor"
      s = "signature"
      s = "from"
      s = "Lcom/anatawa12/jasm/tree/LabelName;"
      s = "to"
      s = "(ILjava/lang/String;Ljava/lang/String;Ljava/lang/String;Lcom/anatawa12/jasm/tree/LabelName;Lcom/anatawa12/jasm/tree/LabelName;)V"
      s = "getDescriptor"
      s = "()Ljava/lang/String;"
      s = "getFrom"
      s = "()Lcom/anatawa12/jasm/tree/LabelName;"
      s = "getName"
      s = "getSignature"
      s = "getTo"
      s = "getVariable"
      s = "()I"
      s = "component1"
      s = "component2"
      s = "component3"
      s = "component4"
      s = "component5"
      s = "component6"
      s = "copy"
      s = "equals"
      s = ""
      s = "other"
      s = ""
      s = "hashCode"
      s = "toString"
      s = "jasm"
   .end annotation
.end annotation

.method public getVariable ()I
   .limit stack 1
   .limit local 1
L_0000:
   .line 11
   .var 0 is this Lcom/anatawa12/jasm/tree/LocalVar; from L_0000 to L_0005
   aload 0
   getfield com/anatawa12/jasm/tree/LocalVar/variable I
   ireturn
L_0005:
.end method

.method public getName ()Ljava/lang/String;
   .annotation invisible org/jetbrains/annotations/NotNull
   .end annotation
   .limit stack 1
   .limit local 1
L_0000:
   .line 11
   .var 0 is this Lcom/anatawa12/jasm/tree/LocalVar; from L_0000 to L_0005
   aload 0
   getfield com/anatawa12/jasm/tree/LocalVar/name Ljava/lang/String;
   areturn
L_0005:
.end method

.method public getDescriptor ()Ljava/lang/String;
   .annotation invisible org/jetbrains/annotations/NotNull
   .end annotation
   .limit stack 1
   .limit local 1
L_0000:
   .line 11
   .var 0 is this Lcom/anatawa12/jasm/tree/LocalVar; from L_0000 to L_0005
   aload 0
   getfield com/anatawa12/jasm/tree/LocalVar/descriptor Ljava/lang/String;
   areturn
L_0005:
.end method

.method public getSignature ()Ljava/lang/String;
   .annotation invisible org/jetbrains/annotations/Nullable
   .end annotation
   .limit stack 1
   .limit local 1
L_0000:
   .line 11
   .var 0 is this Lcom/anatawa12/jasm/tree/LocalVar; from L_0000 to L_0005
   aload 0
   getfield com/anatawa12/jasm/tree/LocalVar/signature Ljava/lang/String;
   areturn
L_0005:
.end method

.method public getFrom ()Lcom/anatawa12/jasm/tree/LabelName;
   .annotation invisible org/jetbrains/annotations/NotNull
   .end annotation
   .limit stack 1
   .limit local 1
L_0000:
   .line 11
   .var 0 is this Lcom/anatawa12/jasm/tree/LocalVar; from L_0000 to L_0005
   aload 0
   getfield com/anatawa12/jasm/tree/LocalVar/from Lcom/anatawa12/jasm/tree/LabelName;
   areturn
L_0005:
.end method

.method public getTo ()Lcom/anatawa12/jasm/tree/LabelName;
   .annotation invisible org/jetbrains/annotations/NotNull
   .end annotation
   .limit stack 1
   .limit local 1
L_0000:
   .line 11
   .var 0 is this Lcom/anatawa12/jasm/tree/LocalVar; from L_0000 to L_0005
   aload 0
   getfield com/anatawa12/jasm/tree/LocalVar/to Lcom/anatawa12/jasm/tree/LabelName;
   areturn
L_0005:
.end method

.method public <init> (ILjava/lang/String;Ljava/lang/String;Ljava/lang/String;Lcom/anatawa12/jasm/tree/LabelName;Lcom/anatawa12/jasm/tree/LabelName;)V
   .annotation invisiblepararm 1 org/jetbrains/annotations/NotNull
   .end annotation
   .annotation invisiblepararm 2 org/jetbrains/annotations/NotNull
   .end annotation
   .annotation invisiblepararm 3 org/jetbrains/annotations/Nullable
   .end annotation
   .annotation invisiblepararm 4 org/jetbrains/annotations/NotNull
   .end annotation
   .annotation invisiblepararm 5 org/jetbrains/annotations/NotNull
   .end annotation
   .limit stack 2
   .limit local 7
L_0000:
   .var 0 is this Lcom/anatawa12/jasm/tree/LocalVar; from L_0000 to L_0025
   .var 1 is variable I from L_0000 to L_0025
   .var 2 is name Ljava/lang/String; from L_0000 to L_0025
   .var 3 is descriptor Ljava/lang/String; from L_0000 to L_0025
   .var 4 is signature Ljava/lang/String; from L_0000 to L_0025
   .var 5 is from Lcom/anatawa12/jasm/tree/LabelName; from L_0000 to L_0025
   .var 6 is to Lcom/anatawa12/jasm/tree/LabelName; from L_0000 to L_0025
   aload 2
   ldc "name"
   invokestatic kotlin/jvm/internal/Intrinsics/checkParameterIsNotNull (Ljava/lang/Object;Ljava/lang/String;)V
   aload 3
   ldc "descriptor"
   invokestatic kotlin/jvm/internal/Intrinsics/checkParameterIsNotNull (Ljava/lang/Object;Ljava/lang/String;)V
   aload 5
   ldc "from"
   invokestatic kotlin/jvm/internal/Intrinsics/checkParameterIsNotNull (Ljava/lang/Object;Ljava/lang/String;)V
   aload 6
   ldc "to"
   invokestatic kotlin/jvm/internal/Intrinsics/checkParameterIsNotNull (Ljava/lang/Object;Ljava/lang/String;)V
L_000d:
   .line 11
   aload 0
   aconst_null
   invokespecial com/anatawa12/jasm/tree/MethodStatement/<init> (Lkotlin/jvm/internal/DefaultConstructorMarker;)V
   aload 0
   iload 1
   putfield com/anatawa12/jasm/tree/LocalVar/variable I
   aload 0
   aload 2
   putfield com/anatawa12/jasm/tree/LocalVar/name Ljava/lang/String;
   aload 0
   aload 3
   putfield com/anatawa12/jasm/tree/LocalVar/descriptor Ljava/lang/String;
   aload 0
   aload 4
   putfield com/anatawa12/jasm/tree/LocalVar/signature Ljava/lang/String;
   aload 0
   aload 5
   putfield com/anatawa12/jasm/tree/LocalVar/from Lcom/anatawa12/jasm/tree/LabelName;
   aload 0
   aload 6
   putfield com/anatawa12/jasm/tree/LocalVar/to Lcom/anatawa12/jasm/tree/LabelName;
   return
L_0025:
.end method

.method public component1 ()I
   .limit stack 1
   .limit local 1
L_0000:
   .var 0 is this Lcom/anatawa12/jasm/tree/LocalVar; from L_0000 to L_0004
   aload 0
   getfield com/anatawa12/jasm/tree/LocalVar/variable I
   ireturn
L_0004:
.end method

.method public component2 ()Ljava/lang/String;
   .annotation invisible org/jetbrains/annotations/NotNull
   .end annotation
   .limit stack 1
   .limit local 1
L_0000:
   .var 0 is this Lcom/anatawa12/jasm/tree/LocalVar; from L_0000 to L_0004
   aload 0
   getfield com/anatawa12/jasm/tree/LocalVar/name Ljava/lang/String;
   areturn
L_0004:
.end method

.method public component3 ()Ljava/lang/String;
   .annotation invisible org/jetbrains/annotations/NotNull
   .end annotation
   .limit stack 1
   .limit local 1
L_0000:
   .var 0 is this Lcom/anatawa12/jasm/tree/LocalVar; from L_0000 to L_0004
   aload 0
   getfield com/anatawa12/jasm/tree/LocalVar/descriptor Ljava/lang/String;
   areturn
L_0004:
.end method

.method public component4 ()Ljava/lang/String;
   .annotation invisible org/jetbrains/annotations/Nullable
   .end annotation
   .limit stack 1
   .limit local 1
L_0000:
   .var 0 is this Lcom/anatawa12/jasm/tree/LocalVar; from L_0000 to L_0004
   aload 0
   getfield com/anatawa12/jasm/tree/LocalVar/signature Ljava/lang/String;
   areturn
L_0004:
.end method

.method public component5 ()Lcom/anatawa12/jasm/tree/LabelName;
   .annotation invisible org/jetbrains/annotations/NotNull
   .end annotation
   .limit stack 1
   .limit local 1
L_0000:
   .var 0 is this Lcom/anatawa12/jasm/tree/LocalVar; from L_0000 to L_0004
   aload 0
   getfield com/anatawa12/jasm/tree/LocalVar/from Lcom/anatawa12/jasm/tree/LabelName;
   areturn
L_0004:
.end method

.method public component6 ()Lcom/anatawa12/jasm/tree/LabelName;
   .annotation invisible org/jetbrains/annotations/NotNull
   .end annotation
   .limit stack 1
   .limit local 1
L_0000:
   .var 0 is this Lcom/anatawa12/jasm/tree/LocalVar; from L_0000 to L_0004
   aload 0
   getfield com/anatawa12/jasm/tree/LocalVar/to Lcom/anatawa12/jasm/tree/LabelName;
   areturn
L_0004:
.end method

.method public copy (ILjava/lang/String;Ljava/lang/String;Ljava/lang/String;Lcom/anatawa12/jasm/tree/LabelName;Lcom/anatawa12/jasm/tree/LabelName;)Lcom/anatawa12/jasm/tree/LocalVar;
   .annotation invisible org/jetbrains/annotations/NotNull
   .end annotation
   .annotation invisiblepararm 1 org/jetbrains/annotations/NotNull
   .end annotation
   .annotation invisiblepararm 2 org/jetbrains/annotations/NotNull
   .end annotation
   .annotation invisiblepararm 3 org/jetbrains/annotations/Nullable
   .end annotation
   .annotation invisiblepararm 4 org/jetbrains/annotations/NotNull
   .end annotation
   .annotation invisiblepararm 5 org/jetbrains/annotations/NotNull
   .end annotation
   .limit stack 8
   .limit local 7
L_0000:
   .var 0 is this Lcom/anatawa12/jasm/tree/LocalVar; from L_0000 to L_0017
   .var 1 is variable I from L_0000 to L_0017
   .var 2 is name Ljava/lang/String; from L_0000 to L_0017
   .var 3 is descriptor Ljava/lang/String; from L_0000 to L_0017
   .var 4 is signature Ljava/lang/String; from L_0000 to L_0017
   .var 5 is from Lcom/anatawa12/jasm/tree/LabelName; from L_0000 to L_0017
   .var 6 is to Lcom/anatawa12/jasm/tree/LabelName; from L_0000 to L_0017
   aload 2
   ldc "name"
   invokestatic kotlin/jvm/internal/Intrinsics/checkParameterIsNotNull (Ljava/lang/Object;Ljava/lang/String;)V
   aload 3
   ldc "descriptor"
   invokestatic kotlin/jvm/internal/Intrinsics/checkParameterIsNotNull (Ljava/lang/Object;Ljava/lang/String;)V
   aload 5
   ldc "from"
   invokestatic kotlin/jvm/internal/Intrinsics/checkParameterIsNotNull (Ljava/lang/Object;Ljava/lang/String;)V
   aload 6
   ldc "to"
   invokestatic kotlin/jvm/internal/Intrinsics/checkParameterIsNotNull (Ljava/lang/Object;Ljava/lang/String;)V
   new com/anatawa12/jasm/tree/LocalVar
   dup
   iload 1
   aload 2
   aload 3
   aload 4
   aload 5
   aload 6
   invokespecial com/anatawa12/jasm/tree/LocalVar/<init> (ILjava/lang/String;Ljava/lang/String;Ljava/lang/String;Lcom/anatawa12/jasm/tree/LabelName;Lcom/anatawa12/jasm/tree/LabelName;)V
   areturn
L_0017:
.end method

.method public copy$default (Lcom/anatawa12/jasm/tree/LocalVar;ILjava/lang/String;Ljava/lang/String;Ljava/lang/String;Lcom/anatawa12/jasm/tree/LabelName;Lcom/anatawa12/jasm/tree/LabelName;ILjava/lang/Object;)Lcom/anatawa12/jasm/tree/LocalVar;
   .limit stack 7
   .limit local 9
   iload 7
   iconst_1
   iand
   ifeq L_0007
   aload 0
   getfield com/anatawa12/jasm/tree/LocalVar/variable I
   istore 1
L_0007:
   .stack
      locals Object com/anatawa12/jasm/tree/LocalVar
      locals Integer
      locals Object java/lang/String
      locals Object java/lang/String
      locals Object java/lang/String
      locals Object com/anatawa12/jasm/tree/LabelName
      locals Object com/anatawa12/jasm/tree/LabelName
      locals Integer
      locals Object java/lang/Object
   .end stack
   iload 7
   iconst_2
   iand
   ifeq L_0010
   aload 0
   getfield com/anatawa12/jasm/tree/LocalVar/name Ljava/lang/String;
   astore 2
L_0010:
   .stack use locals
   .end stack
   iload 7
   iconst_4
   iand
   ifeq L_0019
   aload 0
   getfield com/anatawa12/jasm/tree/LocalVar/descriptor Ljava/lang/String;
   astore 3
L_0019:
   .stack use locals
   .end stack
   iload 7
   bipush 8
   iand
   ifeq L_0022
   aload 0
   getfield com/anatawa12/jasm/tree/LocalVar/signature Ljava/lang/String;
   astore 4
L_0022:
   .stack use locals
   .end stack
   iload 7
   bipush 16
   iand
   ifeq L_002b
   aload 0
   getfield com/anatawa12/jasm/tree/LocalVar/from Lcom/anatawa12/jasm/tree/LabelName;
   astore 5
L_002b:
   .stack use locals
   .end stack
   iload 7
   bipush 32
   iand
   ifeq L_0034
   aload 0
   getfield com/anatawa12/jasm/tree/LocalVar/to Lcom/anatawa12/jasm/tree/LabelName;
   astore 6
L_0034:
   .stack use locals
   .end stack
   aload 0
   iload 1
   aload 2
   aload 3
   aload 4
   aload 5
   aload 6
   invokevirtual com/anatawa12/jasm/tree/LocalVar/copy (ILjava/lang/String;Ljava/lang/String;Ljava/lang/String;Lcom/anatawa12/jasm/tree/LabelName;Lcom/anatawa12/jasm/tree/LabelName;)Lcom/anatawa12/jasm/tree/LocalVar;
   areturn
.end method

.method public toString ()Ljava/lang/String;
   .annotation invisible org/jetbrains/annotations/NotNull
   .end annotation
   .limit stack 2
   .limit local 1
   new java/lang/StringBuilder
   dup
   invokespecial java/lang/StringBuilder/<init> ()V
   ldc "LocalVar(variable="
   invokevirtual java/lang/StringBuilder/append (Ljava/lang/String;)Ljava/lang/StringBuilder;
   aload 0
   getfield com/anatawa12/jasm/tree/LocalVar/variable I
   invokevirtual java/lang/StringBuilder/append (I)Ljava/lang/StringBuilder;
   ldc ", name="
   invokevirtual java/lang/StringBuilder/append (Ljava/lang/String;)Ljava/lang/StringBuilder;
   aload 0
   getfield com/anatawa12/jasm/tree/LocalVar/name Ljava/lang/String;
   invokevirtual java/lang/StringBuilder/append (Ljava/lang/String;)Ljava/lang/StringBuilder;
   ldc ", descriptor="
   invokevirtual java/lang/StringBuilder/append (Ljava/lang/String;)Ljava/lang/StringBuilder;
   aload 0
   getfield com/anatawa12/jasm/tree/LocalVar/descriptor Ljava/lang/String;
   invokevirtual java/lang/StringBuilder/append (Ljava/lang/String;)Ljava/lang/StringBuilder;
   ldc ", signature="
   invokevirtual java/lang/StringBuilder/append (Ljava/lang/String;)Ljava/lang/StringBuilder;
   aload 0
   getfield com/anatawa12/jasm/tree/LocalVar/signature Ljava/lang/String;
   invokevirtual java/lang/StringBuilder/append (Ljava/lang/String;)Ljava/lang/StringBuilder;
   ldc ", from="
   invokevirtual java/lang/StringBuilder/append (Ljava/lang/String;)Ljava/lang/StringBuilder;
   aload 0
   getfield com/anatawa12/jasm/tree/LocalVar/from Lcom/anatawa12/jasm/tree/LabelName;
   invokevirtual java/lang/StringBuilder/append (Ljava/lang/Object;)Ljava/lang/StringBuilder;
   ldc ", to="
   invokevirtual java/lang/StringBuilder/append (Ljava/lang/String;)Ljava/lang/StringBuilder;
   aload 0
   getfield com/anatawa12/jasm/tree/LocalVar/to Lcom/anatawa12/jasm/tree/LabelName;
   invokevirtual java/lang/StringBuilder/append (Ljava/lang/Object;)Ljava/lang/StringBuilder;
   ldc ")"
   invokevirtual java/lang/StringBuilder/append (Ljava/lang/String;)Ljava/lang/StringBuilder;
   invokevirtual java/lang/StringBuilder/toString ()Ljava/lang/String;
   areturn
.end method

.method public hashCode ()I
   .limit stack 3
   .limit local 1
   aload 0
   getfield com/anatawa12/jasm/tree/LocalVar/variable I
   invokestatic java/lang/Integer/hashCode (I)I
   bipush 31
   imul
   aload 0
   getfield com/anatawa12/jasm/tree/LocalVar/name Ljava/lang/String;
   dup
   ifnull L_000b
   invokevirtual java/lang/Object/hashCode ()I
   goto L_000f
L_000b:
   .stack
      locals Object com/anatawa12/jasm/tree/LocalVar
      stacks Integer
      stacks Object java/lang/String
   .end stack
   pop
   iconst_0
L_000f:
   .stack use locals
      stacks Integer
      stacks Integer
   .end stack
   iadd
   bipush 31
   imul
   aload 0
   getfield com/anatawa12/jasm/tree/LocalVar/descriptor Ljava/lang/String;
   dup
   ifnull L_001a
   invokevirtual java/lang/Object/hashCode ()I
   goto L_001e
L_001a:
   .stack use locals
      stacks Integer
      stacks Object java/lang/String
   .end stack
   pop
   iconst_0
L_001e:
   .stack use locals
      stacks Integer
      stacks Integer
   .end stack
   iadd
   bipush 31
   imul
   aload 0
   getfield com/anatawa12/jasm/tree/LocalVar/signature Ljava/lang/String;
   dup
   ifnull L_0029
   invokevirtual java/lang/Object/hashCode ()I
   goto L_002d
L_0029:
   .stack use locals
      stacks Integer
      stacks Object java/lang/String
   .end stack
   pop
   iconst_0
L_002d:
   .stack use locals
      stacks Integer
      stacks Integer
   .end stack
   iadd
   bipush 31
   imul
   aload 0
   getfield com/anatawa12/jasm/tree/LocalVar/from Lcom/anatawa12/jasm/tree/LabelName;
   dup
   ifnull L_0038
   invokevirtual java/lang/Object/hashCode ()I
   goto L_003c
L_0038:
   .stack use locals
      stacks Integer
      stacks Object com/anatawa12/jasm/tree/LabelName
   .end stack
   pop
   iconst_0
L_003c:
   .stack use locals
      stacks Integer
      stacks Integer
   .end stack
   iadd
   bipush 31
   imul
   aload 0
   getfield com/anatawa12/jasm/tree/LocalVar/to Lcom/anatawa12/jasm/tree/LabelName;
   dup
   ifnull L_0047
   invokevirtual java/lang/Object/hashCode ()I
   goto L_004b
L_0047:
   .stack use locals
      stacks Integer
      stacks Object com/anatawa12/jasm/tree/LabelName
   .end stack
   pop
   iconst_0
L_004b:
   .stack use locals
      stacks Integer
      stacks Integer
   .end stack
   iadd
   ireturn
.end method

.method public equals (Ljava/lang/Object;)Z
   .annotation invisiblepararm 0 org/jetbrains/annotations/Nullable
   .end annotation
   .limit stack 2
   .limit local 3
   aload 0
   aload 1
   if_acmpeq L_002c
   aload 1
   instanceof com/anatawa12/jasm/tree/LocalVar
   ifeq L_0030
   aload 1
   checkcast com/anatawa12/jasm/tree/LocalVar
   astore 2
   aload 0
   getfield com/anatawa12/jasm/tree/LocalVar/variable I
   aload 2
   getfield com/anatawa12/jasm/tree/LocalVar/variable I
   if_icmpne L_0030
   aload 0
   getfield com/anatawa12/jasm/tree/LocalVar/name Ljava/lang/String;
   aload 2
   getfield com/anatawa12/jasm/tree/LocalVar/name Ljava/lang/String;
   invokestatic kotlin/jvm/internal/Intrinsics/areEqual (Ljava/lang/Object;Ljava/lang/Object;)Z
   ifeq L_0030
   aload 0
   getfield com/anatawa12/jasm/tree/LocalVar/descriptor Ljava/lang/String;
   aload 2
   getfield com/anatawa12/jasm/tree/LocalVar/descriptor Ljava/lang/String;
   invokestatic kotlin/jvm/internal/Intrinsics/areEqual (Ljava/lang/Object;Ljava/lang/Object;)Z
   ifeq L_0030
   aload 0
   getfield com/anatawa12/jasm/tree/LocalVar/signature Ljava/lang/String;
   aload 2
   getfield com/anatawa12/jasm/tree/LocalVar/signature Ljava/lang/String;
   invokestatic kotlin/jvm/internal/Intrinsics/areEqual (Ljava/lang/Object;Ljava/lang/Object;)Z
   ifeq L_0030
   aload 0
   getfield com/anatawa12/jasm/tree/LocalVar/from Lcom/anatawa12/jasm/tree/LabelName;
   aload 2
   getfield com/anatawa12/jasm/tree/LocalVar/from Lcom/anatawa12/jasm/tree/LabelName;
   invokestatic kotlin/jvm/internal/Intrinsics/areEqual (Ljava/lang/Object;Ljava/lang/Object;)Z
   ifeq L_0030
   aload 0
   getfield com/anatawa12/jasm/tree/LocalVar/to Lcom/anatawa12/jasm/tree/LabelName;
   aload 2
   getfield com/anatawa12/jasm/tree/LocalVar/to Lcom/anatawa12/jasm/tree/LabelName;
   invokestatic kotlin/jvm/internal/Intrinsics/areEqual (Ljava/lang/Object;Ljava/lang/Object;)Z
   ifeq L_0030
L_002c:
   .stack
      locals Object com/anatawa12/jasm/tree/LocalVar
      locals Object java/lang/Object
   .end stack
   iconst_1
   ireturn
L_0030:
   .stack use locals
   .end stack
   iconst_0
   ireturn
.end method

.field private variable I
.end field

.field private name Ljava/lang/String;
   .annotation invisible org/jetbrains/annotations/NotNull
   .end annotation
.end field

.field private descriptor Ljava/lang/String;
   .annotation invisible org/jetbrains/annotations/NotNull
   .end annotation
.end field

.field private signature Ljava/lang/String;
   .annotation invisible org/jetbrains/annotations/Nullable
   .end annotation
.end field

.field private from Lcom/anatawa12/jasm/tree/LabelName;
   .annotation invisible org/jetbrains/annotations/NotNull
   .end annotation
.end field

.field private to Lcom/anatawa12/jasm/tree/LabelName;
   .annotation invisible org/jetbrains/annotations/NotNull
   .end annotation
.end field

