.bytecode 52.0
.source "Token.kt"
.class public com/anatawa12/jasm/tree/Token
.super com/anatawa12/jasm/tree/Node
.signature "<T:Ljava/lang/Object;>Lcom/anatawa12/jasm/tree/Node;"
.inner public com/anatawa12/jasm/tree/Token$Companion inner Companion outer com/anatawa12/jasm/tree/Token

.annotation visible kotlin/Metadata
    mv [ = .annotation array
        I = 1
        I = 1
        I = 16
    .end annotation
    bv [ = .annotation array
        I = 1
        I = 0
        I = 3
    .end annotation
    k I = 1
    d1 [ = .annotation array
        s = "\u0000\$\n\u0002\u0018\u0002\n\u0000\n\u0002\u0018\u0002\n\u0000\n\u0002\u0010\u000e\n\u0002\b\u0002\n\u0002\u0018\u0002\n\u0002\b\b\n\u0002\u0010\u0011\n\u0002\b\b\u0018\u0000 \u0017*\u0004\b\u0000\u0010\u00012\u00020\u0002:\u0001\u0017B%\u0012\u0006\u0010\u0003\u001a\u00020\u0004\u0012\u0006\u0010\u0005\u001a\u00028\u0000\u0012\u0006\u0010\u0006\u001a\u00020\u0007\u0012\u0006\u0010\b\u001a\u00020\u0007¢\u0006\u0002\u0010\tR\u0011\u0010\u0006\u001a\u00020\u0007¢\u0006\b\n\u0000\u001a\u0004\b\n\u0010\u000bR\u0011\u0010\b\u001a\u00020\u0007¢\u0006\b\n\u0000\u001a\u0004\b\u000c\u0010\u000bR\u0011\u0010\u0003\u001a\u00020\u0004¢\u0006\b\n\u0000\u001a\u0004\b\r\u0010\u000eR\"\u0010\u000f\u001a\u000e\u0012\n\b\u0001\u0012\u0006\u0012\u0002\b\u00030\u00000\u0010X\u0096\u0004¢\u0006\n\n\u0002\u0010\u0013\u001a\u0004\b\u0011\u0010\u0012R\u0013\u0010\u0005\u001a\u00028\u0000¢\u0006\n\n\u0002\u0010\u0016\u001a\u0004\b\u0014\u0010\u0015¨\u0006\u0018"
    .end annotation
    d2 [ = .annotation array
        s = "Lcom/anatawa12/jasm/tree/Token;"
        s = "T"
        s = "Lcom/anatawa12/jasm/tree/Node;"
        s = "text"
        s = ""
        s = "value"
        s = "begin"
        s = "Lcom/anatawa12/jasm/tree/CharPosition;"
        s = "end"
        s = "(Ljava/lang/String;Ljava/lang/Object;Lcom/anatawa12/jasm/tree/CharPosition;Lcom/anatawa12/jasm/tree/CharPosition;)V"
        s = "getBegin"
        s = "()Lcom/anatawa12/jasm/tree/CharPosition;"
        s = "getEnd"
        s = "getText"
        s = "()Ljava/lang/String;"
        s = "tokens"
        s = ""
        s = "getTokens"
        s = "()[Lcom/anatawa12/jasm/tree/Token;"
        s = "[Lcom/anatawa12/jasm/tree/Token;"
        s = "getValue"
        s = "()Ljava/lang/Object;"
        s = "Ljava/lang/Object;"
        s = "Companion"
        s = "jasm"
    .end annotation
.end annotation

.method public getTokens "()[Lcom/anatawa12/jasm/tree/Token;"
    .signature "()[Lcom/anatawa12/jasm/tree/Token<*>;"
    .annotation invisible org/jetbrains/annotations/NotNull
    .end annotation
    .limit stack 1
    .limit local 1
L_0000:
    .line 4
    .var 0 is this Lcom/anatawa12/jasm/tree/Token; from L_0000 to L_0005
    aload 0
    getfield com/anatawa12/jasm/tree/Token/tokens "[Lcom/anatawa12/jasm/tree/Token;"
    areturn
L_0005:
.end method

.method public getText ()Ljava/lang/String;
    .annotation invisible org/jetbrains/annotations/NotNull
    .end annotation
    .limit stack 1
    .limit local 1
L_0000:
    .line 3
    .var 0 is this Lcom/anatawa12/jasm/tree/Token; from L_0000 to L_0005
    aload 0
    getfield com/anatawa12/jasm/tree/Token/text Ljava/lang/String;
    areturn
L_0005:
.end method

.method public getValue ()Ljava/lang/Object;
    .signature "()TT;"
    .limit stack 1
    .limit local 1
L_0000:
    .line 3
    .var 0 is this Lcom/anatawa12/jasm/tree/Token; from L_0000 to L_0005
    aload 0
    getfield com/anatawa12/jasm/tree/Token/value Ljava/lang/Object;
    areturn
L_0005:
.end method

.method public getBegin ()Lcom/anatawa12/jasm/tree/CharPosition;
    .annotation invisible org/jetbrains/annotations/NotNull
    .end annotation
    .limit stack 1
    .limit local 1
L_0000:
    .line 3
    .var 0 is this Lcom/anatawa12/jasm/tree/Token; from L_0000 to L_0005
    aload 0
    getfield com/anatawa12/jasm/tree/Token/begin Lcom/anatawa12/jasm/tree/CharPosition;
    areturn
L_0005:
.end method

.method public getEnd ()Lcom/anatawa12/jasm/tree/CharPosition;
    .annotation invisible org/jetbrains/annotations/NotNull
    .end annotation
    .limit stack 1
    .limit local 1
L_0000:
    .line 3
    .var 0 is this Lcom/anatawa12/jasm/tree/Token; from L_0000 to L_0005
    aload 0
    getfield com/anatawa12/jasm/tree/Token/end Lcom/anatawa12/jasm/tree/CharPosition;
    areturn
L_0005:
.end method

.method public <init> (Ljava/lang/String;Ljava/lang/Object;Lcom/anatawa12/jasm/tree/CharPosition;Lcom/anatawa12/jasm/tree/CharPosition;)V
    .signature "(Ljava/lang/String;TT;Lcom/anatawa12/jasm/tree/CharPosition;Lcom/anatawa12/jasm/tree/CharPosition;)V"
    .annotation invisiblepararm 0 org/jetbrains/annotations/NotNull
    .end annotation
    .annotation invisiblepararm 2 org/jetbrains/annotations/NotNull
    .end annotation
    .annotation invisiblepararm 3 org/jetbrains/annotations/NotNull
    .end annotation
    .limit stack 5
    .limit local 5
L_0000:
    .var 0 is this Lcom/anatawa12/jasm/tree/Token; from L_0000 to L_0026
    .var 1 is text Ljava/lang/String; from L_0000 to L_0026
    .var 2 is value Ljava/lang/Object; from L_0000 to L_0026
    .var 3 is begin Lcom/anatawa12/jasm/tree/CharPosition; from L_0000 to L_0026
    .var 4 is end Lcom/anatawa12/jasm/tree/CharPosition; from L_0000 to L_0026
    aload 1
    ldc "text"
    invokestatic kotlin/jvm/internal/Intrinsics/checkParameterIsNotNull (Ljava/lang/Object;Ljava/lang/String;)V
    aload 3
    ldc "begin"
    invokestatic kotlin/jvm/internal/Intrinsics/checkParameterIsNotNull (Ljava/lang/Object;Ljava/lang/String;)V
    aload 4
    ldc "end"
    invokestatic kotlin/jvm/internal/Intrinsics/checkParameterIsNotNull (Ljava/lang/Object;Ljava/lang/String;)V
L_000a:
    .line 3
    aload 0
    invokespecial com/anatawa12/jasm/tree/Node/<init> ()V
    aload 0
    aload 1
    putfield com/anatawa12/jasm/tree/Token/text Ljava/lang/String;
    aload 0
    aload 2
    putfield com/anatawa12/jasm/tree/Token/value Ljava/lang/Object;
    aload 0
    aload 3
    putfield com/anatawa12/jasm/tree/Token/begin Lcom/anatawa12/jasm/tree/CharPosition;
    aload 0
    aload 4
    putfield com/anatawa12/jasm/tree/Token/end Lcom/anatawa12/jasm/tree/CharPosition;
L_001a:
    .line 4
    aload 0
    iconst_1
    anewarray com/anatawa12/jasm/tree/Token
    dup
    iconst_0
    aload 0
    checkcast com/anatawa12/jasm/tree/Token
    aastore
    putfield com/anatawa12/jasm/tree/Token/tokens "[Lcom/anatawa12/jasm/tree/Token;"
    return
L_0026:
.end method

.method static <clinit> ()V
    .limit stack 10
    .limit local 0
    new com/anatawa12/jasm/tree/Token$Companion
    dup
    aconst_null
    invokespecial com/anatawa12/jasm/tree/Token$Companion/<init> (Lkotlin/jvm/internal/DefaultConstructorMarker;)V
    putstatic com/anatawa12/jasm/tree/Token/Companion Lcom/anatawa12/jasm/tree/Token$Companion;
L_0005:
    .line 7
    new com/anatawa12/jasm/tree/Token
    dup
    ldc ""
    aconst_null
    new com/anatawa12/jasm/tree/CharPosition
    dup
    iconst_0
    iconst_0
    iconst_0
    invokespecial com/anatawa12/jasm/tree/CharPosition/<init> (III)V
    new com/anatawa12/jasm/tree/CharPosition
    dup
    iconst_0
    iconst_0
    iconst_0
    invokespecial com/anatawa12/jasm/tree/CharPosition/<init> (III)V
    invokespecial com/anatawa12/jasm/tree/Token/<init> (Ljava/lang/String;Ljava/lang/Object;Lcom/anatawa12/jasm/tree/CharPosition;Lcom/anatawa12/jasm/tree/CharPosition;)V
    putstatic com/anatawa12/jasm/tree/Token/TEST Lcom/anatawa12/jasm/tree/Token;
    return
.end method

.method public access$getTEST$cp ()Lcom/anatawa12/jasm/tree/Token;
    .limit stack 1
    .limit local 0
L_0000:
    .line 3
    getstatic com/anatawa12/jasm/tree/Token/TEST Lcom/anatawa12/jasm/tree/Token;
    areturn
.end method

.field private tokens "[Lcom/anatawa12/jasm/tree/Token;"
    .signature "[Lcom/anatawa12/jasm/tree/Token<*>;"
    .annotation invisible org/jetbrains/annotations/NotNull
    .end annotation
.end field

.field private text Ljava/lang/String;
    .annotation invisible org/jetbrains/annotations/NotNull
    .end annotation
.end field

.field private value Ljava/lang/Object;
    .signature "TT;"
.end field

.field private begin Lcom/anatawa12/jasm/tree/CharPosition;
    .annotation invisible org/jetbrains/annotations/NotNull
    .end annotation
.end field

.field private end Lcom/anatawa12/jasm/tree/CharPosition;
    .annotation invisible org/jetbrains/annotations/NotNull
    .end annotation
.end field

.field private TEST Lcom/anatawa12/jasm/tree/Token;
    .annotation invisible org/jetbrains/annotations/NotNull
    .end annotation
.end field

.field public Companion Lcom/anatawa12/jasm/tree/Token$Companion;
.end field

