.bytecode 52.0
.source "Lexer.kt"
.class public com/anatawa12/jasm/parser/Lexer
.super java/lang/Object
.implements com/anatawa12/jasm/parser/ILexer
.inner private com/anatawa12/jasm/parser/Lexer$TokenVisitor inner TokenVisitor outer com/anatawa12/jasm/parser/Lexer
.inner public com/anatawa12/jasm/parser/Lexer$Reader inner Reader outer com/anatawa12/jasm/parser/Lexer

.annotation visible kotlin/Metadata
   mv [ = .annotation array
      I = 1
      I = 1
      I = 16
   .end annotation
   bv [ = .annotation array
      I = 1
      I = 0
      I = 3
   .end annotation
   k I = 1
   d1 [ = .annotation array
      s = "\u0000V\n\u0002\u0018\u0002\n\u0002\u0018\u0002\n\u0000\n\u0002\u0018\u0002\n\u0002\b\u0002\n\u0002\u0010\b\n\u0000\n\u0002\u0018\u0002\n\u0000\n\u0002\u0018\u0002\n\u0002\b\u0002\n\u0002\u0010\u0000\n\u0002\b\u0004\n\u0002\u0010\u000c\n\u0002\b\u0005\n\u0002\u0010\u000b\n\u0000\n\u0002\u0018\u0002\n\u0000\n\u0002\u0010\u0002\n\u0000\n\u0002\u0010\u0001\n\u0000\n\u0002\u0010\"\n\u0002\b\u0003\u0018\u00002\u00020\u0001:\u0002!\"B\r\u0012\u0006\u0010\u0002\u001a\u00020\u0003¢\u0006\u0002\u0010\u0004J)\u0010\u000b\u001a\u0004\u0018\u0001H\u000c\"\b\b\u0000\u0010\u000c*\u00020\r2\u000c\u0010\u000e\u001a\b\u0012\u0004\u0012\u0002H\u000c0\bH\u0000¢\u0006\u0004\b\u000f\u0010\u0010J\b\u0010\u0011\u001a\u00020\u0012H\u0002J\b\u0010\u0013\u001a\u00020\u0012H\u0002J\u000f\u0010\u0014\u001a\u0004\u0018\u00010\u0012H\u0002¢\u0006\u0002\u0010\u0015J\u000f\u0010\u0016\u001a\u0004\u0018\u00010\u0012H\u0002¢\u0006\u0002\u0010\u0015J\u0014\u0010\u0017\u001a\u00020\u00182\n\u0010\u000e\u001a\u0006\u0012\u0002\b\u00030\bH\u0016J&\u0010\u0019\u001a\b\u0012\u0004\u0012\u0002H\u000c0\u001a\"\b\b\u0000\u0010\u000c*\u00020\r2\u000c\u0010\u000e\u001a\b\u0012\u0004\u0012\u0002H\u000c0\bH\u0016J\b\u0010\u001b\u001a\u00020\u001cH\u0002J\u001a\u0010\u001d\u001a\u00020\u001e2\u0010\u0010\u001f\u001a\u000c\u0012\b\u0012\u0006\u0012\u0002\b\u00030\b0 H\u0016R\u000e\u0010\u0005\u001a\u00020\u0006X\u0082\u000e¢\u0006\u0002\n\u0000R\u0012\u0010\u0007\u001a\u0006\u0012\u0002\b\u00030\bX\u0082.¢\u0006\u0002\n\u0000R\u000e\u0010\u0002\u001a\u00020\u0003X\u0082\u0004¢\u0006\u0002\n\u0000R\u0012\u0010\t\u001a\u00060\nR\u00020\u0000X\u0082\u0004¢\u0006\u0002\n\u0000¨\u0006#"
   .end annotation
   d2 [ = .annotation array
      s = "Lcom/anatawa12/jasm/parser/Lexer;"
      s = "Lcom/anatawa12/jasm/parser/ILexer;"
      s = "reading"
      s = "Lcom/anatawa12/jasm/parser/Lexer\$Reader;"
      s = "(Lcom/anatawa12/jasm/parser/Lexer\$Reader;)V"
      s = "index"
      s = ""
      s = "lexing"
      s = "Lcom/anatawa12/jasm/parser/TokenType;"
      s = "tokenVisitor"
      s = "Lcom/anatawa12/jasm/parser/Lexer\$TokenVisitor;"
      s = "doRead"
      s = "T"
      s = ""
      s = "expect"
      s = "doRead\$jasm"
      s = "(Lcom/anatawa12/jasm/parser/TokenType;)Ljava/lang/Object;"
      s = "get"
      s = ""
      s = "getAndNext"
      s = "getAndNextOrNull"
      s = "()Ljava/lang/Character;"
      s = "getOrNull"
      s = "isNext"
      s = ""
      s = "readToken"
      s = "Lcom/anatawa12/jasm/tree/Token;"
      s = "skipSpace"
      s = ""
      s = "unexpectTokenErrorInternal"
      s = ""
      s = "expects"
      s = ""
      s = "Reader"
      s = "TokenVisitor"
      s = "jasm"
   .end annotation
.end annotation

.method public isNext (Lcom/anatawa12/jasm/parser/TokenType;)Z
   .signature "(Lcom/anatawa12/jasm/parser/TokenType<*>;)Z"
   .annotation invisiblepararm 0 org/jetbrains/annotations/NotNull
   .end annotation
   .limit stack 2
   .limit local 3
L_0000:
   .var 0 is this Lcom/anatawa12/jasm/parser/Lexer; from L_0000 to L_0026
   .var 1 is expect Lcom/anatawa12/jasm/parser/TokenType; from L_0000 to L_0026
   aload 1
   ldc "expect"
   invokestatic kotlin/jvm/internal/Intrinsics/checkParameterIsNotNull (Ljava/lang/Object;Ljava/lang/String;)V
L_0004:
   .line 9
   .catch com/anatawa12/jasm/parser/LexingError from L_0004 to L_001e using L_001e
   nop
L_0007:
   .line 10
   aload 0
   aload 1
   invokevirtual com/anatawa12/jasm/parser/Lexer/doRead$jasm (Lcom/anatawa12/jasm/parser/TokenType;)Ljava/lang/Object;
   astore 2
L_000d:
   .line 11
   .var 2 is result Ljava/lang/Object; from L_000d to L_001e
   aload 0
   iconst_0
   putfield com/anatawa12/jasm/parser/Lexer/index I
L_0012:
   .line 12
   aload 2
   ifnull L_0018
   iconst_1
   goto L_001b
L_0018:
   .stack
      locals Object com/anatawa12/jasm/parser/Lexer
      locals Object com/anatawa12/jasm/parser/TokenType
      locals Object java/lang/Object
   .end stack
   iconst_0
L_001b:
   .stack use locals
      stacks Integer
   .end stack
   ireturn
L_001e:
   .line 13
   .stack
      locals Object com/anatawa12/jasm/parser/Lexer
      locals Object com/anatawa12/jasm/parser/TokenType
      stacks Object com/anatawa12/jasm/parser/LexingError
   .end stack
   astore 2
L_0022:
   .line 14
   .var 2 is e Lcom/anatawa12/jasm/parser/LexingError; from L_0022 to L_0026
   iconst_0
   ireturn
L_0026:
.end method

.method public readToken (Lcom/anatawa12/jasm/parser/TokenType;)Lcom/anatawa12/jasm/tree/Token;
   .signature "<T:Ljava/lang/Object;>(Lcom/anatawa12/jasm/parser/TokenType<TT;>;)Lcom/anatawa12/jasm/tree/Token<TT;>;"
   .annotation invisible org/jetbrains/annotations/NotNull
   .end annotation
   .annotation invisiblepararm 0 org/jetbrains/annotations/NotNull
   .end annotation
   .limit stack 5
   .limit local 5
L_0000:
   .var 0 is this Lcom/anatawa12/jasm/parser/Lexer; from L_0000 to L_0041
   .var 1 is expect Lcom/anatawa12/jasm/parser/TokenType; from L_0000 to L_0041
   aload 1
   ldc "expect"
   invokestatic kotlin/jvm/internal/Intrinsics/checkParameterIsNotNull (Ljava/lang/Object;Ljava/lang/String;)V
L_0004:
   .line 19
   aload 0
   aload 1
   invokevirtual com/anatawa12/jasm/parser/Lexer/doRead$jasm (Lcom/anatawa12/jasm/parser/TokenType;)Ljava/lang/Object;
   dup
   ifnull L_000c
   goto L_001d
L_000c:
   .line 19
   .stack
      locals Object com/anatawa12/jasm/parser/Lexer
      locals Object com/anatawa12/jasm/parser/TokenType
      stacks Object java/lang/Object
   .end stack
   pop
   aload 0
   getfield com/anatawa12/jasm/parser/Lexer/reading Lcom/anatawa12/jasm/parser/Lexer$Reader;
   new java/lang/StringBuilder
   dup
   invokespecial java/lang/StringBuilder/<init> ()V
   ldc "unexpected token. expecting "
   invokevirtual java/lang/StringBuilder/append (Ljava/lang/String;)Ljava/lang/StringBuilder;
   aload 1
   invokevirtual java/lang/StringBuilder/append (Ljava/lang/Object;)Ljava/lang/StringBuilder;
   invokevirtual java/lang/StringBuilder/toString ()Ljava/lang/String;
   invokeinterface com/anatawa12/jasm/parser/Lexer$Reader/error (Ljava/lang/String;)Ljava/lang/Void;
   aconst_null
   athrow
L_001d:
   .stack use locals
      stacks Object java/lang/Object
   .end stack
   astore 2
L_0020:
   .line 20
   .var 2 is value Ljava/lang/Object; from L_0020 to L_0041
   aload 0
   getfield com/anatawa12/jasm/parser/Lexer/reading Lcom/anatawa12/jasm/parser/Lexer$Reader;
   invokeinterface com/anatawa12/jasm/parser/Lexer$Reader/getCharPosition ()Lcom/anatawa12/jasm/tree/CharPosition;
   astore 3
L_0026:
   .line 21
   .var 3 is start Lcom/anatawa12/jasm/tree/CharPosition; from L_0026 to L_0041
   aload 0
   getfield com/anatawa12/jasm/parser/Lexer/reading Lcom/anatawa12/jasm/parser/Lexer$Reader;
   aload 0
   getfield com/anatawa12/jasm/parser/Lexer/index I
   invokeinterface com/anatawa12/jasm/parser/Lexer$Reader/setCurrentTo (I)V
L_002d:
   .line 22
   aload 0
   iconst_0
   putfield com/anatawa12/jasm/parser/Lexer/index I
L_0032:
   .line 23
   aload 0
   getfield com/anatawa12/jasm/parser/Lexer/reading Lcom/anatawa12/jasm/parser/Lexer$Reader;
   invokeinterface com/anatawa12/jasm/parser/Lexer$Reader/getCharPosition ()Lcom/anatawa12/jasm/tree/CharPosition;
   astore 4
L_0038:
   .line 24
   .var 4 is end Lcom/anatawa12/jasm/tree/CharPosition; from L_0038 to L_0041
   new com/anatawa12/jasm/tree/Token
   dup
   aload 2
   aload 3
   aload 4
   invokespecial com/anatawa12/jasm/tree/Token/<init> (Ljava/lang/Object;Lcom/anatawa12/jasm/tree/CharPosition;Lcom/anatawa12/jasm/tree/CharPosition;)V
   areturn
L_0041:
.end method

.method private skipSpace ()V
   .limit stack 2
   .limit local 1
L_0000:
   .line 30
   .var 0 is this Lcom/anatawa12/jasm/parser/Lexer; from L_0000 to L_002c
   .stack
      locals Object com/anatawa12/jasm/parser/Lexer
   .end stack
   aload 0
   getfield com/anatawa12/jasm/parser/Lexer/reading Lcom/anatawa12/jasm/parser/Lexer$Reader;
   aload 0
   getfield com/anatawa12/jasm/parser/Lexer/index I
   invokeinterface com/anatawa12/jasm/parser/Lexer$Reader/getOrNull (I)Ljava/lang/Character;
   dup
   ifnull L_000f
   invokevirtual java/lang/Character/charValue ()C
   invokestatic kotlin/text/CharsKt/isWhitespace (C)Z
   iconst_1
   if_icmpne L_001c
   goto L_0013
L_000f:
   .stack use locals
      stacks Object java/lang/Character
   .end stack
   pop
   goto L_001c
L_0013:
   .line 31
   .stack use locals
   .end stack
   aload 0
   invokespecial com/anatawa12/jasm/parser/Lexer/getAndNext ()C
   pop
L_0019:
   .line 30
   goto L_0000
L_001c:
   .line 32
   .stack use locals
   .end stack
   aload 0
   getfield com/anatawa12/jasm/parser/Lexer/reading Lcom/anatawa12/jasm/parser/Lexer$Reader;
   aload 0
   getfield com/anatawa12/jasm/parser/Lexer/index I
   invokeinterface com/anatawa12/jasm/parser/Lexer$Reader/setCurrentTo (I)V
L_0024:
   .line 33
   aload 0
   iconst_0
   putfield com/anatawa12/jasm/parser/Lexer/index I
L_0029:
   .line 34
   return
L_002c:
.end method

.method private getAndNext ()C
   .limit stack 4
   .limit local 2
L_0000:
   .line 35
   .var 0 is this Lcom/anatawa12/jasm/parser/Lexer; from L_0000 to L_002d
   aload 0
   getfield com/anatawa12/jasm/parser/Lexer/reading Lcom/anatawa12/jasm/parser/Lexer$Reader;
   aload 0
   dup
   getfield com/anatawa12/jasm/parser/Lexer/index I
   dup
   istore 1
   iconst_1
   iadd
   putfield com/anatawa12/jasm/parser/Lexer/index I
   iload 1
   invokeinterface com/anatawa12/jasm/parser/Lexer$Reader/getOrNull (I)Ljava/lang/Character;
   dup
   ifnull L_0012
   invokevirtual java/lang/Character/charValue ()C
   goto L_002a
L_0012:
   .line 35
   .stack
      locals Object com/anatawa12/jasm/parser/Lexer
      locals Integer
      stacks Object java/lang/Character
   .end stack
   pop
   aload 0
   getfield com/anatawa12/jasm/parser/Lexer/reading Lcom/anatawa12/jasm/parser/Lexer$Reader;
   new java/lang/StringBuilder
   dup
   invokespecial java/lang/StringBuilder/<init> ()V
   ldc "unexpect eof in token: "
   invokevirtual java/lang/StringBuilder/append (Ljava/lang/String;)Ljava/lang/StringBuilder;
   aload 0
   getfield com/anatawa12/jasm/parser/Lexer/lexing Lcom/anatawa12/jasm/parser/TokenType;
   dup
   ifnonnull L_0023
   ldc "lexing"
   invokestatic kotlin/jvm/internal/Intrinsics/throwUninitializedPropertyAccessException (Ljava/lang/String;)V
L_0023:
   .stack use locals
      stacks Object com/anatawa12/jasm/parser/Lexer$Reader
      stacks Object java/lang/StringBuilder
      stacks Object com/anatawa12/jasm/parser/TokenType
   .end stack
   invokevirtual java/lang/StringBuilder/append (Ljava/lang/Object;)Ljava/lang/StringBuilder;
   invokevirtual java/lang/StringBuilder/toString ()Ljava/lang/String;
   invokeinterface com/anatawa12/jasm/parser/Lexer$Reader/error (Ljava/lang/String;)Ljava/lang/Void;
   aconst_null
   athrow
L_002a:
   .stack use locals
      stacks Integer
   .end stack
   ireturn
L_002d:
.end method

.method private getAndNextOrNull ()Ljava/lang/Character;
   .limit stack 4
   .limit local 2
L_0000:
   .line 36
   .var 0 is this Lcom/anatawa12/jasm/parser/Lexer; from L_0000 to L_000f
   aload 0
   getfield com/anatawa12/jasm/parser/Lexer/reading Lcom/anatawa12/jasm/parser/Lexer$Reader;
   aload 0
   dup
   getfield com/anatawa12/jasm/parser/Lexer/index I
   dup
   istore 1
   iconst_1
   iadd
   putfield com/anatawa12/jasm/parser/Lexer/index I
   iload 1
   invokeinterface com/anatawa12/jasm/parser/Lexer$Reader/getOrNull (I)Ljava/lang/Character;
   areturn
L_000f:
.end method

.method private get ()C
   .limit stack 4
   .limit local 1
L_0000:
   .line 37
   .var 0 is this Lcom/anatawa12/jasm/parser/Lexer; from L_0000 to L_0026
   aload 0
   getfield com/anatawa12/jasm/parser/Lexer/reading Lcom/anatawa12/jasm/parser/Lexer$Reader;
   aload 0
   getfield com/anatawa12/jasm/parser/Lexer/index I
   invokeinterface com/anatawa12/jasm/parser/Lexer$Reader/getOrNull (I)Ljava/lang/Character;
   dup
   ifnull L_000b
   invokevirtual java/lang/Character/charValue ()C
   goto L_0023
L_000b:
   .line 37
   .stack
      locals Object com/anatawa12/jasm/parser/Lexer
      stacks Object java/lang/Character
   .end stack
   pop
   aload 0
   getfield com/anatawa12/jasm/parser/Lexer/reading Lcom/anatawa12/jasm/parser/Lexer$Reader;
   new java/lang/StringBuilder
   dup
   invokespecial java/lang/StringBuilder/<init> ()V
   ldc "unexpect eof in token: "
   invokevirtual java/lang/StringBuilder/append (Ljava/lang/String;)Ljava/lang/StringBuilder;
   aload 0
   getfield com/anatawa12/jasm/parser/Lexer/lexing Lcom/anatawa12/jasm/parser/TokenType;
   dup
   ifnonnull L_001c
   ldc "lexing"
   invokestatic kotlin/jvm/internal/Intrinsics/throwUninitializedPropertyAccessException (Ljava/lang/String;)V
L_001c:
   .stack use locals
      stacks Object com/anatawa12/jasm/parser/Lexer$Reader
      stacks Object java/lang/StringBuilder
      stacks Object com/anatawa12/jasm/parser/TokenType
   .end stack
   invokevirtual java/lang/StringBuilder/append (Ljava/lang/Object;)Ljava/lang/StringBuilder;
   invokevirtual java/lang/StringBuilder/toString ()Ljava/lang/String;
   invokeinterface com/anatawa12/jasm/parser/Lexer$Reader/error (Ljava/lang/String;)Ljava/lang/Void;
   aconst_null
   athrow
L_0023:
   .stack use locals
      stacks Integer
   .end stack
   ireturn
L_0026:
.end method

.method private getOrNull ()Ljava/lang/Character;
   .limit stack 2
   .limit local 1
L_0000:
   .line 38
   .var 0 is this Lcom/anatawa12/jasm/parser/Lexer; from L_0000 to L_0008
   aload 0
   getfield com/anatawa12/jasm/parser/Lexer/reading Lcom/anatawa12/jasm/parser/Lexer$Reader;
   aload 0
   getfield com/anatawa12/jasm/parser/Lexer/index I
   invokeinterface com/anatawa12/jasm/parser/Lexer$Reader/getOrNull (I)Ljava/lang/Character;
   areturn
L_0008:
.end method

.method public unexpectTokenErrorInternal (Ljava/util/Set;)Ljava/lang/Void;
   .signature "(Ljava/util/Set<+Lcom/anatawa12/jasm/parser/TokenType<*>;>;)Ljava/lang/Void;"
   .annotation invisible org/jetbrains/annotations/NotNull
   .end annotation
   .annotation invisiblepararm 0 org/jetbrains/annotations/NotNull
   .end annotation
   .limit stack 11
   .limit local 2
L_0000:
   .var 0 is this Lcom/anatawa12/jasm/parser/Lexer; from L_0000 to L_001d
   .var 1 is expects Ljava/util/Set; from L_0000 to L_001d
   aload 1
   ldc "expects"
   invokestatic kotlin/jvm/internal/Intrinsics/checkParameterIsNotNull (Ljava/lang/Object;Ljava/lang/String;)V
L_0004:
   .line 40
   aload 0
   getfield com/anatawa12/jasm/parser/Lexer/reading Lcom/anatawa12/jasm/parser/Lexer$Reader;
   new java/lang/StringBuilder
   dup
   invokespecial java/lang/StringBuilder/<init> ()V
   ldc "unexpect token. expecting "
   invokevirtual java/lang/StringBuilder/append (Ljava/lang/String;)Ljava/lang/StringBuilder;
   aload 1
   checkcast java/lang/Iterable
   aconst_null
   aconst_null
   aconst_null
   iconst_0
   aconst_null
   aconst_null
   bipush 63
   aconst_null
   invokestatic kotlin/collections/CollectionsKt/joinToString$default (Ljava/lang/Iterable;Ljava/lang/CharSequence;Ljava/lang/CharSequence;Ljava/lang/CharSequence;ILjava/lang/CharSequence;Lkotlin/jvm/functions/Function1;ILjava/lang/Object;)Ljava/lang/String;
   invokevirtual java/lang/StringBuilder/append (Ljava/lang/String;)Ljava/lang/StringBuilder;
   invokevirtual java/lang/StringBuilder/toString ()Ljava/lang/String;
   invokeinterface com/anatawa12/jasm/parser/Lexer$Reader/error (Ljava/lang/String;)Ljava/lang/Void;
   aconst_null
   athrow
L_001d:
.end method

.method public doRead$jasm (Lcom/anatawa12/jasm/parser/TokenType;)Ljava/lang/Object;
   .signature "<T:Ljava/lang/Object;>(Lcom/anatawa12/jasm/parser/TokenType<TT;>;)TT;"
   .annotation invisible org/jetbrains/annotations/Nullable
   .end annotation
   .annotation invisiblepararm 0 org/jetbrains/annotations/NotNull
   .end annotation
   .limit stack 2
   .limit local 2
L_0000:
   .var 0 is this Lcom/anatawa12/jasm/parser/Lexer; from L_0000 to L_0015
   .var 1 is expect Lcom/anatawa12/jasm/parser/TokenType; from L_0000 to L_0015
   aload 1
   ldc "expect"
   invokestatic kotlin/jvm/internal/Intrinsics/checkParameterIsNotNull (Ljava/lang/Object;Ljava/lang/String;)V
L_0004:
   .line 395
   aload 0
   aload 1
   putfield com/anatawa12/jasm/parser/Lexer/lexing Lcom/anatawa12/jasm/parser/TokenType;
L_0009:
   .line 396
   aload 0
   invokespecial com/anatawa12/jasm/parser/Lexer/skipSpace ()V
L_000d:
   .line 397
   aload 1
   aload 0
   getfield com/anatawa12/jasm/parser/Lexer/tokenVisitor Lcom/anatawa12/jasm/parser/Lexer$TokenVisitor;
   checkcast com/anatawa12/jasm/parser/ITokenVisitorNullable
   invokevirtual com/anatawa12/jasm/parser/TokenType/accept (Lcom/anatawa12/jasm/parser/ITokenVisitorNullable;)Ljava/lang/Object;
   areturn
L_0015:
.end method

.method public <init> (Lcom/anatawa12/jasm/parser/Lexer$Reader;)V
   .annotation invisiblepararm 0 org/jetbrains/annotations/NotNull
   .end annotation
   .limit stack 4
   .limit local 2
L_0000:
   .var 0 is this Lcom/anatawa12/jasm/parser/Lexer; from L_0000 to L_0014
   .var 1 is reading Lcom/anatawa12/jasm/parser/Lexer$Reader; from L_0000 to L_0014
   aload 1
   ldc "reading"
   invokestatic kotlin/jvm/internal/Intrinsics/checkParameterIsNotNull (Ljava/lang/Object;Ljava/lang/String;)V
L_0004:
   .line 7
   aload 0
   invokespecial java/lang/Object/<init> ()V
   aload 0
   aload 1
   putfield com/anatawa12/jasm/parser/Lexer/reading Lcom/anatawa12/jasm/parser/Lexer$Reader;
L_000b:
   .line 42
   aload 0
   new com/anatawa12/jasm/parser/Lexer$TokenVisitor
   dup
   aload 0
   invokespecial com/anatawa12/jasm/parser/Lexer$TokenVisitor/<init> (Lcom/anatawa12/jasm/parser/Lexer;)V
   putfield com/anatawa12/jasm/parser/Lexer/tokenVisitor Lcom/anatawa12/jasm/parser/Lexer$TokenVisitor;
   return
L_0014:
.end method

.method public isNext (Ljava/util/Set;)Z
   .signature "(Ljava/util/Set<+Lcom/anatawa12/jasm/parser/TokenType<*>;>;)Z"
   .annotation invisiblepararm 0 org/jetbrains/annotations/NotNull
   .end annotation
   .limit stack 2
   .limit local 2
L_0000:
   .var 0 is this Lcom/anatawa12/jasm/parser/ILexer; from L_0000 to L_000a
   .var 1 is expect Ljava/util/Set; from L_0000 to L_000a
   aload 1
   ldc "expect"
   invokestatic kotlin/jvm/internal/Intrinsics/checkParameterIsNotNull (Ljava/lang/Object;Ljava/lang/String;)V
L_0004:
   .line 7
   aload 0
   aload 1
   invokestatic com/anatawa12/jasm/parser/ILexer$DefaultImpls/isNext (Lcom/anatawa12/jasm/parser/ILexer;Ljava/util/Set;)Z
   ireturn
L_000a:
.end method

.method public unexpectTokenError "([Lcom/anatawa12/jasm/parser/TokenType;)Ljava/lang/Void;"
   .signature "([Lcom/anatawa12/jasm/parser/TokenType<*>;)Ljava/lang/Void;"
   .annotation invisible org/jetbrains/annotations/NotNull
   .end annotation
   .annotation invisiblepararm 0 org/jetbrains/annotations/NotNull
   .end annotation
   .limit stack 2
   .limit local 2
L_0000:
   .var 0 is this Lcom/anatawa12/jasm/parser/ILexer; from L_0000 to L_000a
   .var 1 is expects "[Lcom/anatawa12/jasm/parser/TokenType;" from L_0000 to L_000a
   aload 1
   ldc "expects"
   invokestatic kotlin/jvm/internal/Intrinsics/checkParameterIsNotNull (Ljava/lang/Object;Ljava/lang/String;)V
L_0004:
   .line 7
   aload 0
   aload 1
   invokestatic com/anatawa12/jasm/parser/ILexer$DefaultImpls/unexpectTokenError "(Lcom/anatawa12/jasm/parser/ILexer;[Lcom/anatawa12/jasm/parser/TokenType;)Ljava/lang/Void;"
   areturn
L_000a:
.end method

.method public unexpectTokenError "([Ljava/util/Set;)Ljava/lang/Void;"
   .signature "([Ljava/util/Set<+Lcom/anatawa12/jasm/parser/TokenType<*>;>;)Ljava/lang/Void;"
   .annotation invisible org/jetbrains/annotations/NotNull
   .end annotation
   .annotation invisiblepararm 0 org/jetbrains/annotations/NotNull
   .end annotation
   .limit stack 2
   .limit local 2
L_0000:
   .var 0 is this Lcom/anatawa12/jasm/parser/ILexer; from L_0000 to L_000a
   .var 1 is expects "[Ljava/util/Set;" from L_0000 to L_000a
   aload 1
   ldc "expects"
   invokestatic kotlin/jvm/internal/Intrinsics/checkParameterIsNotNull (Ljava/lang/Object;Ljava/lang/String;)V
L_0004:
   .line 7
   aload 0
   aload 1
   invokestatic com/anatawa12/jasm/parser/ILexer$DefaultImpls/unexpectTokenError "(Lcom/anatawa12/jasm/parser/ILexer;[Ljava/util/Set;)Ljava/lang/Void;"
   areturn
L_000a:
.end method

.method public access$getAndNext (Lcom/anatawa12/jasm/parser/Lexer;)C
   .limit stack 1
   .limit local 1
L_0000:
   .line 7
   .var 0 is $this Lcom/anatawa12/jasm/parser/Lexer; from L_0000 to L_0005
   aload 0
   invokespecial com/anatawa12/jasm/parser/Lexer/getAndNext ()C
   ireturn
L_0005:
.end method

.method public access$getOrNull (Lcom/anatawa12/jasm/parser/Lexer;)Ljava/lang/Character;
   .limit stack 1
   .limit local 1
L_0000:
   .line 7
   .var 0 is $this Lcom/anatawa12/jasm/parser/Lexer; from L_0000 to L_0005
   aload 0
   invokespecial com/anatawa12/jasm/parser/Lexer/getOrNull ()Ljava/lang/Character;
   areturn
L_0005:
.end method

.method public access$get (Lcom/anatawa12/jasm/parser/Lexer;)C
   .limit stack 1
   .limit local 1
L_0000:
   .line 7
   .var 0 is $this Lcom/anatawa12/jasm/parser/Lexer; from L_0000 to L_0005
   aload 0
   invokespecial com/anatawa12/jasm/parser/Lexer/get ()C
   ireturn
L_0005:
.end method

.field private lexing Lcom/anatawa12/jasm/parser/TokenType;
   .signature "Lcom/anatawa12/jasm/parser/TokenType<*>;"
.end field

.field private index I
.end field

.field private tokenVisitor Lcom/anatawa12/jasm/parser/Lexer$TokenVisitor;
.end field

.field private reading Lcom/anatawa12/jasm/parser/Lexer$Reader;
.end field

