.bytecode 52.0
.source "Parser.kt"
.class public com/anatawa12/jasm/parser/Parser$Companion
.super java/lang/Object
.inner public com/anatawa12/jasm/parser/Parser$Companion inner Companion outer com/anatawa12/jasm/parser/Parser

.annotation visible kotlin/Metadata
   mv [ = .annotation array
      I = 1
      I = 1
      I = 16
   .end annotation
   bv [ = .annotation array
      I = 1
      I = 0
      I = 3
   .end annotation
   k I = 1
   d1 [ = .annotation array
      s = "\u0000%\n\u0002\u0018\u0002\n\u0002\u0010\u0000\n\u0002\b\u0002\n\u0002\u0018\u0002\n\u0002\b\u0007\n\u0002\u0018\u0002\n\u0002\b-\n\u0002\u0018\u0002\n\u0003\b§\u0001\b\u0086\u0003\u0018\u00002\u00020\u0001B\u0007\b\u0002¢\u0006\u0002\u0010\u0002R\u0011\u0010\u0003\u001a\u00020\u0004¢\u0006\b\n\u0000\u001a\u0004\b\u0005\u0010\u0006R\u0011\u0010\u0007\u001a\u00020\u0004¢\u0006\b\n\u0000\u001a\u0004\b\b\u0010\u0006R\u0011\u0010\t\u001a\u00020\u0004¢\u0006\b\n\u0000\u001a\u0004\b\n\u0010\u0006R\u0011\u0010\u000b\u001a\u00020\u000c¢\u0006\b\n\u0000\u001a\u0004\b\r\u0010\u000eR\u0011\u0010\u000f\u001a\u00020\u000c¢\u0006\b\n\u0000\u001a\u0004\b\u0010\u0010\u000eR\u0011\u0010\u0011\u001a\u00020\u000c¢\u0006\b\n\u0000\u001a\u0004\b\u0012\u0010\u000eR\u0011\u0010\u0013\u001a\u00020\u000c¢\u0006\b\n\u0000\u001a\u0004\b\u0014\u0010\u000eR\u0011\u0010\u0015\u001a\u00020\u000c¢\u0006\b\n\u0000\u001a\u0004\b\u0016\u0010\u000eR\u0011\u0010\u0017\u001a\u00020\u000c¢\u0006\b\n\u0000\u001a\u0004\b\u0018\u0010\u000eR\u0011\u0010\u0019\u001a\u00020\u000c¢\u0006\b\n\u0000\u001a\u0004\b\u001a\u0010\u000eR\u0011\u0010\u001b\u001a\u00020\u000c¢\u0006\b\n\u0000\u001a\u0004\b\u001c\u0010\u000eR\u0011\u0010\u001d\u001a\u00020\u000c¢\u0006\b\n\u0000\u001a\u0004\b\u001e\u0010\u000eR\u0011\u0010\u001f\u001a\u00020\u000c¢\u0006\b\n\u0000\u001a\u0004\b \u0010\u000eR\u0011\u0010!\u001a\u00020\u000c¢\u0006\b\n\u0000\u001a\u0004\b\"\u0010\u000eR\u0011\u0010#\u001a\u00020\u000c¢\u0006\b\n\u0000\u001a\u0004\b\$\u0010\u000eR\u0011\u0010%\u001a\u00020\u000c¢\u0006\b\n\u0000\u001a\u0004\b&\u0010\u000eR\u0011\u0010\'\u001a\u00020\u000c¢\u0006\b\n\u0000\u001a\u0004\b(\u0010\u000eR\u0011\u0010)\u001a\u00020\u000c¢\u0006\b\n\u0000\u001a\u0004\b*\u0010\u000eR\u0011\u0010+\u001a\u00020\u000c¢\u0006\b\n\u0000\u001a\u0004\b,\u0010\u000eR\u0011\u0010-\u001a\u00020\u000c¢\u0006\b\n\u0000\u001a\u0004\b.\u0010\u000eR\u0011\u0010/\u001a\u00020\u000c¢\u0006\b\n\u0000\u001a\u0004\b0\u0010\u000eR\u0011\u00101\u001a\u00020\u000c¢\u0006\b\n\u0000\u001a\u0004\b2\u0010\u000eR\u0011\u00103\u001a\u00020\u000c¢\u0006\b\n\u0000\u001a\u0004\b4\u0010\u000eR\u0011\u00105\u001a\u00020\u000c¢\u0006\b\n\u0000\u001a\u0004\b6\u0010\u000eR\u0011\u00107\u001a\u00020\u0004¢\u0006\b\n\u0000\u001a\u0004\b8\u0010\u0006R\u0011\u00109\u001a\u00020:¢\u0006\b\n\u0000\u001a\u0004\b;\u0010<R\u0011\u0010=\u001a\u00020:¢\u0006\b\n\u0000\u001a\u0004\b>\u0010<R\u0011\u0010?\u001a\u00020:¢\u0006\b\n\u0000\u001a\u0004\b@\u0010<R\u0011\u0010A\u001a\u00020:¢\u0006\b\n\u0000\u001a\u0004\bB\u0010<R\u0011\u0010C\u001a\u00020:¢\u0006\b\n\u0000\u001a\u0004\bD\u0010<R\u0011\u0010E\u001a\u00020:¢\u0006\b\n\u0000\u001a\u0004\bF\u0010<R\u0011\u0010G\u001a\u00020:¢\u0006\b\n\u0000\u001a\u0004\bH\u0010<R\u0011\u0010I\u001a\u00020:¢\u0006\b\n\u0000\u001a\u0004\bJ\u0010<R\u0011\u0010K\u001a\u00020:¢\u0006\b\n\u0000\u001a\u0004\bL\u0010<R\u0011\u0010M\u001a\u00020:¢\u0006\b\n\u0000\u001a\u0004\bN\u0010<R\u0011\u0010O\u001a\u00020:¢\u0006\b\n\u0000\u001a\u0004\bP\u0010<R\u0011\u0010Q\u001a\u00020:¢\u0006\b\n\u0000\u001a\u0004\bR\u0010<R\u0011\u0010S\u001a\u00020:¢\u0006\b\n\u0000\u001a\u0004\bT\u0010<R\u0011\u0010U\u001a\u00020:¢\u0006\b\n\u0000\u001a\u0004\bV\u0010<R\u0011\u0010W\u001a\u00020:¢\u0006\b\n\u0000\u001a\u0004\bX\u0010<R\u0011\u0010Y\u001a\u00020:¢\u0006\b\n\u0000\u001a\u0004\bZ\u0010<R\u0011\u0010[\u001a\u00020:¢\u0006\b\n\u0000\u001a\u0004\b\\\u0010<R\u0011\u0010]\u001a\u00020:¢\u0006\b\n\u0000\u001a\u0004\b^\u0010<R\u0011\u0010_\u001a\u00020:¢\u0006\b\n\u0000\u001a\u0004\b`\u0010<R\u0011\u0010a\u001a\u00020:¢\u0006\b\n\u0000\u001a\u0004\bb\u0010<R\u0011\u0010c\u001a\u00020:¢\u0006\b\n\u0000\u001a\u0004\bd\u0010<R\u0011\u0010e\u001a\u00020:¢\u0006\b\n\u0000\u001a\u0004\bf\u0010<R\u0011\u0010g\u001a\u00020:¢\u0006\b\n\u0000\u001a\u0004\bh\u0010<R\u0011\u0010i\u001a\u00020:¢\u0006\b\n\u0000\u001a\u0004\bj\u0010<R\u0011\u0010k\u001a\u00020:¢\u0006\b\n\u0000\u001a\u0004\bl\u0010<R\u0011\u0010m\u001a\u00020:¢\u0006\b\n\u0000\u001a\u0004\bn\u0010<R\u0011\u0010o\u001a\u00020:¢\u0006\b\n\u0000\u001a\u0004\bp\u0010<R\u0011\u0010q\u001a\u00020:¢\u0006\b\n\u0000\u001a\u0004\br\u0010<R\u0011\u0010s\u001a\u00020:¢\u0006\b\n\u0000\u001a\u0004\bt\u0010<R\u0011\u0010u\u001a\u00020:¢\u0006\b\n\u0000\u001a\u0004\bv\u0010<R\u0011\u0010w\u001a\u00020:¢\u0006\b\n\u0000\u001a\u0004\bx\u0010<R\u0011\u0010y\u001a\u00020:¢\u0006\b\n\u0000\u001a\u0004\bz\u0010<R\u0011\u0010{\u001a\u00020:¢\u0006\b\n\u0000\u001a\u0004\b|\u0010<R\u0011\u0010}\u001a\u00020:¢\u0006\b\n\u0000\u001a\u0004\b~\u0010<R\u0012\u0010\u007f\u001a\u00020:¢\u0006\t\n\u0000\u001a\u0005\b\u0080\u0001\u0010<R\u0013\u0010\u0081\u0001\u001a\u00020:¢\u0006\t\n\u0000\u001a\u0005\b\u0082\u0001\u0010<R\u0013\u0010\u0083\u0001\u001a\u00020:¢\u0006\t\n\u0000\u001a\u0005\b\u0084\u0001\u0010<R\u0013\u0010\u0085\u0001\u001a\u00020:¢\u0006\t\n\u0000\u001a\u0005\b\u0086\u0001\u0010<R\u0013\u0010\u0087\u0001\u001a\u00020:¢\u0006\t\n\u0000\u001a\u0005\b\u0088\u0001\u0010<R\u0013\u0010\u0089\u0001\u001a\u00020:¢\u0006\t\n\u0000\u001a\u0005\b\u008a\u0001\u0010<R\u0013\u0010\u008b\u0001\u001a\u00020:¢\u0006\t\n\u0000\u001a\u0005\b\u008c\u0001\u0010<R\u0013\u0010\u008d\u0001\u001a\u00020:¢\u0006\t\n\u0000\u001a\u0005\b\u008e\u0001\u0010<R\u0013\u0010\u008f\u0001\u001a\u00020:¢\u0006\t\n\u0000\u001a\u0005\b\u0090\u0001\u0010<R\u0013\u0010\u0091\u0001\u001a\u00020:¢\u0006\t\n\u0000\u001a\u0005\b\u0092\u0001\u0010<R\u0013\u0010\u0093\u0001\u001a\u00020:¢\u0006\t\n\u0000\u001a\u0005\b\u0094\u0001\u0010<R\u0013\u0010\u0095\u0001\u001a\u00020:¢\u0006\t\n\u0000\u001a\u0005\b\u0096\u0001\u0010<R\u0013\u0010\u0097\u0001\u001a\u00020:¢\u0006\t\n\u0000\u001a\u0005\b\u0098\u0001\u0010<R\u0013\u0010\u0099\u0001\u001a\u00020:¢\u0006\t\n\u0000\u001a\u0005\b\u009a\u0001\u0010<R\u0013\u0010\u009b\u0001\u001a\u00020:¢\u0006\t\n\u0000\u001a\u0005\b\u009c\u0001\u0010<R\u0013\u0010\u009d\u0001\u001a\u00020:¢\u0006\t\n\u0000\u001a\u0005\b\u009e\u0001\u0010<R\u0013\u0010\u009f\u0001\u001a\u00020:¢\u0006\t\n\u0000\u001a\u0005\b \u0001\u0010<R\u0013\u0010¡\u0001\u001a\u00020:¢\u0006\t\n\u0000\u001a\u0005\b¢\u0001\u0010<R\u0013\u0010£\u0001\u001a\u00020:¢\u0006\t\n\u0000\u001a\u0005\b¤\u0001\u0010<R\u0013\u0010¥\u0001\u001a\u00020:¢\u0006\t\n\u0000\u001a\u0005\b¦\u0001\u0010<R\u0013\u0010§\u0001\u001a\u00020:¢\u0006\t\n\u0000\u001a\u0005\b¨\u0001\u0010<R\u0013\u0010©\u0001\u001a\u00020:¢\u0006\t\n\u0000\u001a\u0005\bª\u0001\u0010<R\u0013\u0010«\u0001\u001a\u00020:¢\u0006\t\n\u0000\u001a\u0005\b¬\u0001\u0010<R\u0013\u0010\u00ad\u0001\u001a\u00020:¢\u0006\t\n\u0000\u001a\u0005\b®\u0001\u0010<R\u0013\u0010¯\u0001\u001a\u00020:¢\u0006\t\n\u0000\u001a\u0005\b°\u0001\u0010<R\u0013\u0010±\u0001\u001a\u00020:¢\u0006\t\n\u0000\u001a\u0005\b²\u0001\u0010<R\u0013\u0010³\u0001\u001a\u00020:¢\u0006\t\n\u0000\u001a\u0005\b´\u0001\u0010<R\u0013\u0010µ\u0001\u001a\u00020:¢\u0006\t\n\u0000\u001a\u0005\b¶\u0001\u0010<R\u0013\u0010·\u0001\u001a\u00020:¢\u0006\t\n\u0000\u001a\u0005\b¸\u0001\u0010<R\u0013\u0010¹\u0001\u001a\u00020:¢\u0006\t\n\u0000\u001a\u0005\bº\u0001\u0010<R\u0013\u0010»\u0001\u001a\u00020:¢\u0006\t\n\u0000\u001a\u0005\b¼\u0001\u0010<R\u0013\u0010½\u0001\u001a\u00020:¢\u0006\t\n\u0000\u001a\u0005\b¾\u0001\u0010<R\u0013\u0010¿\u0001\u001a\u00020:¢\u0006\t\n\u0000\u001a\u0005\bÀ\u0001\u0010<R\u0013\u0010Á\u0001\u001a\u00020:¢\u0006\t\n\u0000\u001a\u0005\bÂ\u0001\u0010<R\u0013\u0010Ã\u0001\u001a\u00020:¢\u0006\t\n\u0000\u001a\u0005\bÄ\u0001\u0010<R\u0013\u0010Å\u0001\u001a\u00020:¢\u0006\t\n\u0000\u001a\u0005\bÆ\u0001\u0010<R\u0013\u0010Ç\u0001\u001a\u00020\u0004¢\u0006\t\n\u0000\u001a\u0005\bÈ\u0001\u0010\u0006R\u0013\u0010É\u0001\u001a\u00020\u0004¢\u0006\t\n\u0000\u001a\u0005\bÊ\u0001\u0010\u0006R\u0013\u0010Ë\u0001\u001a\u00020\u0004¢\u0006\t\n\u0000\u001a\u0005\bÌ\u0001\u0010\u0006R\u0013\u0010Í\u0001\u001a\u00020\u0004¢\u0006\t\n\u0000\u001a\u0005\bÎ\u0001\u0010\u0006R\u0013\u0010Ï\u0001\u001a\u00020\u0004¢\u0006\t\n\u0000\u001a\u0005\bÐ\u0001\u0010\u0006R\u0013\u0010Ñ\u0001\u001a\u00020\u0004¢\u0006\t\n\u0000\u001a\u0005\bÒ\u0001\u0010\u0006R\u0013\u0010Ó\u0001\u001a\u00020\u0004¢\u0006\t\n\u0000\u001a\u0005\bÔ\u0001\u0010\u0006R\u0013\u0010Õ\u0001\u001a\u00020\u0004¢\u0006\t\n\u0000\u001a\u0005\bÖ\u0001\u0010\u0006R\u0013\u0010×\u0001\u001a\u00020\u0004¢\u0006\t\n\u0000\u001a\u0005\bØ\u0001\u0010\u0006R\u0013\u0010Ù\u0001\u001a\u00020\u0004¢\u0006\t\n\u0000\u001a\u0005\bÚ\u0001\u0010\u0006R\u0013\u0010Û\u0001\u001a\u00020\u0004¢\u0006\t\n\u0000\u001a\u0005\bÜ\u0001\u0010\u0006R\u0013\u0010Ý\u0001\u001a\u00020\u0004¢\u0006\t\n\u0000\u001a\u0005\bÞ\u0001\u0010\u0006R\u0013\u0010ß\u0001\u001a\u00020\u0004¢\u0006\t\n\u0000\u001a\u0005\bà\u0001\u0010\u0006¨\u0006á\u0001"
   .end annotation
   d2 [ = .annotation array
      s = "Lcom/anatawa12/jasm/parser/Parser\$Companion;"
      s = ""
      s = "()V"
      s = "asterisks"
      s = "Lcom/anatawa12/jasm/parser/TokenType\$Char;"
      s = "getAsterisks"
      s = "()Lcom/anatawa12/jasm/parser/TokenType\$Char;"
      s = "colon"
      s = "getColon"
      s = "dot"
      s = "getDot"
      s = "dotAnnotation"
      s = "Lcom/anatawa12/jasm/parser/TokenType\$DotedKeyWord;"
      s = "getDotAnnotation"
      s = "()Lcom/anatawa12/jasm/parser/TokenType\$DotedKeyWord;"
      s = "dotAutoline"
      s = "getDotAutoline"
      s = "dotBytecode"
      s = "getDotBytecode"
      s = "dotCatch"
      s = "getDotCatch"
      s = "dotClass"
      s = "getDotClass"
      s = "dotDebug"
      s = "getDotDebug"
      s = "dotDeprecated"
      s = "getDotDeprecated"
      s = "dotEnclosing"
      s = "getDotEnclosing"
      s = "dotEnd"
      s = "getDotEnd"
      s = "dotField"
      s = "getDotField"
      s = "dotImplements"
      s = "getDotImplements"
      s = "dotInner"
      s = "getDotInner"
      s = "dotLimit"
      s = "getDotLimit"
      s = "dotLine"
      s = "getDotLine"
      s = "dotMethod"
      s = "getDotMethod"
      s = "dotSignature"
      s = "getDotSignature"
      s = "dotSource"
      s = "getDotSource"
      s = "dotStack"
      s = "getDotStack"
      s = "dotSuper"
      s = "getDotSuper"
      s = "dotThrows"
      s = "getDotThrows"
      s = "dotVar"
      s = "getDotVar"
      s = "equal"
      s = "getEqual"
      s = "keyAbstract"
      s = "Lcom/anatawa12/jasm/parser/TokenType\$KeyWord;"
      s = "getKeyAbstract"
      s = "()Lcom/anatawa12/jasm/parser/TokenType\$KeyWord;"
      s = "keyAnnotation"
      s = "getKeyAnnotation"
      s = "keyArray"
      s = "getKeyArray"
      s = "keyBoolean"
      s = "getKeyBoolean"
      s = "keyBridge"
      s = "getKeyBridge"
      s = "keyByte"
      s = "getKeyByte"
      s = "keyChar"
      s = "getKeyChar"
      s = "keyClass"
      s = "getKeyClass"
      s = "keyDefault"
      s = "getKeyDefault"
      s = "keyDouble"
      s = "getKeyDouble"
      s = "keyEnum"
      s = "getKeyEnum"
      s = "keyFalse"
      s = "getKeyFalse"
      s = "keyField"
      s = "getKeyField"
      s = "keyFinal"
      s = "getKeyFinal"
      s = "keyFloat"
      s = "getKeyFloat"
      s = "keyFrom"
      s = "getKeyFrom"
      s = "keyGetField"
      s = "getKeyGetField"
      s = "keyGetStatic"
      s = "getKeyGetStatic"
      s = "keyHandle"
      s = "getKeyHandle"
      s = "keyInner"
      s = "getKeyInner"
      s = "keyInt"
      s = "getKeyInt"
      s = "keyInterface"
      s = "getKeyInterface"
      s = "keyInvisible"
      s = "getKeyInvisible"
      s = "keyInvisiblePararm"
      s = "getKeyInvisiblePararm"
      s = "keyInvokeInterface"
      s = "getKeyInvokeInterface"
      s = "keyInvokeSpecial"
      s = "getKeyInvokeSpecial"
      s = "keyInvokeStatic"
      s = "getKeyInvokeStatic"
      s = "keyInvokeVirtual"
      s = "getKeyInvokeVirtual"
      s = "keyIs"
      s = "getKeyIs"
      s = "keyLocal"
      s = "getKeyLocal"
      s = "keyLocals"
      s = "getKeyLocals"
      s = "keyLong"
      s = "getKeyLong"
      s = "keyMandated"
      s = "getKeyMandated"
      s = "keyMethod"
      s = "getKeyMethod"
      s = "keyMethodType"
      s = "getKeyMethodType"
      s = "keyNative"
      s = "getKeyNative"
      s = "keyNewInvokeSpecial"
      s = "getKeyNewInvokeSpecial"
      s = "keyOuter"
      s = "getKeyOuter"
      s = "keyPrivate"
      s = "getKeyPrivate"
      s = "keyProtected"
      s = "getKeyProtected"
      s = "keyPublic"
      s = "getKeyPublic"
      s = "keyPutField"
      s = "getKeyPutField"
      s = "keyPutStatic"
      s = "getKeyPutStatic"
      s = "keyShort"
      s = "getKeyShort"
      s = "keySignature"
      s = "getKeySignature"
      s = "keyStack"
      s = "getKeyStack"
      s = "keyStackDouble"
      s = "getKeyStackDouble"
      s = "keyStackFloat"
      s = "getKeyStackFloat"
      s = "keyStackInteger"
      s = "getKeyStackInteger"
      s = "keyStackLong"
      s = "getKeyStackLong"
      s = "keyStackNull"
      s = "getKeyStackNull"
      s = "keyStackObject"
      s = "getKeyStackObject"
      s = "keyStackTop"
      s = "getKeyStackTop"
      s = "keyStackUninitialized"
      s = "getKeyStackUninitialized"
      s = "keyStackUninitializedThis"
      s = "getKeyStackUninitializedThis"
      s = "keyStacks"
      s = "getKeyStacks"
      s = "keyStatic"
      s = "getKeyStatic"
      s = "keyStrict"
      s = "getKeyStrict"
      s = "keySuper"
      s = "getKeySuper"
      s = "keySynchronized"
      s = "getKeySynchronized"
      s = "keySynthetic"
      s = "getKeySynthetic"
      s = "keyTo"
      s = "getKeyTo"
      s = "keyTransient"
      s = "getKeyTransient"
      s = "keyTrue"
      s = "getKeyTrue"
      s = "keyUse"
      s = "getKeyUse"
      s = "keyUsing"
      s = "getKeyUsing"
      s = "keyVarargs"
      s = "getKeyVarargs"
      s = "keyVisible"
      s = "getKeyVisible"
      s = "keyVisiblePararm"
      s = "getKeyVisiblePararm"
      s = "keyVolatile"
      s = "getKeyVolatile"
      s = "v_Annotation"
      s = "getV_Annotation"
      s = "v_Array"
      s = "getV_Array"
      s = "v_Class"
      s = "getV_Class"
      s = "v_Enum"
      s = "getV_Enum"
      s = "v_String"
      s = "getV_String"
      s = "v_boolean"
      s = "getV_boolean"
      s = "v_byte"
      s = "getV_byte"
      s = "v_char"
      s = "getV_char"
      s = "v_double"
      s = "getV_double"
      s = "v_float"
      s = "getV_float"
      s = "v_int"
      s = "getV_int"
      s = "v_long"
      s = "getV_long"
      s = "v_short"
      s = "getV_short"
      s = "jasm"
   .end annotation
.end annotation

.method public getDotAutoline ()Lcom/anatawa12/jasm/parser/TokenType$DotedKeyWord;
   .annotation invisible org/jetbrains/annotations/NotNull
   .end annotation
   .limit stack 1
   .limit local 1
L_0000:
   .line 938
   .var 0 is this Lcom/anatawa12/jasm/parser/Parser$Companion; from L_0000 to L_0004
   invokestatic com/anatawa12/jasm/parser/Parser/access$getDotAutoline$cp ()Lcom/anatawa12/jasm/parser/TokenType$DotedKeyWord;
   areturn
L_0004:
.end method

.method public getDotBytecode ()Lcom/anatawa12/jasm/parser/TokenType$DotedKeyWord;
   .annotation invisible org/jetbrains/annotations/NotNull
   .end annotation
   .limit stack 1
   .limit local 1
L_0000:
   .line 939
   .var 0 is this Lcom/anatawa12/jasm/parser/Parser$Companion; from L_0000 to L_0004
   invokestatic com/anatawa12/jasm/parser/Parser/access$getDotBytecode$cp ()Lcom/anatawa12/jasm/parser/TokenType$DotedKeyWord;
   areturn
L_0004:
.end method

.method public getDotSource ()Lcom/anatawa12/jasm/parser/TokenType$DotedKeyWord;
   .annotation invisible org/jetbrains/annotations/NotNull
   .end annotation
   .limit stack 1
   .limit local 1
L_0000:
   .line 940
   .var 0 is this Lcom/anatawa12/jasm/parser/Parser$Companion; from L_0000 to L_0004
   invokestatic com/anatawa12/jasm/parser/Parser/access$getDotSource$cp ()Lcom/anatawa12/jasm/parser/TokenType$DotedKeyWord;
   areturn
L_0004:
.end method

.method public getDotClass ()Lcom/anatawa12/jasm/parser/TokenType$DotedKeyWord;
   .annotation invisible org/jetbrains/annotations/NotNull
   .end annotation
   .limit stack 1
   .limit local 1
L_0000:
   .line 941
   .var 0 is this Lcom/anatawa12/jasm/parser/Parser$Companion; from L_0000 to L_0004
   invokestatic com/anatawa12/jasm/parser/Parser/access$getDotClass$cp ()Lcom/anatawa12/jasm/parser/TokenType$DotedKeyWord;
   areturn
L_0004:
.end method

.method public getDotSuper ()Lcom/anatawa12/jasm/parser/TokenType$DotedKeyWord;
   .annotation invisible org/jetbrains/annotations/NotNull
   .end annotation
   .limit stack 1
   .limit local 1
L_0000:
   .line 942
   .var 0 is this Lcom/anatawa12/jasm/parser/Parser$Companion; from L_0000 to L_0004
   invokestatic com/anatawa12/jasm/parser/Parser/access$getDotSuper$cp ()Lcom/anatawa12/jasm/parser/TokenType$DotedKeyWord;
   areturn
L_0004:
.end method

.method public getDotImplements ()Lcom/anatawa12/jasm/parser/TokenType$DotedKeyWord;
   .annotation invisible org/jetbrains/annotations/NotNull
   .end annotation
   .limit stack 1
   .limit local 1
L_0000:
   .line 943
   .var 0 is this Lcom/anatawa12/jasm/parser/Parser$Companion; from L_0000 to L_0004
   invokestatic com/anatawa12/jasm/parser/Parser/access$getDotImplements$cp ()Lcom/anatawa12/jasm/parser/TokenType$DotedKeyWord;
   areturn
L_0004:
.end method

.method public getDotSignature ()Lcom/anatawa12/jasm/parser/TokenType$DotedKeyWord;
   .annotation invisible org/jetbrains/annotations/NotNull
   .end annotation
   .limit stack 1
   .limit local 1
L_0000:
   .line 944
   .var 0 is this Lcom/anatawa12/jasm/parser/Parser$Companion; from L_0000 to L_0004
   invokestatic com/anatawa12/jasm/parser/Parser/access$getDotSignature$cp ()Lcom/anatawa12/jasm/parser/TokenType$DotedKeyWord;
   areturn
L_0004:
.end method

.method public getDotEnclosing ()Lcom/anatawa12/jasm/parser/TokenType$DotedKeyWord;
   .annotation invisible org/jetbrains/annotations/NotNull
   .end annotation
   .limit stack 1
   .limit local 1
L_0000:
   .line 945
   .var 0 is this Lcom/anatawa12/jasm/parser/Parser$Companion; from L_0000 to L_0004
   invokestatic com/anatawa12/jasm/parser/Parser/access$getDotEnclosing$cp ()Lcom/anatawa12/jasm/parser/TokenType$DotedKeyWord;
   areturn
L_0004:
.end method

.method public getDotDebug ()Lcom/anatawa12/jasm/parser/TokenType$DotedKeyWord;
   .annotation invisible org/jetbrains/annotations/NotNull
   .end annotation
   .limit stack 1
   .limit local 1
L_0000:
   .line 946
   .var 0 is this Lcom/anatawa12/jasm/parser/Parser$Companion; from L_0000 to L_0004
   invokestatic com/anatawa12/jasm/parser/Parser/access$getDotDebug$cp ()Lcom/anatawa12/jasm/parser/TokenType$DotedKeyWord;
   areturn
L_0004:
.end method

.method public getDotInner ()Lcom/anatawa12/jasm/parser/TokenType$DotedKeyWord;
   .annotation invisible org/jetbrains/annotations/NotNull
   .end annotation
   .limit stack 1
   .limit local 1
L_0000:
   .line 947
   .var 0 is this Lcom/anatawa12/jasm/parser/Parser$Companion; from L_0000 to L_0004
   invokestatic com/anatawa12/jasm/parser/Parser/access$getDotInner$cp ()Lcom/anatawa12/jasm/parser/TokenType$DotedKeyWord;
   areturn
L_0004:
.end method

.method public getDotMethod ()Lcom/anatawa12/jasm/parser/TokenType$DotedKeyWord;
   .annotation invisible org/jetbrains/annotations/NotNull
   .end annotation
   .limit stack 1
   .limit local 1
L_0000:
   .line 948
   .var 0 is this Lcom/anatawa12/jasm/parser/Parser$Companion; from L_0000 to L_0004
   invokestatic com/anatawa12/jasm/parser/Parser/access$getDotMethod$cp ()Lcom/anatawa12/jasm/parser/TokenType$DotedKeyWord;
   areturn
L_0004:
.end method

.method public getDotEnd ()Lcom/anatawa12/jasm/parser/TokenType$DotedKeyWord;
   .annotation invisible org/jetbrains/annotations/NotNull
   .end annotation
   .limit stack 1
   .limit local 1
L_0000:
   .line 949
   .var 0 is this Lcom/anatawa12/jasm/parser/Parser$Companion; from L_0000 to L_0004
   invokestatic com/anatawa12/jasm/parser/Parser/access$getDotEnd$cp ()Lcom/anatawa12/jasm/parser/TokenType$DotedKeyWord;
   areturn
L_0004:
.end method

.method public getDotLimit ()Lcom/anatawa12/jasm/parser/TokenType$DotedKeyWord;
   .annotation invisible org/jetbrains/annotations/NotNull
   .end annotation
   .limit stack 1
   .limit local 1
L_0000:
   .line 950
   .var 0 is this Lcom/anatawa12/jasm/parser/Parser$Companion; from L_0000 to L_0004
   invokestatic com/anatawa12/jasm/parser/Parser/access$getDotLimit$cp ()Lcom/anatawa12/jasm/parser/TokenType$DotedKeyWord;
   areturn
L_0004:
.end method

.method public getDotLine ()Lcom/anatawa12/jasm/parser/TokenType$DotedKeyWord;
   .annotation invisible org/jetbrains/annotations/NotNull
   .end annotation
   .limit stack 1
   .limit local 1
L_0000:
   .line 951
   .var 0 is this Lcom/anatawa12/jasm/parser/Parser$Companion; from L_0000 to L_0004
   invokestatic com/anatawa12/jasm/parser/Parser/access$getDotLine$cp ()Lcom/anatawa12/jasm/parser/TokenType$DotedKeyWord;
   areturn
L_0004:
.end method

.method public getDotVar ()Lcom/anatawa12/jasm/parser/TokenType$DotedKeyWord;
   .annotation invisible org/jetbrains/annotations/NotNull
   .end annotation
   .limit stack 1
   .limit local 1
L_0000:
   .line 952
   .var 0 is this Lcom/anatawa12/jasm/parser/Parser$Companion; from L_0000 to L_0004
   invokestatic com/anatawa12/jasm/parser/Parser/access$getDotVar$cp ()Lcom/anatawa12/jasm/parser/TokenType$DotedKeyWord;
   areturn
L_0004:
.end method

.method public getDotThrows ()Lcom/anatawa12/jasm/parser/TokenType$DotedKeyWord;
   .annotation invisible org/jetbrains/annotations/NotNull
   .end annotation
   .limit stack 1
   .limit local 1
L_0000:
   .line 953
   .var 0 is this Lcom/anatawa12/jasm/parser/Parser$Companion; from L_0000 to L_0004
   invokestatic com/anatawa12/jasm/parser/Parser/access$getDotThrows$cp ()Lcom/anatawa12/jasm/parser/TokenType$DotedKeyWord;
   areturn
L_0004:
.end method

.method public getDotCatch ()Lcom/anatawa12/jasm/parser/TokenType$DotedKeyWord;
   .annotation invisible org/jetbrains/annotations/NotNull
   .end annotation
   .limit stack 1
   .limit local 1
L_0000:
   .line 954
   .var 0 is this Lcom/anatawa12/jasm/parser/Parser$Companion; from L_0000 to L_0004
   invokestatic com/anatawa12/jasm/parser/Parser/access$getDotCatch$cp ()Lcom/anatawa12/jasm/parser/TokenType$DotedKeyWord;
   areturn
L_0004:
.end method

.method public getDotDeprecated ()Lcom/anatawa12/jasm/parser/TokenType$DotedKeyWord;
   .annotation invisible org/jetbrains/annotations/NotNull
   .end annotation
   .limit stack 1
   .limit local 1
L_0000:
   .line 955
   .var 0 is this Lcom/anatawa12/jasm/parser/Parser$Companion; from L_0000 to L_0004
   invokestatic com/anatawa12/jasm/parser/Parser/access$getDotDeprecated$cp ()Lcom/anatawa12/jasm/parser/TokenType$DotedKeyWord;
   areturn
L_0004:
.end method

.method public getDotStack ()Lcom/anatawa12/jasm/parser/TokenType$DotedKeyWord;
   .annotation invisible org/jetbrains/annotations/NotNull
   .end annotation
   .limit stack 1
   .limit local 1
L_0000:
   .line 956
   .var 0 is this Lcom/anatawa12/jasm/parser/Parser$Companion; from L_0000 to L_0004
   invokestatic com/anatawa12/jasm/parser/Parser/access$getDotStack$cp ()Lcom/anatawa12/jasm/parser/TokenType$DotedKeyWord;
   areturn
L_0004:
.end method

.method public getDotAnnotation ()Lcom/anatawa12/jasm/parser/TokenType$DotedKeyWord;
   .annotation invisible org/jetbrains/annotations/NotNull
   .end annotation
   .limit stack 1
   .limit local 1
L_0000:
   .line 957
   .var 0 is this Lcom/anatawa12/jasm/parser/Parser$Companion; from L_0000 to L_0004
   invokestatic com/anatawa12/jasm/parser/Parser/access$getDotAnnotation$cp ()Lcom/anatawa12/jasm/parser/TokenType$DotedKeyWord;
   areturn
L_0004:
.end method

.method public getDotField ()Lcom/anatawa12/jasm/parser/TokenType$DotedKeyWord;
   .annotation invisible org/jetbrains/annotations/NotNull
   .end annotation
   .limit stack 1
   .limit local 1
L_0000:
   .line 958
   .var 0 is this Lcom/anatawa12/jasm/parser/Parser$Companion; from L_0000 to L_0004
   invokestatic com/anatawa12/jasm/parser/Parser/access$getDotField$cp ()Lcom/anatawa12/jasm/parser/TokenType$DotedKeyWord;
   areturn
L_0004:
.end method

.method public getKeyTrue ()Lcom/anatawa12/jasm/parser/TokenType$KeyWord;
   .annotation invisible org/jetbrains/annotations/NotNull
   .end annotation
   .limit stack 1
   .limit local 1
L_0000:
   .line 960
   .var 0 is this Lcom/anatawa12/jasm/parser/Parser$Companion; from L_0000 to L_0004
   invokestatic com/anatawa12/jasm/parser/Parser/access$getKeyTrue$cp ()Lcom/anatawa12/jasm/parser/TokenType$KeyWord;
   areturn
L_0004:
.end method

.method public getKeyFalse ()Lcom/anatawa12/jasm/parser/TokenType$KeyWord;
   .annotation invisible org/jetbrains/annotations/NotNull
   .end annotation
   .limit stack 1
   .limit local 1
L_0000:
   .line 961
   .var 0 is this Lcom/anatawa12/jasm/parser/Parser$Companion; from L_0000 to L_0004
   invokestatic com/anatawa12/jasm/parser/Parser/access$getKeyFalse$cp ()Lcom/anatawa12/jasm/parser/TokenType$KeyWord;
   areturn
L_0004:
.end method

.method public getKeyMethod ()Lcom/anatawa12/jasm/parser/TokenType$KeyWord;
   .annotation invisible org/jetbrains/annotations/NotNull
   .end annotation
   .limit stack 1
   .limit local 1
L_0000:
   .line 963
   .var 0 is this Lcom/anatawa12/jasm/parser/Parser$Companion; from L_0000 to L_0004
   invokestatic com/anatawa12/jasm/parser/Parser/access$getKeyMethod$cp ()Lcom/anatawa12/jasm/parser/TokenType$KeyWord;
   areturn
L_0004:
.end method

.method public getKeyClass ()Lcom/anatawa12/jasm/parser/TokenType$KeyWord;
   .annotation invisible org/jetbrains/annotations/NotNull
   .end annotation
   .limit stack 1
   .limit local 1
L_0000:
   .line 964
   .var 0 is this Lcom/anatawa12/jasm/parser/Parser$Companion; from L_0000 to L_0004
   invokestatic com/anatawa12/jasm/parser/Parser/access$getKeyClass$cp ()Lcom/anatawa12/jasm/parser/TokenType$KeyWord;
   areturn
L_0004:
.end method

.method public getKeyInner ()Lcom/anatawa12/jasm/parser/TokenType$KeyWord;
   .annotation invisible org/jetbrains/annotations/NotNull
   .end annotation
   .limit stack 1
   .limit local 1
L_0000:
   .line 965
   .var 0 is this Lcom/anatawa12/jasm/parser/Parser$Companion; from L_0000 to L_0004
   invokestatic com/anatawa12/jasm/parser/Parser/access$getKeyInner$cp ()Lcom/anatawa12/jasm/parser/TokenType$KeyWord;
   areturn
L_0004:
.end method

.method public getKeyOuter ()Lcom/anatawa12/jasm/parser/TokenType$KeyWord;
   .annotation invisible org/jetbrains/annotations/NotNull
   .end annotation
   .limit stack 1
   .limit local 1
L_0000:
   .line 966
   .var 0 is this Lcom/anatawa12/jasm/parser/Parser$Companion; from L_0000 to L_0004
   invokestatic com/anatawa12/jasm/parser/Parser/access$getKeyOuter$cp ()Lcom/anatawa12/jasm/parser/TokenType$KeyWord;
   areturn
L_0004:
.end method

.method public getKeyStack ()Lcom/anatawa12/jasm/parser/TokenType$KeyWord;
   .annotation invisible org/jetbrains/annotations/NotNull
   .end annotation
   .limit stack 1
   .limit local 1
L_0000:
   .line 967
   .var 0 is this Lcom/anatawa12/jasm/parser/Parser$Companion; from L_0000 to L_0004
   invokestatic com/anatawa12/jasm/parser/Parser/access$getKeyStack$cp ()Lcom/anatawa12/jasm/parser/TokenType$KeyWord;
   areturn
L_0004:
.end method

.method public getKeyLocal ()Lcom/anatawa12/jasm/parser/TokenType$KeyWord;
   .annotation invisible org/jetbrains/annotations/NotNull
   .end annotation
   .limit stack 1
   .limit local 1
L_0000:
   .line 968
   .var 0 is this Lcom/anatawa12/jasm/parser/Parser$Companion; from L_0000 to L_0004
   invokestatic com/anatawa12/jasm/parser/Parser/access$getKeyLocal$cp ()Lcom/anatawa12/jasm/parser/TokenType$KeyWord;
   areturn
L_0004:
.end method

.method public getKeyIs ()Lcom/anatawa12/jasm/parser/TokenType$KeyWord;
   .annotation invisible org/jetbrains/annotations/NotNull
   .end annotation
   .limit stack 1
   .limit local 1
L_0000:
   .line 969
   .var 0 is this Lcom/anatawa12/jasm/parser/Parser$Companion; from L_0000 to L_0004
   invokestatic com/anatawa12/jasm/parser/Parser/access$getKeyIs$cp ()Lcom/anatawa12/jasm/parser/TokenType$KeyWord;
   areturn
L_0004:
.end method

.method public getKeySignature ()Lcom/anatawa12/jasm/parser/TokenType$KeyWord;
   .annotation invisible org/jetbrains/annotations/NotNull
   .end annotation
   .limit stack 1
   .limit local 1
L_0000:
   .line 970
   .var 0 is this Lcom/anatawa12/jasm/parser/Parser$Companion; from L_0000 to L_0004
   invokestatic com/anatawa12/jasm/parser/Parser/access$getKeySignature$cp ()Lcom/anatawa12/jasm/parser/TokenType$KeyWord;
   areturn
L_0004:
.end method

.method public getKeyFrom ()Lcom/anatawa12/jasm/parser/TokenType$KeyWord;
   .annotation invisible org/jetbrains/annotations/NotNull
   .end annotation
   .limit stack 1
   .limit local 1
L_0000:
   .line 971
   .var 0 is this Lcom/anatawa12/jasm/parser/Parser$Companion; from L_0000 to L_0004
   invokestatic com/anatawa12/jasm/parser/Parser/access$getKeyFrom$cp ()Lcom/anatawa12/jasm/parser/TokenType$KeyWord;
   areturn
L_0004:
.end method

.method public getKeyTo ()Lcom/anatawa12/jasm/parser/TokenType$KeyWord;
   .annotation invisible org/jetbrains/annotations/NotNull
   .end annotation
   .limit stack 1
   .limit local 1
L_0000:
   .line 972
   .var 0 is this Lcom/anatawa12/jasm/parser/Parser$Companion; from L_0000 to L_0004
   invokestatic com/anatawa12/jasm/parser/Parser/access$getKeyTo$cp ()Lcom/anatawa12/jasm/parser/TokenType$KeyWord;
   areturn
L_0004:
.end method

.method public getKeyUsing ()Lcom/anatawa12/jasm/parser/TokenType$KeyWord;
   .annotation invisible org/jetbrains/annotations/NotNull
   .end annotation
   .limit stack 1
   .limit local 1
L_0000:
   .line 973
   .var 0 is this Lcom/anatawa12/jasm/parser/Parser$Companion; from L_0000 to L_0004
   invokestatic com/anatawa12/jasm/parser/Parser/access$getKeyUsing$cp ()Lcom/anatawa12/jasm/parser/TokenType$KeyWord;
   areturn
L_0004:
.end method

.method public getKeyField ()Lcom/anatawa12/jasm/parser/TokenType$KeyWord;
   .annotation invisible org/jetbrains/annotations/NotNull
   .end annotation
   .limit stack 1
   .limit local 1
L_0000:
   .line 974
   .var 0 is this Lcom/anatawa12/jasm/parser/Parser$Companion; from L_0000 to L_0004
   invokestatic com/anatawa12/jasm/parser/Parser/access$getKeyField$cp ()Lcom/anatawa12/jasm/parser/TokenType$KeyWord;
   areturn
L_0004:
.end method

.method public getKeyHandle ()Lcom/anatawa12/jasm/parser/TokenType$KeyWord;
   .annotation invisible org/jetbrains/annotations/NotNull
   .end annotation
   .limit stack 1
   .limit local 1
L_0000:
   .line 975
   .var 0 is this Lcom/anatawa12/jasm/parser/Parser$Companion; from L_0000 to L_0004
   invokestatic com/anatawa12/jasm/parser/Parser/access$getKeyHandle$cp ()Lcom/anatawa12/jasm/parser/TokenType$KeyWord;
   areturn
L_0004:
.end method

.method public getKeyMethodType ()Lcom/anatawa12/jasm/parser/TokenType$KeyWord;
   .annotation invisible org/jetbrains/annotations/NotNull
   .end annotation
   .limit stack 1
   .limit local 1
L_0000:
   .line 976
   .var 0 is this Lcom/anatawa12/jasm/parser/Parser$Companion; from L_0000 to L_0004
   invokestatic com/anatawa12/jasm/parser/Parser/access$getKeyMethodType$cp ()Lcom/anatawa12/jasm/parser/TokenType$KeyWord;
   areturn
L_0004:
.end method

.method public getKeyUse ()Lcom/anatawa12/jasm/parser/TokenType$KeyWord;
   .annotation invisible org/jetbrains/annotations/NotNull
   .end annotation
   .limit stack 1
   .limit local 1
L_0000:
   .line 978
   .var 0 is this Lcom/anatawa12/jasm/parser/Parser$Companion; from L_0000 to L_0004
   invokestatic com/anatawa12/jasm/parser/Parser/access$getKeyUse$cp ()Lcom/anatawa12/jasm/parser/TokenType$KeyWord;
   areturn
L_0004:
.end method

.method public getKeyLocals ()Lcom/anatawa12/jasm/parser/TokenType$KeyWord;
   .annotation invisible org/jetbrains/annotations/NotNull
   .end annotation
   .limit stack 1
   .limit local 1
L_0000:
   .line 979
   .var 0 is this Lcom/anatawa12/jasm/parser/Parser$Companion; from L_0000 to L_0004
   invokestatic com/anatawa12/jasm/parser/Parser/access$getKeyLocals$cp ()Lcom/anatawa12/jasm/parser/TokenType$KeyWord;
   areturn
L_0004:
.end method

.method public getKeyStacks ()Lcom/anatawa12/jasm/parser/TokenType$KeyWord;
   .annotation invisible org/jetbrains/annotations/NotNull
   .end annotation
   .limit stack 1
   .limit local 1
L_0000:
   .line 980
   .var 0 is this Lcom/anatawa12/jasm/parser/Parser$Companion; from L_0000 to L_0004
   invokestatic com/anatawa12/jasm/parser/Parser/access$getKeyStacks$cp ()Lcom/anatawa12/jasm/parser/TokenType$KeyWord;
   areturn
L_0004:
.end method

.method public getKeyDefault ()Lcom/anatawa12/jasm/parser/TokenType$KeyWord;
   .annotation invisible org/jetbrains/annotations/NotNull
   .end annotation
   .limit stack 1
   .limit local 1
L_0000:
   .line 981
   .var 0 is this Lcom/anatawa12/jasm/parser/Parser$Companion; from L_0000 to L_0004
   invokestatic com/anatawa12/jasm/parser/Parser/access$getKeyDefault$cp ()Lcom/anatawa12/jasm/parser/TokenType$KeyWord;
   areturn
L_0004:
.end method

.method public getKeyGetField ()Lcom/anatawa12/jasm/parser/TokenType$KeyWord;
   .annotation invisible org/jetbrains/annotations/NotNull
   .end annotation
   .limit stack 1
   .limit local 1
L_0000:
   .line 984
   .var 0 is this Lcom/anatawa12/jasm/parser/Parser$Companion; from L_0000 to L_0004
   invokestatic com/anatawa12/jasm/parser/Parser/access$getKeyGetField$cp ()Lcom/anatawa12/jasm/parser/TokenType$KeyWord;
   areturn
L_0004:
.end method

.method public getKeyGetStatic ()Lcom/anatawa12/jasm/parser/TokenType$KeyWord;
   .annotation invisible org/jetbrains/annotations/NotNull
   .end annotation
   .limit stack 1
   .limit local 1
L_0000:
   .line 985
   .var 0 is this Lcom/anatawa12/jasm/parser/Parser$Companion; from L_0000 to L_0004
   invokestatic com/anatawa12/jasm/parser/Parser/access$getKeyGetStatic$cp ()Lcom/anatawa12/jasm/parser/TokenType$KeyWord;
   areturn
L_0004:
.end method

.method public getKeyPutField ()Lcom/anatawa12/jasm/parser/TokenType$KeyWord;
   .annotation invisible org/jetbrains/annotations/NotNull
   .end annotation
   .limit stack 1
   .limit local 1
L_0000:
   .line 986
   .var 0 is this Lcom/anatawa12/jasm/parser/Parser$Companion; from L_0000 to L_0004
   invokestatic com/anatawa12/jasm/parser/Parser/access$getKeyPutField$cp ()Lcom/anatawa12/jasm/parser/TokenType$KeyWord;
   areturn
L_0004:
.end method

.method public getKeyPutStatic ()Lcom/anatawa12/jasm/parser/TokenType$KeyWord;
   .annotation invisible org/jetbrains/annotations/NotNull
   .end annotation
   .limit stack 1
   .limit local 1
L_0000:
   .line 987
   .var 0 is this Lcom/anatawa12/jasm/parser/Parser$Companion; from L_0000 to L_0004
   invokestatic com/anatawa12/jasm/parser/Parser/access$getKeyPutStatic$cp ()Lcom/anatawa12/jasm/parser/TokenType$KeyWord;
   areturn
L_0004:
.end method

.method public getKeyInvokeVirtual ()Lcom/anatawa12/jasm/parser/TokenType$KeyWord;
   .annotation invisible org/jetbrains/annotations/NotNull
   .end annotation
   .limit stack 1
   .limit local 1
L_0000:
   .line 988
   .var 0 is this Lcom/anatawa12/jasm/parser/Parser$Companion; from L_0000 to L_0004
   invokestatic com/anatawa12/jasm/parser/Parser/access$getKeyInvokeVirtual$cp ()Lcom/anatawa12/jasm/parser/TokenType$KeyWord;
   areturn
L_0004:
.end method

.method public getKeyInvokeStatic ()Lcom/anatawa12/jasm/parser/TokenType$KeyWord;
   .annotation invisible org/jetbrains/annotations/NotNull
   .end annotation
   .limit stack 1
   .limit local 1
L_0000:
   .line 989
   .var 0 is this Lcom/anatawa12/jasm/parser/Parser$Companion; from L_0000 to L_0004
   invokestatic com/anatawa12/jasm/parser/Parser/access$getKeyInvokeStatic$cp ()Lcom/anatawa12/jasm/parser/TokenType$KeyWord;
   areturn
L_0004:
.end method

.method public getKeyInvokeSpecial ()Lcom/anatawa12/jasm/parser/TokenType$KeyWord;
   .annotation invisible org/jetbrains/annotations/NotNull
   .end annotation
   .limit stack 1
   .limit local 1
L_0000:
   .line 990
   .var 0 is this Lcom/anatawa12/jasm/parser/Parser$Companion; from L_0000 to L_0004
   invokestatic com/anatawa12/jasm/parser/Parser/access$getKeyInvokeSpecial$cp ()Lcom/anatawa12/jasm/parser/TokenType$KeyWord;
   areturn
L_0004:
.end method

.method public getKeyNewInvokeSpecial ()Lcom/anatawa12/jasm/parser/TokenType$KeyWord;
   .annotation invisible org/jetbrains/annotations/NotNull
   .end annotation
   .limit stack 1
   .limit local 1
L_0000:
   .line 991
   .var 0 is this Lcom/anatawa12/jasm/parser/Parser$Companion; from L_0000 to L_0004
   invokestatic com/anatawa12/jasm/parser/Parser/access$getKeyNewInvokeSpecial$cp ()Lcom/anatawa12/jasm/parser/TokenType$KeyWord;
   areturn
L_0004:
.end method

.method public getKeyInvokeInterface ()Lcom/anatawa12/jasm/parser/TokenType$KeyWord;
   .annotation invisible org/jetbrains/annotations/NotNull
   .end annotation
   .limit stack 1
   .limit local 1
L_0000:
   .line 992
   .var 0 is this Lcom/anatawa12/jasm/parser/Parser$Companion; from L_0000 to L_0004
   invokestatic com/anatawa12/jasm/parser/Parser/access$getKeyInvokeInterface$cp ()Lcom/anatawa12/jasm/parser/TokenType$KeyWord;
   areturn
L_0004:
.end method

.method public getKeyVisible ()Lcom/anatawa12/jasm/parser/TokenType$KeyWord;
   .annotation invisible org/jetbrains/annotations/NotNull
   .end annotation
   .limit stack 1
   .limit local 1
L_0000:
   .line 995
   .var 0 is this Lcom/anatawa12/jasm/parser/Parser$Companion; from L_0000 to L_0004
   invokestatic com/anatawa12/jasm/parser/Parser/access$getKeyVisible$cp ()Lcom/anatawa12/jasm/parser/TokenType$KeyWord;
   areturn
L_0004:
.end method

.method public getKeyInvisible ()Lcom/anatawa12/jasm/parser/TokenType$KeyWord;
   .annotation invisible org/jetbrains/annotations/NotNull
   .end annotation
   .limit stack 1
   .limit local 1
L_0000:
   .line 996
   .var 0 is this Lcom/anatawa12/jasm/parser/Parser$Companion; from L_0000 to L_0004
   invokestatic com/anatawa12/jasm/parser/Parser/access$getKeyInvisible$cp ()Lcom/anatawa12/jasm/parser/TokenType$KeyWord;
   areturn
L_0004:
.end method

.method public getKeyVisiblePararm ()Lcom/anatawa12/jasm/parser/TokenType$KeyWord;
   .annotation invisible org/jetbrains/annotations/NotNull
   .end annotation
   .limit stack 1
   .limit local 1
L_0000:
   .line 997
   .var 0 is this Lcom/anatawa12/jasm/parser/Parser$Companion; from L_0000 to L_0004
   invokestatic com/anatawa12/jasm/parser/Parser/access$getKeyVisiblePararm$cp ()Lcom/anatawa12/jasm/parser/TokenType$KeyWord;
   areturn
L_0004:
.end method

.method public getKeyInvisiblePararm ()Lcom/anatawa12/jasm/parser/TokenType$KeyWord;
   .annotation invisible org/jetbrains/annotations/NotNull
   .end annotation
   .limit stack 1
   .limit local 1
L_0000:
   .line 998
   .var 0 is this Lcom/anatawa12/jasm/parser/Parser$Companion; from L_0000 to L_0004
   invokestatic com/anatawa12/jasm/parser/Parser/access$getKeyInvisiblePararm$cp ()Lcom/anatawa12/jasm/parser/TokenType$KeyWord;
   areturn
L_0004:
.end method

.method public getKeyStackTop ()Lcom/anatawa12/jasm/parser/TokenType$KeyWord;
   .annotation invisible org/jetbrains/annotations/NotNull
   .end annotation
   .limit stack 1
   .limit local 1
L_0000:
   .line 1001
   .var 0 is this Lcom/anatawa12/jasm/parser/Parser$Companion; from L_0000 to L_0004
   invokestatic com/anatawa12/jasm/parser/Parser/access$getKeyStackTop$cp ()Lcom/anatawa12/jasm/parser/TokenType$KeyWord;
   areturn
L_0004:
.end method

.method public getKeyStackInteger ()Lcom/anatawa12/jasm/parser/TokenType$KeyWord;
   .annotation invisible org/jetbrains/annotations/NotNull
   .end annotation
   .limit stack 1
   .limit local 1
L_0000:
   .line 1002
   .var 0 is this Lcom/anatawa12/jasm/parser/Parser$Companion; from L_0000 to L_0004
   invokestatic com/anatawa12/jasm/parser/Parser/access$getKeyStackInteger$cp ()Lcom/anatawa12/jasm/parser/TokenType$KeyWord;
   areturn
L_0004:
.end method

.method public getKeyStackFloat ()Lcom/anatawa12/jasm/parser/TokenType$KeyWord;
   .annotation invisible org/jetbrains/annotations/NotNull
   .end annotation
   .limit stack 1
   .limit local 1
L_0000:
   .line 1003
   .var 0 is this Lcom/anatawa12/jasm/parser/Parser$Companion; from L_0000 to L_0004
   invokestatic com/anatawa12/jasm/parser/Parser/access$getKeyStackFloat$cp ()Lcom/anatawa12/jasm/parser/TokenType$KeyWord;
   areturn
L_0004:
.end method

.method public getKeyStackLong ()Lcom/anatawa12/jasm/parser/TokenType$KeyWord;
   .annotation invisible org/jetbrains/annotations/NotNull
   .end annotation
   .limit stack 1
   .limit local 1
L_0000:
   .line 1004
   .var 0 is this Lcom/anatawa12/jasm/parser/Parser$Companion; from L_0000 to L_0004
   invokestatic com/anatawa12/jasm/parser/Parser/access$getKeyStackLong$cp ()Lcom/anatawa12/jasm/parser/TokenType$KeyWord;
   areturn
L_0004:
.end method

.method public getKeyStackDouble ()Lcom/anatawa12/jasm/parser/TokenType$KeyWord;
   .annotation invisible org/jetbrains/annotations/NotNull
   .end annotation
   .limit stack 1
   .limit local 1
L_0000:
   .line 1005
   .var 0 is this Lcom/anatawa12/jasm/parser/Parser$Companion; from L_0000 to L_0004
   invokestatic com/anatawa12/jasm/parser/Parser/access$getKeyStackDouble$cp ()Lcom/anatawa12/jasm/parser/TokenType$KeyWord;
   areturn
L_0004:
.end method

.method public getKeyStackNull ()Lcom/anatawa12/jasm/parser/TokenType$KeyWord;
   .annotation invisible org/jetbrains/annotations/NotNull
   .end annotation
   .limit stack 1
   .limit local 1
L_0000:
   .line 1006
   .var 0 is this Lcom/anatawa12/jasm/parser/Parser$Companion; from L_0000 to L_0004
   invokestatic com/anatawa12/jasm/parser/Parser/access$getKeyStackNull$cp ()Lcom/anatawa12/jasm/parser/TokenType$KeyWord;
   areturn
L_0004:
.end method

.method public getKeyStackUninitializedThis ()Lcom/anatawa12/jasm/parser/TokenType$KeyWord;
   .annotation invisible org/jetbrains/annotations/NotNull
   .end annotation
   .limit stack 1
   .limit local 1
L_0000:
   .line 1007
   .var 0 is this Lcom/anatawa12/jasm/parser/Parser$Companion; from L_0000 to L_0004
   invokestatic com/anatawa12/jasm/parser/Parser/access$getKeyStackUninitializedThis$cp ()Lcom/anatawa12/jasm/parser/TokenType$KeyWord;
   areturn
L_0004:
.end method

.method public getKeyStackObject ()Lcom/anatawa12/jasm/parser/TokenType$KeyWord;
   .annotation invisible org/jetbrains/annotations/NotNull
   .end annotation
   .limit stack 1
   .limit local 1
L_0000:
   .line 1008
   .var 0 is this Lcom/anatawa12/jasm/parser/Parser$Companion; from L_0000 to L_0004
   invokestatic com/anatawa12/jasm/parser/Parser/access$getKeyStackObject$cp ()Lcom/anatawa12/jasm/parser/TokenType$KeyWord;
   areturn
L_0004:
.end method

.method public getKeyStackUninitialized ()Lcom/anatawa12/jasm/parser/TokenType$KeyWord;
   .annotation invisible org/jetbrains/annotations/NotNull
   .end annotation
   .limit stack 1
   .limit local 1
L_0000:
   .line 1009
   .var 0 is this Lcom/anatawa12/jasm/parser/Parser$Companion; from L_0000 to L_0004
   invokestatic com/anatawa12/jasm/parser/Parser/access$getKeyStackUninitialized$cp ()Lcom/anatawa12/jasm/parser/TokenType$KeyWord;
   areturn
L_0004:
.end method

.method public getKeyBoolean ()Lcom/anatawa12/jasm/parser/TokenType$KeyWord;
   .annotation invisible org/jetbrains/annotations/NotNull
   .end annotation
   .limit stack 1
   .limit local 1
L_0000:
   .line 1011
   .var 0 is this Lcom/anatawa12/jasm/parser/Parser$Companion; from L_0000 to L_0004
   invokestatic com/anatawa12/jasm/parser/Parser/access$getKeyBoolean$cp ()Lcom/anatawa12/jasm/parser/TokenType$KeyWord;
   areturn
L_0004:
.end method

.method public getKeyChar ()Lcom/anatawa12/jasm/parser/TokenType$KeyWord;
   .annotation invisible org/jetbrains/annotations/NotNull
   .end annotation
   .limit stack 1
   .limit local 1
L_0000:
   .line 1012
   .var 0 is this Lcom/anatawa12/jasm/parser/Parser$Companion; from L_0000 to L_0004
   invokestatic com/anatawa12/jasm/parser/Parser/access$getKeyChar$cp ()Lcom/anatawa12/jasm/parser/TokenType$KeyWord;
   areturn
L_0004:
.end method

.method public getKeyFloat ()Lcom/anatawa12/jasm/parser/TokenType$KeyWord;
   .annotation invisible org/jetbrains/annotations/NotNull
   .end annotation
   .limit stack 1
   .limit local 1
L_0000:
   .line 1013
   .var 0 is this Lcom/anatawa12/jasm/parser/Parser$Companion; from L_0000 to L_0004
   invokestatic com/anatawa12/jasm/parser/Parser/access$getKeyFloat$cp ()Lcom/anatawa12/jasm/parser/TokenType$KeyWord;
   areturn
L_0004:
.end method

.method public getKeyDouble ()Lcom/anatawa12/jasm/parser/TokenType$KeyWord;
   .annotation invisible org/jetbrains/annotations/NotNull
   .end annotation
   .limit stack 1
   .limit local 1
L_0000:
   .line 1014
   .var 0 is this Lcom/anatawa12/jasm/parser/Parser$Companion; from L_0000 to L_0004
   invokestatic com/anatawa12/jasm/parser/Parser/access$getKeyDouble$cp ()Lcom/anatawa12/jasm/parser/TokenType$KeyWord;
   areturn
L_0004:
.end method

.method public getKeyByte ()Lcom/anatawa12/jasm/parser/TokenType$KeyWord;
   .annotation invisible org/jetbrains/annotations/NotNull
   .end annotation
   .limit stack 1
   .limit local 1
L_0000:
   .line 1015
   .var 0 is this Lcom/anatawa12/jasm/parser/Parser$Companion; from L_0000 to L_0004
   invokestatic com/anatawa12/jasm/parser/Parser/access$getKeyByte$cp ()Lcom/anatawa12/jasm/parser/TokenType$KeyWord;
   areturn
L_0004:
.end method

.method public getKeyShort ()Lcom/anatawa12/jasm/parser/TokenType$KeyWord;
   .annotation invisible org/jetbrains/annotations/NotNull
   .end annotation
   .limit stack 1
   .limit local 1
L_0000:
   .line 1016
   .var 0 is this Lcom/anatawa12/jasm/parser/Parser$Companion; from L_0000 to L_0004
   invokestatic com/anatawa12/jasm/parser/Parser/access$getKeyShort$cp ()Lcom/anatawa12/jasm/parser/TokenType$KeyWord;
   areturn
L_0004:
.end method

.method public getKeyInt ()Lcom/anatawa12/jasm/parser/TokenType$KeyWord;
   .annotation invisible org/jetbrains/annotations/NotNull
   .end annotation
   .limit stack 1
   .limit local 1
L_0000:
   .line 1017
   .var 0 is this Lcom/anatawa12/jasm/parser/Parser$Companion; from L_0000 to L_0004
   invokestatic com/anatawa12/jasm/parser/Parser/access$getKeyInt$cp ()Lcom/anatawa12/jasm/parser/TokenType$KeyWord;
   areturn
L_0004:
.end method

.method public getKeyLong ()Lcom/anatawa12/jasm/parser/TokenType$KeyWord;
   .annotation invisible org/jetbrains/annotations/NotNull
   .end annotation
   .limit stack 1
   .limit local 1
L_0000:
   .line 1018
   .var 0 is this Lcom/anatawa12/jasm/parser/Parser$Companion; from L_0000 to L_0004
   invokestatic com/anatawa12/jasm/parser/Parser/access$getKeyLong$cp ()Lcom/anatawa12/jasm/parser/TokenType$KeyWord;
   areturn
L_0004:
.end method

.method public getKeyPublic ()Lcom/anatawa12/jasm/parser/TokenType$KeyWord;
   .annotation invisible org/jetbrains/annotations/NotNull
   .end annotation
   .limit stack 1
   .limit local 1
L_0000:
   .line 1020
   .var 0 is this Lcom/anatawa12/jasm/parser/Parser$Companion; from L_0000 to L_0004
   invokestatic com/anatawa12/jasm/parser/Parser/access$getKeyPublic$cp ()Lcom/anatawa12/jasm/parser/TokenType$KeyWord;
   areturn
L_0004:
.end method

.method public getKeyPrivate ()Lcom/anatawa12/jasm/parser/TokenType$KeyWord;
   .annotation invisible org/jetbrains/annotations/NotNull
   .end annotation
   .limit stack 1
   .limit local 1
L_0000:
   .line 1021
   .var 0 is this Lcom/anatawa12/jasm/parser/Parser$Companion; from L_0000 to L_0004
   invokestatic com/anatawa12/jasm/parser/Parser/access$getKeyPrivate$cp ()Lcom/anatawa12/jasm/parser/TokenType$KeyWord;
   areturn
L_0004:
.end method

.method public getKeyProtected ()Lcom/anatawa12/jasm/parser/TokenType$KeyWord;
   .annotation invisible org/jetbrains/annotations/NotNull
   .end annotation
   .limit stack 1
   .limit local 1
L_0000:
   .line 1022
   .var 0 is this Lcom/anatawa12/jasm/parser/Parser$Companion; from L_0000 to L_0004
   invokestatic com/anatawa12/jasm/parser/Parser/access$getKeyProtected$cp ()Lcom/anatawa12/jasm/parser/TokenType$KeyWord;
   areturn
L_0004:
.end method

.method public getKeyStatic ()Lcom/anatawa12/jasm/parser/TokenType$KeyWord;
   .annotation invisible org/jetbrains/annotations/NotNull
   .end annotation
   .limit stack 1
   .limit local 1
L_0000:
   .line 1023
   .var 0 is this Lcom/anatawa12/jasm/parser/Parser$Companion; from L_0000 to L_0004
   invokestatic com/anatawa12/jasm/parser/Parser/access$getKeyStatic$cp ()Lcom/anatawa12/jasm/parser/TokenType$KeyWord;
   areturn
L_0004:
.end method

.method public getKeyFinal ()Lcom/anatawa12/jasm/parser/TokenType$KeyWord;
   .annotation invisible org/jetbrains/annotations/NotNull
   .end annotation
   .limit stack 1
   .limit local 1
L_0000:
   .line 1024
   .var 0 is this Lcom/anatawa12/jasm/parser/Parser$Companion; from L_0000 to L_0004
   invokestatic com/anatawa12/jasm/parser/Parser/access$getKeyFinal$cp ()Lcom/anatawa12/jasm/parser/TokenType$KeyWord;
   areturn
L_0004:
.end method

.method public getKeySuper ()Lcom/anatawa12/jasm/parser/TokenType$KeyWord;
   .annotation invisible org/jetbrains/annotations/NotNull
   .end annotation
   .limit stack 1
   .limit local 1
L_0000:
   .line 1025
   .var 0 is this Lcom/anatawa12/jasm/parser/Parser$Companion; from L_0000 to L_0004
   invokestatic com/anatawa12/jasm/parser/Parser/access$getKeySuper$cp ()Lcom/anatawa12/jasm/parser/TokenType$KeyWord;
   areturn
L_0004:
.end method

.method public getKeySynchronized ()Lcom/anatawa12/jasm/parser/TokenType$KeyWord;
   .annotation invisible org/jetbrains/annotations/NotNull
   .end annotation
   .limit stack 1
   .limit local 1
L_0000:
   .line 1026
   .var 0 is this Lcom/anatawa12/jasm/parser/Parser$Companion; from L_0000 to L_0004
   invokestatic com/anatawa12/jasm/parser/Parser/access$getKeySynchronized$cp ()Lcom/anatawa12/jasm/parser/TokenType$KeyWord;
   areturn
L_0004:
.end method

.method public getKeyVolatile ()Lcom/anatawa12/jasm/parser/TokenType$KeyWord;
   .annotation invisible org/jetbrains/annotations/NotNull
   .end annotation
   .limit stack 1
   .limit local 1
L_0000:
   .line 1027
   .var 0 is this Lcom/anatawa12/jasm/parser/Parser$Companion; from L_0000 to L_0004
   invokestatic com/anatawa12/jasm/parser/Parser/access$getKeyVolatile$cp ()Lcom/anatawa12/jasm/parser/TokenType$KeyWord;
   areturn
L_0004:
.end method

.method public getKeyBridge ()Lcom/anatawa12/jasm/parser/TokenType$KeyWord;
   .annotation invisible org/jetbrains/annotations/NotNull
   .end annotation
   .limit stack 1
   .limit local 1
L_0000:
   .line 1028
   .var 0 is this Lcom/anatawa12/jasm/parser/Parser$Companion; from L_0000 to L_0004
   invokestatic com/anatawa12/jasm/parser/Parser/access$getKeyBridge$cp ()Lcom/anatawa12/jasm/parser/TokenType$KeyWord;
   areturn
L_0004:
.end method

.method public getKeyVarargs ()Lcom/anatawa12/jasm/parser/TokenType$KeyWord;
   .annotation invisible org/jetbrains/annotations/NotNull
   .end annotation
   .limit stack 1
   .limit local 1
L_0000:
   .line 1029
   .var 0 is this Lcom/anatawa12/jasm/parser/Parser$Companion; from L_0000 to L_0004
   invokestatic com/anatawa12/jasm/parser/Parser/access$getKeyVarargs$cp ()Lcom/anatawa12/jasm/parser/TokenType$KeyWord;
   areturn
L_0004:
.end method

.method public getKeyTransient ()Lcom/anatawa12/jasm/parser/TokenType$KeyWord;
   .annotation invisible org/jetbrains/annotations/NotNull
   .end annotation
   .limit stack 1
   .limit local 1
L_0000:
   .line 1030
   .var 0 is this Lcom/anatawa12/jasm/parser/Parser$Companion; from L_0000 to L_0004
   invokestatic com/anatawa12/jasm/parser/Parser/access$getKeyTransient$cp ()Lcom/anatawa12/jasm/parser/TokenType$KeyWord;
   areturn
L_0004:
.end method

.method public getKeyNative ()Lcom/anatawa12/jasm/parser/TokenType$KeyWord;
   .annotation invisible org/jetbrains/annotations/NotNull
   .end annotation
   .limit stack 1
   .limit local 1
L_0000:
   .line 1031
   .var 0 is this Lcom/anatawa12/jasm/parser/Parser$Companion; from L_0000 to L_0004
   invokestatic com/anatawa12/jasm/parser/Parser/access$getKeyNative$cp ()Lcom/anatawa12/jasm/parser/TokenType$KeyWord;
   areturn
L_0004:
.end method

.method public getKeyInterface ()Lcom/anatawa12/jasm/parser/TokenType$KeyWord;
   .annotation invisible org/jetbrains/annotations/NotNull
   .end annotation
   .limit stack 1
   .limit local 1
L_0000:
   .line 1032
   .var 0 is this Lcom/anatawa12/jasm/parser/Parser$Companion; from L_0000 to L_0004
   invokestatic com/anatawa12/jasm/parser/Parser/access$getKeyInterface$cp ()Lcom/anatawa12/jasm/parser/TokenType$KeyWord;
   areturn
L_0004:
.end method

.method public getKeyAbstract ()Lcom/anatawa12/jasm/parser/TokenType$KeyWord;
   .annotation invisible org/jetbrains/annotations/NotNull
   .end annotation
   .limit stack 1
   .limit local 1
L_0000:
   .line 1033
   .var 0 is this Lcom/anatawa12/jasm/parser/Parser$Companion; from L_0000 to L_0004
   invokestatic com/anatawa12/jasm/parser/Parser/access$getKeyAbstract$cp ()Lcom/anatawa12/jasm/parser/TokenType$KeyWord;
   areturn
L_0004:
.end method

.method public getKeyStrict ()Lcom/anatawa12/jasm/parser/TokenType$KeyWord;
   .annotation invisible org/jetbrains/annotations/NotNull
   .end annotation
   .limit stack 1
   .limit local 1
L_0000:
   .line 1034
   .var 0 is this Lcom/anatawa12/jasm/parser/Parser$Companion; from L_0000 to L_0004
   invokestatic com/anatawa12/jasm/parser/Parser/access$getKeyStrict$cp ()Lcom/anatawa12/jasm/parser/TokenType$KeyWord;
   areturn
L_0004:
.end method

.method public getKeySynthetic ()Lcom/anatawa12/jasm/parser/TokenType$KeyWord;
   .annotation invisible org/jetbrains/annotations/NotNull
   .end annotation
   .limit stack 1
   .limit local 1
L_0000:
   .line 1035
   .var 0 is this Lcom/anatawa12/jasm/parser/Parser$Companion; from L_0000 to L_0004
   invokestatic com/anatawa12/jasm/parser/Parser/access$getKeySynthetic$cp ()Lcom/anatawa12/jasm/parser/TokenType$KeyWord;
   areturn
L_0004:
.end method

.method public getKeyArray ()Lcom/anatawa12/jasm/parser/TokenType$KeyWord;
   .annotation invisible org/jetbrains/annotations/NotNull
   .end annotation
   .limit stack 1
   .limit local 1
L_0000:
   .line 1036
   .var 0 is this Lcom/anatawa12/jasm/parser/Parser$Companion; from L_0000 to L_0004
   invokestatic com/anatawa12/jasm/parser/Parser/access$getKeyArray$cp ()Lcom/anatawa12/jasm/parser/TokenType$KeyWord;
   areturn
L_0004:
.end method

.method public getKeyAnnotation ()Lcom/anatawa12/jasm/parser/TokenType$KeyWord;
   .annotation invisible org/jetbrains/annotations/NotNull
   .end annotation
   .limit stack 1
   .limit local 1
L_0000:
   .line 1037
   .var 0 is this Lcom/anatawa12/jasm/parser/Parser$Companion; from L_0000 to L_0004
   invokestatic com/anatawa12/jasm/parser/Parser/access$getKeyAnnotation$cp ()Lcom/anatawa12/jasm/parser/TokenType$KeyWord;
   areturn
L_0004:
.end method

.method public getKeyEnum ()Lcom/anatawa12/jasm/parser/TokenType$KeyWord;
   .annotation invisible org/jetbrains/annotations/NotNull
   .end annotation
   .limit stack 1
   .limit local 1
L_0000:
   .line 1038
   .var 0 is this Lcom/anatawa12/jasm/parser/Parser$Companion; from L_0000 to L_0004
   invokestatic com/anatawa12/jasm/parser/Parser/access$getKeyEnum$cp ()Lcom/anatawa12/jasm/parser/TokenType$KeyWord;
   areturn
L_0004:
.end method

.method public getKeyMandated ()Lcom/anatawa12/jasm/parser/TokenType$KeyWord;
   .annotation invisible org/jetbrains/annotations/NotNull
   .end annotation
   .limit stack 1
   .limit local 1
L_0000:
   .line 1039
   .var 0 is this Lcom/anatawa12/jasm/parser/Parser$Companion; from L_0000 to L_0004
   invokestatic com/anatawa12/jasm/parser/Parser/access$getKeyMandated$cp ()Lcom/anatawa12/jasm/parser/TokenType$KeyWord;
   areturn
L_0004:
.end method

.method public getColon ()Lcom/anatawa12/jasm/parser/TokenType$Char;
   .annotation invisible org/jetbrains/annotations/NotNull
   .end annotation
   .limit stack 1
   .limit local 1
L_0000:
   .line 1041
   .var 0 is this Lcom/anatawa12/jasm/parser/Parser$Companion; from L_0000 to L_0004
   invokestatic com/anatawa12/jasm/parser/Parser/access$getColon$cp ()Lcom/anatawa12/jasm/parser/TokenType$Char;
   areturn
L_0004:
.end method

.method public getEqual ()Lcom/anatawa12/jasm/parser/TokenType$Char;
   .annotation invisible org/jetbrains/annotations/NotNull
   .end annotation
   .limit stack 1
   .limit local 1
L_0000:
   .line 1042
   .var 0 is this Lcom/anatawa12/jasm/parser/Parser$Companion; from L_0000 to L_0004
   invokestatic com/anatawa12/jasm/parser/Parser/access$getEqual$cp ()Lcom/anatawa12/jasm/parser/TokenType$Char;
   areturn
L_0004:
.end method

.method public getDot ()Lcom/anatawa12/jasm/parser/TokenType$Char;
   .annotation invisible org/jetbrains/annotations/NotNull
   .end annotation
   .limit stack 1
   .limit local 1
L_0000:
   .line 1043
   .var 0 is this Lcom/anatawa12/jasm/parser/Parser$Companion; from L_0000 to L_0004
   invokestatic com/anatawa12/jasm/parser/Parser/access$getDot$cp ()Lcom/anatawa12/jasm/parser/TokenType$Char;
   areturn
L_0004:
.end method

.method public getAsterisks ()Lcom/anatawa12/jasm/parser/TokenType$Char;
   .annotation invisible org/jetbrains/annotations/NotNull
   .end annotation
   .limit stack 1
   .limit local 1
L_0000:
   .line 1044
   .var 0 is this Lcom/anatawa12/jasm/parser/Parser$Companion; from L_0000 to L_0004
   invokestatic com/anatawa12/jasm/parser/Parser/access$getAsterisks$cp ()Lcom/anatawa12/jasm/parser/TokenType$Char;
   areturn
L_0004:
.end method

.method public getV_byte ()Lcom/anatawa12/jasm/parser/TokenType$Char;
   .annotation invisible org/jetbrains/annotations/NotNull
   .end annotation
   .limit stack 1
   .limit local 1
L_0000:
   .line 1047
   .var 0 is this Lcom/anatawa12/jasm/parser/Parser$Companion; from L_0000 to L_0004
   invokestatic com/anatawa12/jasm/parser/Parser/access$getV_byte$cp ()Lcom/anatawa12/jasm/parser/TokenType$Char;
   areturn
L_0004:
.end method

.method public getV_char ()Lcom/anatawa12/jasm/parser/TokenType$Char;
   .annotation invisible org/jetbrains/annotations/NotNull
   .end annotation
   .limit stack 1
   .limit local 1
L_0000:
   .line 1048
   .var 0 is this Lcom/anatawa12/jasm/parser/Parser$Companion; from L_0000 to L_0004
   invokestatic com/anatawa12/jasm/parser/Parser/access$getV_char$cp ()Lcom/anatawa12/jasm/parser/TokenType$Char;
   areturn
L_0004:
.end method

.method public getV_double ()Lcom/anatawa12/jasm/parser/TokenType$Char;
   .annotation invisible org/jetbrains/annotations/NotNull
   .end annotation
   .limit stack 1
   .limit local 1
L_0000:
   .line 1049
   .var 0 is this Lcom/anatawa12/jasm/parser/Parser$Companion; from L_0000 to L_0004
   invokestatic com/anatawa12/jasm/parser/Parser/access$getV_double$cp ()Lcom/anatawa12/jasm/parser/TokenType$Char;
   areturn
L_0004:
.end method

.method public getV_float ()Lcom/anatawa12/jasm/parser/TokenType$Char;
   .annotation invisible org/jetbrains/annotations/NotNull
   .end annotation
   .limit stack 1
   .limit local 1
L_0000:
   .line 1050
   .var 0 is this Lcom/anatawa12/jasm/parser/Parser$Companion; from L_0000 to L_0004
   invokestatic com/anatawa12/jasm/parser/Parser/access$getV_float$cp ()Lcom/anatawa12/jasm/parser/TokenType$Char;
   areturn
L_0004:
.end method

.method public getV_int ()Lcom/anatawa12/jasm/parser/TokenType$Char;
   .annotation invisible org/jetbrains/annotations/NotNull
   .end annotation
   .limit stack 1
   .limit local 1
L_0000:
   .line 1051
   .var 0 is this Lcom/anatawa12/jasm/parser/Parser$Companion; from L_0000 to L_0004
   invokestatic com/anatawa12/jasm/parser/Parser/access$getV_int$cp ()Lcom/anatawa12/jasm/parser/TokenType$Char;
   areturn
L_0004:
.end method

.method public getV_long ()Lcom/anatawa12/jasm/parser/TokenType$Char;
   .annotation invisible org/jetbrains/annotations/NotNull
   .end annotation
   .limit stack 1
   .limit local 1
L_0000:
   .line 1052
   .var 0 is this Lcom/anatawa12/jasm/parser/Parser$Companion; from L_0000 to L_0004
   invokestatic com/anatawa12/jasm/parser/Parser/access$getV_long$cp ()Lcom/anatawa12/jasm/parser/TokenType$Char;
   areturn
L_0004:
.end method

.method public getV_short ()Lcom/anatawa12/jasm/parser/TokenType$Char;
   .annotation invisible org/jetbrains/annotations/NotNull
   .end annotation
   .limit stack 1
   .limit local 1
L_0000:
   .line 1053
   .var 0 is this Lcom/anatawa12/jasm/parser/Parser$Companion; from L_0000 to L_0004
   invokestatic com/anatawa12/jasm/parser/Parser/access$getV_short$cp ()Lcom/anatawa12/jasm/parser/TokenType$Char;
   areturn
L_0004:
.end method

.method public getV_boolean ()Lcom/anatawa12/jasm/parser/TokenType$Char;
   .annotation invisible org/jetbrains/annotations/NotNull
   .end annotation
   .limit stack 1
   .limit local 1
L_0000:
   .line 1054
   .var 0 is this Lcom/anatawa12/jasm/parser/Parser$Companion; from L_0000 to L_0004
   invokestatic com/anatawa12/jasm/parser/Parser/access$getV_boolean$cp ()Lcom/anatawa12/jasm/parser/TokenType$Char;
   areturn
L_0004:
.end method

.method public getV_String ()Lcom/anatawa12/jasm/parser/TokenType$Char;
   .annotation invisible org/jetbrains/annotations/NotNull
   .end annotation
   .limit stack 1
   .limit local 1
L_0000:
   .line 1055
   .var 0 is this Lcom/anatawa12/jasm/parser/Parser$Companion; from L_0000 to L_0004
   invokestatic com/anatawa12/jasm/parser/Parser/access$getV_String$cp ()Lcom/anatawa12/jasm/parser/TokenType$Char;
   areturn
L_0004:
.end method

.method public getV_Enum ()Lcom/anatawa12/jasm/parser/TokenType$Char;
   .annotation invisible org/jetbrains/annotations/NotNull
   .end annotation
   .limit stack 1
   .limit local 1
L_0000:
   .line 1056
   .var 0 is this Lcom/anatawa12/jasm/parser/Parser$Companion; from L_0000 to L_0004
   invokestatic com/anatawa12/jasm/parser/Parser/access$getV_Enum$cp ()Lcom/anatawa12/jasm/parser/TokenType$Char;
   areturn
L_0004:
.end method

.method public getV_Class ()Lcom/anatawa12/jasm/parser/TokenType$Char;
   .annotation invisible org/jetbrains/annotations/NotNull
   .end annotation
   .limit stack 1
   .limit local 1
L_0000:
   .line 1057
   .var 0 is this Lcom/anatawa12/jasm/parser/Parser$Companion; from L_0000 to L_0004
   invokestatic com/anatawa12/jasm/parser/Parser/access$getV_Class$cp ()Lcom/anatawa12/jasm/parser/TokenType$Char;
   areturn
L_0004:
.end method

.method public getV_Annotation ()Lcom/anatawa12/jasm/parser/TokenType$Char;
   .annotation invisible org/jetbrains/annotations/NotNull
   .end annotation
   .limit stack 1
   .limit local 1
L_0000:
   .line 1058
   .var 0 is this Lcom/anatawa12/jasm/parser/Parser$Companion; from L_0000 to L_0004
   invokestatic com/anatawa12/jasm/parser/Parser/access$getV_Annotation$cp ()Lcom/anatawa12/jasm/parser/TokenType$Char;
   areturn
L_0004:
.end method

.method public getV_Array ()Lcom/anatawa12/jasm/parser/TokenType$Char;
   .annotation invisible org/jetbrains/annotations/NotNull
   .end annotation
   .limit stack 1
   .limit local 1
L_0000:
   .line 1059
   .var 0 is this Lcom/anatawa12/jasm/parser/Parser$Companion; from L_0000 to L_0004
   invokestatic com/anatawa12/jasm/parser/Parser/access$getV_Array$cp ()Lcom/anatawa12/jasm/parser/TokenType$Char;
   areturn
L_0004:
.end method

.method private <init> ()V
   .limit stack 1
   .limit local 1
L_0000:
   .line 937
   .var 0 is this Lcom/anatawa12/jasm/parser/Parser$Companion; from L_0000 to L_0005
   aload 0
   invokespecial java/lang/Object/<init> ()V
   return
L_0005:
.end method

.method public <init> (Lkotlin/jvm/internal/DefaultConstructorMarker;)V
   .limit stack 1
   .limit local 2
L_0000:
   .line 937
   .var 0 is this Lcom/anatawa12/jasm/parser/Parser$Companion; from L_0000 to L_0005
   .var 1 is $constructor_marker Lkotlin/jvm/internal/DefaultConstructorMarker; from L_0000 to L_0005
   aload 0
   invokespecial com/anatawa12/jasm/parser/Parser$Companion/<init> ()V
   return
L_0005:
.end method

