.bytecode 52.0
.source "TokenType.kt"
.class public com/anatawa12/jasm/parser/TokenType$OwnerAndName
.super com/anatawa12/jasm/parser/TokenType
.signature "Lcom/anatawa12/jasm/parser/TokenType<Lkotlin/Pair<+Ljava/lang/String;+Ljava/lang/String;>;>;"
.inner public com/anatawa12/jasm/parser/TokenType$OwnerAndName inner OwnerAndName outer com/anatawa12/jasm/parser/TokenType

.annotation visible kotlin/Metadata
    mv [ = .annotation array
        I = 1
        I = 1
        I = 16
    .end annotation
    bv [ = .annotation array
        I = 1
        I = 0
        I = 3
    .end annotation
    k I = 1
    d1 [ = .annotation array
        s = "\u0000\u001c\n\u0002\u0018\u0002\n\u0002\u0018\u0002\n\u0002\u0018\u0002\n\u0002\u0010\u000e\n\u0002\b\u0003\n\u0002\u0018\u0002\n\u0002\b\u0002\bÆ\u0002\u0018\u00002\u0014\u0012\u0010\u0012\u000e\u0012\u0004\u0012\u00020\u0003\u0012\u0004\u0012\u00020\u00030\u00020\u0001B\u0007\b\u0002¢\u0006\u0002\u0010\u0004J\u001e\u0010\u0005\u001a\u0010\u0012\u0004\u0012\u00020\u0003\u0012\u0004\u0012\u00020\u0003\u0018\u00010\u00022\u0006\u0010\u0006\u001a\u00020\u0007H\u0016J\b\u0010\b\u001a\u00020\u0003H\u0016¨\u0006\t"
    .end annotation
    d2 [ = .annotation array
        s = "Lcom/anatawa12/jasm/parser/TokenType\$OwnerAndName;"
        s = "Lcom/anatawa12/jasm/parser/TokenType;"
        s = "Lkotlin/Pair;"
        s = ""
        s = "()V"
        s = "accept"
        s = "visitor"
        s = "Lcom/anatawa12/jasm/parser/ITokenVisitorNullable;"
        s = "toString"
        s = "jasm"
    .end annotation
.end annotation

.method public accept (Lcom/anatawa12/jasm/parser/ITokenVisitorNullable;)Lkotlin/Pair;
    .signature "(Lcom/anatawa12/jasm/parser/ITokenVisitorNullable;)Lkotlin/Pair<Ljava/lang/String;Ljava/lang/String;>;"
    .annotation invisible org/jetbrains/annotations/Nullable
    .end annotation
    .annotation invisiblepararm 0 org/jetbrains/annotations/NotNull
    .end annotation
    .limit stack 2
    .limit local 2
L_0000:
    .var 0 is this Lcom/anatawa12/jasm/parser/TokenType$OwnerAndName; from L_0000 to L_000a
    .var 1 is visitor Lcom/anatawa12/jasm/parser/ITokenVisitorNullable; from L_0000 to L_000a
    aload 1
    ldc "visitor"
    invokestatic kotlin/jvm/internal/Intrinsics/checkParameterIsNotNull (Ljava/lang/Object;Ljava/lang/String;)V
L_0004:
    .line 49
    aload 1
    aload 0
    invokeinterface com/anatawa12/jasm/parser/ITokenVisitorNullable/visitOwnerAndName (Lcom/anatawa12/jasm/parser/TokenType$OwnerAndName;)Lkotlin/Pair;
    areturn
L_000a:
.end method

.method public accept (Lcom/anatawa12/jasm/parser/ITokenVisitorNullable;)Ljava/lang/Object;
    .limit stack 2
    .limit local 2
L_0000:
    .line 48
    aload 0
    aload 1
    invokevirtual com/anatawa12/jasm/parser/TokenType$OwnerAndName/accept (Lcom/anatawa12/jasm/parser/ITokenVisitorNullable;)Lkotlin/Pair;
    areturn
.end method

.method public toString ()Ljava/lang/String;
    .annotation invisible org/jetbrains/annotations/NotNull
    .end annotation
    .limit stack 1
    .limit local 1
L_0000:
    .line 50
    .var 0 is this Lcom/anatawa12/jasm/parser/TokenType$OwnerAndName; from L_0000 to L_0004
    ldc "owner and name"
    areturn
L_0004:
.end method

.method private <init> ()V
    .limit stack 2
    .limit local 1
L_0000:
    .line 48
    .var 0 is this Lcom/anatawa12/jasm/parser/TokenType$OwnerAndName; from L_0000 to L_0008
    aload 0
    aconst_null
L_0004:
    .line 48
    invokespecial com/anatawa12/jasm/parser/TokenType/<init> (Lkotlin/jvm/internal/DefaultConstructorMarker;)V
    return
L_0008:
.end method

.method static <clinit> ()V
    .limit stack 2
    .limit local 1
L_0000:
    .line 48
    new com/anatawa12/jasm/parser/TokenType$OwnerAndName
    dup
    invokespecial com/anatawa12/jasm/parser/TokenType$OwnerAndName/<init> ()V
    astore 0
    aload 0
    putstatic com/anatawa12/jasm/parser/TokenType$OwnerAndName/INSTANCE Lcom/anatawa12/jasm/parser/TokenType$OwnerAndName;
    return
.end method

.field public INSTANCE Lcom/anatawa12/jasm/parser/TokenType$OwnerAndName;
.end field

